Workbook

Sheet design.old
C3: Construct | D3: Compliance Progress and Breach Prevention | H3: Organizational and Industry Dynamics | I3: Data and Breach Analysis
C4: Research Question | D4: 1. What differences exist in compliance status and breach prevention measures between companies that experienced breaches before and after achieving compliance? | H4: 2. How do breach occurrences and data classification vary across industries, company statuses, and acquisition statuses? | I4: 3. How do the types of data compromised and the root causes of breach differ between compliant and non-compliant companies?
C5: Hypothesis | D5: H01. There is no significant difference in compliance status or breach prevention measures between companies that experienced breaches before and after achieving compliance. | H5: H02. Breach occurrences and data classifications do not significantly differ across industries, company statuses, or acquisition statuses. | I5: H03. There is no significant difference in the types of data compromised or the root causes of breaches between compliant and non-compliant companies.
D6: Ha1. There is a significant difference in compliance status or breach prevention measures between companies that experienced breaches before and after achieving compliance. | H6: Ha2. Breach occurrences and data classifications significantly differ across industries, company statuses, and acquisition statuses. | I6: Ha3. There is a significant difference in the types of data compromised and the root causes of breaches between compliant and non-compliant companies.
C7: Variable | D7: Independent Variable: compliance status and breach prevention measures Dependent Variable: differences in company outcomes related to breaches before and after achieving compliance | H7: Independent Variable: industries, company statuses and acquisition statuses Dependent Variable: breach occurrences and classification of data | I7: Independent Variable: compliance status (compliant vs non-compliant companies) Dependent Variable: types of data compromised and root causes of breaches
C8: Test | D8: Paired T-test (Inferential); Mean, median, standard deviation, frequency distributions (Descriptive) | H8: Paired T-test (Inferential); Mean, median, standard deviation, frequency distributions (Descriptive) | I8: Paired T-test (Inferential); Mean, median, standard deviation, frequency distributions (Descriptive)
B9: Instrument | D9: Category
B10: Survey Question | C10: Likert Scale | D10: Compliance Status (adherence to industry standards and regulations) | E10: Company Status (public/private) | F10: Industry Status (type of industry) | G10: Acquisition Status (acquired/non-acquired) | H10: Data Classification (sensitive data types) | I10: Root Cause Analysis (cause of breach) | J10: Training and Enforcement (compliance training for employees)
A11: 1 | B11: The company's adherence to all relevant industry standards and regulations. | C11: 0 - Not Effective, 5 - Most Effective | D11: ✓
A12: 2 | B12: The company's public or private status impacts its approach to compliance and data protection. | C12: 0 - Not Effective, 5 - Most Effective | E12: ✓
A13: 3 | B13: The company's industry type influences its compliance requirements and challenges. | C13: 0 - Not Effective, 5 - Most Effective | F13: ✓
A14: 4 | B14: The company's acquisition status affects its compliance practices (having either been acquired or not acquiired by another entity). | C14: 0 - Not Effective, 5 - Most Effective | G14: ✓
A15: 5 | B15: The company's data classification system effectiveness in identifying and protecting sensitive information. | C15: 0 - Not Effective, 5 - Most Effective | H15: ✓
A16: 6 | B16: When a data breach occurs, the company's root cause analysis thoroughness in identifying and improving compliance failures. | C16: 0 - Not Effective, 5 - Most Effective | I16: ✓
A17: 7 | B17: The company's policies and procedures effectiveness in ensuring third-party vendors comply with relevant regulations and standards. | C17: 0 - Not Effective, 5 - Most Effective | J17: ✓
B19: Theoretical Frameworks
B20: Institutional Theory: Examines how regulatory requirements, industry standards, and societal expectations shape companies' compliance status and breach risk.
B21: Transaction Cost Economics (TCE) Theory: Analyzes the costs and benefits of cybersecurity strategies and compliance measures, and their impact on breach risk.
B22: Expected Outcomes
B23: Understanding differences in compliance, public status, and acquisition status in relation to breaches.

Sheet INF STATS
C4: GDPR Before and After
C40: Acquisitions Before and After
C72: Public Before and After
C106: data classification
C202: Root Cause and GDPR

Sheet DIFF STATS
BR3: Data Classification (Sensitive)
B4: Sample Set | E4: Breaches | I4: Causes | M4: Vulnerabilities | Q4: Breaches and Acquisitions | V4: Descriptive Stats | AB4: Breaches and Going Public | AG4: Descriptive Stats | AM4: Industry | AQ4: Breaches and Compliance | BB4: Compliance | BC4: Count of Companies | BD4: % of Companies | BE4: PII | BF4: PII % | BG4: PHI | BH4: PHI % | BI4: PCI | BJ4: PCI % | BR4: PII | BS4: 112 | BT4: =BS4/SUM($BS$4:$BS$6) -> 0.68292683
B5: Name | C5: (All) | E5: Row Labels | F5: Count of Name | I5: Row Labels | J5: Count of Industry | M5: Row Labels | N5: Count of Industry | Q5: Row Labels | R5: Count of B2A Years | S5: % | T5: AVG Yrs | V5: Breach before Acquisition | Y5: Breach after Acquisition | AB5: Row Labels | AC5: Count of B2P Years | AD5: % | AE5: AVG Yrs | AG5: Breach before going Public | AJ5: Breach after going Public | AM5: Row Labels | AN5: Count of Industry | AQ5: Row Labels | AR5: Count of GDPR | AU5: Breach before GDPR | AX5: Breach after GDPR | BB5: GDPR | BC5: 179 | BD5: =BC5/GETPIVOTDATA("Name",$B$7) -> 0.88613861 | BE5: =COUNTIFS(SAMPLES!$R$3:$R$204,"yes",SAMPLES!AB3:AB204,"yes") -> 97 | BF5: =BE5/SUM($BE$5:$BE$13) -> 0.58787879 | BG5: =COUNTIFS(SAMPLES!$R$3:$R$204,"yes",SAMPLES!AF3:AF204,"yes") -> 22 | BH5: =BG5/SUM($BG$5:$BG$13) -> 0.42307692 | BI5: =COUNTIFS(SAMPLES!$R$3:$R$204,"yes",SAMPLES!AD3:AD204,"yes") -> 17 | BJ5: =BI5/SUM($BI$5:$BI$13) -> 0.53125 | BR5: PHI | BS5: 32 | BT5: =BS5/SUM($BS$4:$BS$6) -> 0.19512195
E6: 2017 | F6: 11 | I6: System Vulnerability Exploit | J6: 27 | K6: =GETPIVOTDATA("Industry",$I$5,"How the Breach Happened","System Vulnerability Exploit")/GETPIVOTDATA("Industry",$I$5) -> 0.13366337 | M6: System Vulnerability Exploit | N6: 27 | Q6: after | R6: 27 | S6: =GETPIVOTDATA("B2A Years",$Q$5,"B2A","after")/GETPIVOTDATA("B2A Years",$Q$5) -> 0.5625 | T6: =AVERAGEIF(SAMPLES!AP3:AP204,"after",SAMPLES!AQ3:AQ204) -> 7.962963 | AB6: after | AC6: 78 | AD6: =GETPIVOTDATA("B2P Years",$AB$5,"B2P","after")/GETPIVOTDATA("B2P Years",$AB$5) -> 0.93975904 | AE6: =AVERAGEIF(SAMPLES!AR3:AR204,"after",SAMPLES!AS3:AS204) -> 24.5 | AM6: Technology | AN6: 44 | AO6: =GETPIVOTDATA("Industry",$AM$5,"Industry","Technology")/GETPIVOTDATA("Industry",$AM$5) -> 0.21782178 | AQ6: yes | AR6: 179 | BB6: HIPAA | BC6: 34 | BD6: =BC6/GETPIVOTDATA("Name",$B$7) -> 0.16831683 | BE6: =COUNTIFS(SAMPLES!$W$3:$W$204,"yes",SAMPLES!AB3:AB204,"yes") -> 16 | BF6: =BE6/SUM($BE$5:$BE$13) -> 0.096969697 | BG6: =COUNTIFS(SAMPLES!$W$3:$W$204,"yes",SAMPLES!AF3:AF204,"yes") -> 27 | BH6: =BG6/SUM($BG$5:$BG$13) -> 0.51923077 | BI6: =COUNTIFS(SAMPLES!$W$3:$W$204,"yes",SAMPLES!AD3:AD204,"yes") -> 0 | BJ6: =BI6/SUM($BI$5:$BI$13) -> 0 | BR6: PCI | BS6: 20 | BT6: =BS6/SUM($BS$4:$BS$6) -> 0.12195122
B7: Count of Name | E7: 2018 | F7: 16 | I7: Ransomware | J7: 22 | K7: =GETPIVOTDATA("Industry",$I$5,"How the Breach Happened","Ransomware")/GETPIVOTDATA("Industry",$I$5) -> 0.10891089 | M7: API Vulnerability Exploit | N7: 5 | Q7: before | R7: 14 | S7: =GETPIVOTDATA("B2A Years",$Q$5,"B2A","before")/GETPIVOTDATA("B2A Years",$Q$5) -> 0.29166667 | T7: =AVERAGEIF(SAMPLES!AP3:AP204,"before",SAMPLES!AQ3:AQ204) -> 1.2142857 | V7: Mean | W7: 1.2142857 | Y7: Mean | Z7: 7.962963 | AB7: before | AC7: 4 | AD7: =GETPIVOTDATA("B2P Years",$AB$5,"B2P","before")/GETPIVOTDATA("B2P Years",$AB$5) -> 0.048192771 | AE7: =AVERAGEIF(SAMPLES!AR3:AR204,"before",SAMPLES!AS3:AS204) -> 1.5 | AG7: Mean | AH7: 1.5 | AJ7: Mean | AK7: 24.5 | AM7: Healthcare | AN7: 27 | AO7: =GETPIVOTDATA("Industry",$AM$5,"Industry","Healthcare")/GETPIVOTDATA("Industry",$AM$5) -> 0.13366337 | AQ7: Grand Total | AR7: 179 | AU7: Mean | AV7: 0.03960396 | AX7: Mean | AY7: 0.84653465 | BB7: PCI | BC7: 23 | BD7: =BC7/GETPIVOTDATA("Name",$B$7) -> 0.11386139 | BE7: =COUNTIFS(SAMPLES!$T$3:$T$204,"yes",SAMPLES!AB3:AB204,"yes") -> 12 | BF7: =BE7/SUM($BE$5:$BE$13) -> 0.072727273 | BG7: =COUNTIFS(SAMPLES!$T$3:$T$204,"yes",SAMPLES!AF3:AF204,"yes") -> 2 | BH7: =BG7/SUM($BG$5:$BG$13) -> 0.038461538 | BI7: =COUNTIFS(SAMPLES!$T$3:$T$204,"yes",SAMPLES!AD3:AD204,"yes") -> 8 | BJ7: =BI7/SUM($BI$5:$BI$13) -> 0.25
B8: 202 | E8: 2019 | F8: 29 | I8: Phishing | J8: 19 | K8: =GETPIVOTDATA("Industry",$I$5,"How the Breach Happened","Phishing")/GETPIVOTDATA("Industry",$I$5) -> 0.094059406 | M8: Software Vulnerability Exploit | N8: 4 | Q8: same year | R8: 7 | S8: =GETPIVOTDATA("B2A Years",$Q$5,"B2A","same year")/GETPIVOTDATA("B2A Years",$Q$5) -> 0.14583333 | T8: =AVERAGEIF(SAMPLES!AP3:AP204,"same year",SAMPLES!AQ3:AQ204) -> 0 | V8: Standard Error | W8: 0.15472668 | Y8: Standard Error | Z8: 1.4622325 | AB8: same year | AC8: 1 | AD8: =GETPIVOTDATA("B2P Years",$AB$5,"B2P","same year")/GETPIVOTDATA("B2P Years",$AB$5) -> 0.012048193 | AE8: =AVERAGEIF(SAMPLES!AR3:AR204,"same year",SAMPLES!AS3:AS204) -> 0 | AG8: Standard Error | AH8: 0.28867513 | AJ8: Standard Error | AK8: 2.5139471 | AM8: Social Media | AN8: 23 | AO8: =GETPIVOTDATA("Industry",$AM$5,"Industry","Social Media")/GETPIVOTDATA("Industry",$AM$5) -> 0.11386139 | AU8: Standard Error | AV8: 0.013756136 | AX8: Standard Error | AY8: 0.025423158 | BB8: CCPA | BC8: 22 | BD8: =BC8/GETPIVOTDATA("Name",$B$7) -> 0.10891089 | BE8: =COUNTIFS(SAMPLES!$Y$3:$Y$204,"yes",SAMPLES!AB3:AB204,"yes") -> 16 | BF8: =BE8/SUM($BE$5:$BE$13) -> 0.096969697 | BG8: =COUNTIFS(SAMPLES!$Y$3:$Y$204,"yes",SAMPLES!AF3:AF204,"yes") -> 0 | BH8: =BG8/SUM($BG$5:$BG$13) -> 0 | BI8: =COUNTIFS(SAMPLES!$Y$3:$Y$204,"yes",SAMPLES!AD3:AD204,"yes") -> 2 | BJ8: =BI8/SUM($BI$5:$BI$13) -> 0.0625 | BR8: Data Classification (Other)
E9: 2020 | F9: 52 | I9: Unsecured database | J9: 18 | K9: =GETPIVOTDATA("Industry",$I$5,"How the Breach Happened","Misconfigured Database")/GETPIVOTDATA("Industry",$I$5) -> 0.089108911 | M9: Database Vulnerability Exploit | N9: 3 | Q9: Grand Total | R9: 48 | V9: Median | W9: 1 | Y9: Median | Z9: 5 | AB9: Grand Total | AC9: 83 | AG9: Median | AH9: 1.5 | AJ9: Median | AK9: 19 | AM9: Telecommunications | AN9: 13 | AO9: =GETPIVOTDATA("Industry",$AM$5,"Industry","Telecommunications")/GETPIVOTDATA("Industry",$AM$5) -> 0.064356436 | AU9: Median | AV9: 0 | AX9: Median | AY9: 1 | BB9: ISO | BC9: 19 | BD9: =BC9/GETPIVOTDATA("Name",$B$7) -> 0.094059406 | BE9: =COUNTIFS(SAMPLES!$S$3:$S$204,"yes",SAMPLES!AB3:AB204,"yes") -> 10 | BF9: =BE9/SUM($BE$5:$BE$13) -> 0.060606061 | BG9: =COUNTIFS(SAMPLES!$S$3:$S$204,"yes",SAMPLES!AF3:AF204,"yes") -> 0 | BH9: =BG9/SUM($BG$5:$BG$13) -> 0 | BI9: =COUNTIFS(SAMPLES!$S$3:$S$204,"yes",SAMPLES!AD3:AD204,"yes") -> 1 | BJ9: =BI9/SUM($BI$5:$BI$13) -> 0.03125 | BR9: Company Data | BS9: 47 | BT9: =BS9/SUM($BS$9:$BS$10) -> 0.4159292
E10: 2021 | F10: 45 | I10: Misconfigured Database | J10: 18 | K10: =GETPIVOTDATA("Industry",$I$5,"How the Breach Happened","Unsecured database")/GETPIVOTDATA("Industry",$I$5) -> 0.089108911 | M10: Network Vulnerability Exploit | N10: 2 | V10: Mode | W10: 1 | Y10: Mode | Z10: 2 | AG10: Mode | AH10: 1 | AJ10: Mode | AK10: 7 | AM10: Retail | AN10: 12 | AO10: =GETPIVOTDATA("Industry",$AM$5,"Industry","Retail")/GETPIVOTDATA("Industry",$AM$5) -> 0.059405941 | AQ10: Row Labels | AR10: Count of B2GDPR | AS10: % | AT10: AVG Yrs | AU10: Mode | AV10: 0 | AX10: Mode | AY10: 1 | BB10: SOC | BC10: 10 | BD10: =BC10/GETPIVOTDATA("Name",$B$7) -> 0.04950495 | BE10: =COUNTIFS(SAMPLES!$X$3:$X$204,"yes",SAMPLES!AB3:AB204,"yes") -> 6 | BF10: =BE10/SUM($BE$5:$BE$13) -> 0.036363636 | BG10: =COUNTIFS(SAMPLES!$X$3:$X$204,"yes",SAMPLES!AF3:AF204,"yes") -> 0 | BH10: =BG10/SUM($BG$5:$BG$13) -> 0 | BI10: =COUNTIFS(SAMPLES!$X$3:$X$204,"yes",SAMPLES!AD3:AD204,"yes") -> 0 | BJ10: =BI10/SUM($BI$5:$BI$13) -> 0 | BR10: Technical Data | BS10: 66 | BT10: =BS10/SUM($BS$9:$BS$10) -> 0.5840708
E11: 2022 | F11: 25 | I11: Third Party | J11: 12 | K11: =GETPIVOTDATA("Industry",$I$5,"How the Breach Happened","Third Party")/GETPIVOTDATA("Industry",$I$5) -> 0.059405941 | M11: Software Vulnerability Exploit (state sponsored) | N11: 1 | V11: Standard Deviation | W11: 0.57893422 | Y11: Standard Deviation | Z11: 7.5979829 | AG11: Standard Deviation | AH11: 0.57735027 | AJ11: Standard Deviation | AK11: 22.20258 | AM11: Entertainment | AN11: 10 | AO11: =GETPIVOTDATA("Industry",$AM$5,"Industry","Entertainment")/GETPIVOTDATA("Industry",$AM$5) -> 0.04950495 | AQ11: after | AR11: 155 | AS11: =GETPIVOTDATA("B2GDPR",$AQ$10,"B2GDPR","after")/GETPIVOTDATA("B2GDPR",$AQ$10) -> 0.86592179 | AT11: =AVERAGEIF(SAMPLES!AT3:AT204,"after",SAMPLES!AU3:AU204) -> 2.6580645 | AU11: Standard Deviation | AV11: 0.19551143 | AX11: Standard Deviation | AY11: 0.36133097 | BB11: SOX | BC11: 6 | BD11: =BC11/GETPIVOTDATA("Name",$B$7) -> 0.02970297 | BE11: =COUNTIFS(SAMPLES!$U$3:$U$204,"yes",SAMPLES!AB3:AB204,"yes") -> 3 | BF11: =BE11/SUM($BE$5:$BE$13) -> 0.018181818 | BG11: =COUNTIFS(SAMPLES!$U$3:$U$204,"yes",SAMPLES!AF3:AF204,"yes") -> 1 | BH11: =BG11/SUM($BG$5:$BG$13) -> 0.019230769 | BI11: =COUNTIFS(SAMPLES!$U$3:$U$204,"yes",SAMPLES!AD3:AD204,"yes") -> 1 | BJ11: =BI11/SUM($BI$5:$BI$13) -> 0.03125
E12: 2023 | F12: 17 | I12: Data Scraping | J12: 11 | K12: =GETPIVOTDATA("Industry",$I$5,"How the Breach Happened","Data Scraping")/GETPIVOTDATA("Industry",$I$5) -> 0.054455446 | M12: Vulnerability in website and mobile app | N12: 1 | V12: Sample Variance | W12: 0.33516484 | Y12: Sample Variance | Z12: 57.729345 | AG12: Sample Variance | AH12: 0.33333333 | AJ12: Sample Variance | AK12: 492.95455 | AM12: Financial Services | AN12: 10 | AO12: =GETPIVOTDATA("Industry",$AM$5,"Industry","Financial Services")/GETPIVOTDATA("Industry",$AM$5) -> 0.04950495 | AQ12: before | AR12: 8 | AS12: =GETPIVOTDATA("B2GDPR",$AQ$10,"B2GDPR","before")/GETPIVOTDATA("B2GDPR",$AQ$10) -> 0.044692737 | AT12: =AVERAGEIF(SAMPLES!AT3:AT204,"before",SAMPLES!AU3:AU204) -> 1 | AU12: Sample Variance | AV12: 0.038224718 | AX12: Sample Variance | AY12: 0.13056007 | BB12: GLBA | BC12: 5 | BD12: =BC12/GETPIVOTDATA("Name",$B$7) -> 0.024752475 | BE12: =COUNTIFS(SAMPLES!$V$3:$V$204,"yes",SAMPLES!AB3:AB204,"yes") -> 3 | BF12: =BE12/SUM($BE$5:$BE$13) -> 0.018181818 | BG12: =COUNTIFS(SAMPLES!$V$3:$V$204,"yes",SAMPLES!AF3:AF204,"yes") -> 0 | BH12: =BG12/SUM($BG$5:$BG$13) -> 0 | BI12: =COUNTIFS(SAMPLES!$V$3:$V$204,"yes",SAMPLES!AD3:AD204,"yes") -> 3 | BJ12: =BI12/SUM($BI$5:$BI$13) -> 0.09375
E13: 2024 | F13: 7 | I13: Credential Stuffing | J13: 8 | K13: =GETPIVOTDATA("Industry",$I$5,"How the Breach Happened","Credential Stuffing")/GETPIVOTDATA("Industry",$I$5) -> 0.03960396 | M13: Cloud Storage Vulnerability Exploit | N13: 1 | V13: Kurtosis | W13: 7.6791185 | Y13: Kurtosis | Z13: -0.1384306 | AG13: Kurtosis | AH13: -6 | AJ13: Kurtosis | AK13: 5.0132951 | AM13: Insurance | AN13: 7 | AO13: =GETPIVOTDATA("Industry",$AM$5,"Industry","Insurance")/GETPIVOTDATA("Industry",$AM$5) -> 0.034653465 | AQ13: same year | AR13: 16 | AS13: =GETPIVOTDATA("B2GDPR",$AQ$10,"B2GDPR","same year")/GETPIVOTDATA("B2GDPR",$AQ$10) -> 0.089385475 | AT13: =AVERAGEIF(SAMPLES!AT3:AT204,"same year",SAMPLES!AU3:AU204) -> 0 | AU13: Kurtosis | AV13: 20.832898 | AX13: Kurtosis | AY13: 1.7704937 | BB13: RAMP | BC13: 3 | BD13: =BC13/GETPIVOTDATA("Name",$B$7) -> 0.014851485 | BE13: =COUNTIFS(SAMPLES!$Z$3:$Z$204,"yes",SAMPLES!AB3:AB204,"yes") -> 2 | BF13: =BE13/SUM($BE$5:$BE$13) -> 0.012121212 | BG13: =COUNTIFS(SAMPLES!$Z$3:$Z$204,"yes",SAMPLES!AF3:AF204,"yes") -> 0 | BH13: =BG13/SUM($BG$5:$BG$13) -> 0 | BI13: =COUNTIFS(SAMPLES!$Z$3:$Z$204,"yes",SAMPLES!AD3:AD204,"yes") -> 0 | BJ13: =BI13/SUM($BI$5:$BI$13) -> 0
E14: Grand Total | F14: 202 | I14: Unauthorized Access | J14: 7 | K14: =GETPIVOTDATA("Industry",$I$5,"How the Breach Happened","Unauthorized Access")/GETPIVOTDATA("Industry",$I$5) -> 0.034653465 | M14: Web Application Vulnerability Exploit | N14: 1 | V14: Skewness | W14: 2.8033423 | Y14: Skewness | Z14: 1.1714325 | AG14: Skewness | AH14: 0 | AJ14: Skewness | AK14: 1.7841799 | AM14: Marketing | AN14: 6 | AO14: =GETPIVOTDATA("Industry",$AM$5,"Industry","Marketing")/GETPIVOTDATA("Industry",$AM$5) -> 0.02970297 | AQ14: Grand Total | AR14: 179 | AU14: Skewness | AV14: 4.7567552 | AX14: Skewness | AY14: -1.937282
I15: API Vulnerability Exploit | J15: 5 | K15: =GETPIVOTDATA("Industry",$I$5,"How the Breach Happened","API Vulnerability Exploit")/GETPIVOTDATA("Industry",$I$5) -> 0.024752475 | M15: Vulnerability in legacy file transfer system | N15: 1 | Q15: Breaches and Acquisitions | V15: Range | W15: 2 | Y15: Range | Z15: 24 | AG15: Range | AH15: 1 | AJ15: Range | AK15: 127 | AM15: Hospitality | AN15: 5 | AO15: =GETPIVOTDATA("Industry",$AM$5,"Industry","Hospitality")/GETPIVOTDATA("Industry",$AM$5) -> 0.024752475 | AU15: Range | AV15: 1 | AX15: Range | AY15: 1
I16: Unspecified | J16: 5 | M16: Grand Total | N16: 46 | O16: =GETPIVOTDATA("Industry",$M$5)/GETPIVOTDATA("Industry",$I$5) -> 0.22772277 | Q16: Row Labels | R16: Count of Acquired | V16: Minimum | W16: 1 | Y16: Minimum | Z16: 1 | AB16: Row Labels | AC16: Count of Is Public | AG16: Minimum | AH16: 1 | AJ16: Minimum | AK16: 1 | AM16: Financial Technology (FinTech) | AN16: 5 | AU16: Minimum | AV16: 0 | AX16: Minimum | AY16: 0
I17: Malware | J17: 4 | Q17: No | R17: 154 | S17: =GETPIVOTDATA("Acquired",$Q$16,"Acquired","No")/GETPIVOTDATA("Acquired",$Q$16) -> 0.76237624 | V17: Maximum | W17: 3 | Y17: Maximum | Z17: 25 | AB17: No | AC17: 119 | AD17: =GETPIVOTDATA("Is Public",$AB$16,"Is Public","No")/GETPIVOTDATA("Is Public",$AB$16) -> 0.58910891 | AG17: Maximum | AH17: 2 | AJ17: Maximum | AK17: 128 | AM17: Cybersecurity | AN17: 4 | AU17: Maximum | AV17: 1 | AX17: Maximum | AY17: 1
I18: Supply Chain Attack | J18: 4 | Q18: Yes | R18: 48 | S18: =GETPIVOTDATA("Acquired",$Q$16,"Acquired","Yes")/GETPIVOTDATA("Acquired",$Q$16) -> 0.23762376 | V18: Sum | W18: 17 | Y18: Sum | Z18: 215 | AB18: Yes | AC18: 83 | AD18: =GETPIVOTDATA("Is Public",$AB$16,"Is Public","Yes")/GETPIVOTDATA("Is Public",$AB$16) -> 0.41089109 | AG18: Sum | AH18: 6 | AJ18: Sum | AK18: 1911 | AM18: Airlines | AN18: 4 | AU18: Sum | AV18: 8 | AX18: Sum | AY18: 171
I19: Social Engineering | J19: 4 | Q19: Grand Total | R19: 202 | V19: Count | W19: 14 | Y19: Count | Z19: 27 | AB19: Grand Total | AC19: 202 | AG19: Count | AH19: 4 | AJ19: Count | AK19: 78 | AM19: Electronics | AN19: 4 | AU19: Count | AV19: 202 | AX19: Count | AY19: 202
B20: Row Labels | I20: Software Vulnerability Exploit | J20: 4 | M20: root cause | AM20: Automotive | AN20: 3
B21: 179 | I21: Database Vulnerability Exploit | J21: 3 | AM21: Government | AN21: 3
B22: yes | I22: Unsecured AWS S3 bucket | J22: 3 | M22: Mean | N22: 5.4594595 | Q22: Avg Yrs Before | R22: Avg Yrs During | S22: Avg Yrs After | AB22: Avg Yrs Before | AC22: Avg Yrs During | AD22: Avg yrs After | AM22: Transportation | AN22: 3
B23: (blank) | I23: Misconfigured Cloud Storage | J23: 3 | M23: Standard Error | N23: 1.1214497 | Q23: =AVERAGEIFS(SAMPLES!AQ3:AQ204,SAMPLES!AP3:AP204,"before") -> 1.2142857 | R23: =AVERAGEIFS(SAMPLES!AQ3:AQ204,SAMPLES!AP3:AP204,"same year") -> 0 | S23: =AVERAGEIFS(SAMPLES!AQ3:AQ204,SAMPLES!AP3:AP204,"after") -> 7.962963 | AB23: =AVERAGEIFS(SAMPLES!AS3:AS204,SAMPLES!AR3:AR204,"before") -> 1.5 | AC23: =AVERAGEIFS(SAMPLES!AS3:AS204,SAMPLES!AR3:AR204,"same year") -> 0 | AD23: =AVERAGEIFS(SAMPLES!AS3:AS204,SAMPLES!AR3:AR204,"after") -> 24.5 | AM23: Food Delivery | AN23: 3
B24: Grand Total | I24: Unsecured Cloud Storage | J24: 2 | M24: Median | N24: 2 | AM24: Education | AN24: 2
I25: Misonfigured Server | J25: 2 | M25: Mode | N25: 1 | AM25: Conglomerate | AN25: 1
I26: Insider Threat | J26: 2 | M26: Standard Deviation | N26: 6.8215125 | AM26: Sports | AN26: 1
I27: Social engineering via forged legal requests | J27: 2 | M27: Sample Variance | N27: 46.533033 | AM27: Analytics | AN27: 1
I28: Network Vulnerability Exploit | J28: 2 | M28: Kurtosis | N28: 2.5253418 | AM28: Professional Services | AN28: 1
I29: Unsecured Server | J29: 2 | M29: Skewness | N29: 1.8463504 | AM29: Humanitarian Services | AN29: 1
I30: Unauthorized access by a former employee | J30: 1 | M30: Range | N30: 26 | AM30: Travel & Leisure | AN30: 1
I31: Certificate Exploit | J31: 1 | M31: Minimum | N31: 1 | AM31: Design Software | AN31: 1
I32: Software Vulnerability Exploit (state sponsored) | J32: 1 | M32: Maximum | N32: 27 | AM32: Aerospace | AN32: 1
I33: Misconfigured Firewall | J33: 1 | M33: Sum | N33: 202 | AM33: Food & Beverage | AN33: 1
I34: Vulnerability in website and mobile app | J34: 1 | M34: Count | N34: 37 | AM34: Consumer Goods | AN34: 1
I35: Cloud Storage Vulnerability Exploit | J35: 1 | AM35: Media | AN35: 1
I36: Two Factor Authentication Exploit | J36: 1 | AM36: Video Games | AN36: 1
I37: Vulnerability in legacy file transfer system | J37: 1 | AM37: Food Processing | AN37: 1
I38: Skimming attack | J38: 1 | AM38: Fundraising | AN38: 1
I39: Web Application Vulnerability Exploit | J39: 1 | AM39: (blank)
I40: Point-of-sale System Compromise | J40: 1 | AM40: Grand Total | AN40: 202
I41: Compromised employee accounts | J41: 1
I42: Source Code Exploit | J42: 1
I43: (blank)
I44: Grand Total | J44: 202
B46: Breached Company Stats
B47: Rank | C47: Records | D47: Company
B48: 1 | C48: =LARGE(SAMPLES!N3:N204,1) -> 10880000000 | D48: =VLOOKUP(C48,SAMPLES!$N$3:$AY$204,38,FALSE) -> CAM4
B49: 2 | C49: =LARGE(SAMPLES!N3:N204,2) -> 8300000000 | D49: =VLOOKUP(C49,SAMPLES!$N$3:$AY$204,38,FALSE) -> Advanced Info Service (AIS)
B50: 3 | C50: =LARGE(SAMPLES!N3:N204,3) -> 5000000000 | D50: =VLOOKUP(C50,SAMPLES!$N$3:$AY$204,38,FALSE) -> Keepnet Labs
B51: 4 | C51: =LARGE(SAMPLES!N3:N204,4) -> 3000000000 | D51: =VLOOKUP(C51,SAMPLES!$N$3:$AY$204,38,FALSE) -> Clearview AI
B52: 5 | C52: =LARGE(SAMPLES!N3:N204,5) -> 2000000000 | D52: =VLOOKUP(C52,SAMPLES!$N$3:$AY$204,38,FALSE) -> Orvibo | I52: Industry Stats
B53: 6 | C53: =LARGE(SAMPLES!N3:N204,6) -> 1100000000 | D53: =VLOOKUP(C53,SAMPLES!$N$3:$AY$204,38,FALSE) -> Aadhaar | I53: Row Labels | J53: Count of Industry | M53: Distinct Industries
B54: 7 | C54: =LARGE(SAMPLES!N3:N204,7) -> 1000000000 | D54: =VLOOKUP(C54,SAMPLES!$N$3:$AY$204,38,FALSE) -> TrueDialog | I54: Technology | J54: 44 | K54: =GETPIVOTDATA("Industry",$I$53,"Industry","Technology")/GETPIVOTDATA("Industry",$I$53) -> 0.21782178 | M54: 33
B55: 8 | C55: =LARGE(SAMPLES!N3:N204,8) -> 900000000 | D55: =VLOOKUP(C55,SAMPLES!$N$3:$AY$204,38,FALSE) -> Whisper | I55: Healthcare | J55: 27 | K55: =GETPIVOTDATA("Industry",$I$53,"Industry","Healthcare")/GETPIVOTDATA("Industry",$I$53) -> 0.13366337 | M55: 0.78
B56: 9 | C56: =LARGE(SAMPLES!N3:N204,9) -> 885000000 | D56: =VLOOKUP(C56,SAMPLES!$N$3:$AY$204,38,FALSE) -> First American Financial Corp | I56: Social Media | J56: 23 | K56: =GETPIVOTDATA("Industry",$I$53,"Industry","Social Media")/GETPIVOTDATA("Industry",$I$53) -> 0.11386139
B57: 10 | C57: =LARGE(SAMPLES!N3:N204,10) -> 763000000 | D57: =VLOOKUP(C57,SAMPLES!$N$3:$AY$204,38,FALSE) -> Verifications.io | I57: Telecommunications | J57: 13 | K57: =GETPIVOTDATA("Industry",$I$53,"Industry","Telecommunications")/GETPIVOTDATA("Industry",$I$53) -> 0.064356436
I58: Retail | J58: 12 | K58: =GETPIVOTDATA("Industry",$I$53,"Industry","Retail")/GETPIVOTDATA("Industry",$I$53) -> 0.059405941
I59: Entertainment | J59: 10 | K59: =GETPIVOTDATA("Industry",$I$53,"Industry","Entertainment")/GETPIVOTDATA("Industry",$I$53) -> 0.04950495
I60: Financial Services | J60: 10 | K60: =GETPIVOTDATA("Industry",$I$53,"Industry","Financial Services")/GETPIVOTDATA("Industry",$I$53) -> 0.04950495
I61: Insurance | J61: 7 | K61: =GETPIVOTDATA("Industry",$I$53,"Industry","Insurance")/GETPIVOTDATA("Industry",$I$53) -> 0.034653465
I62: Marketing | J62: 6 | K62: =GETPIVOTDATA("Industry",$I$53,"Industry","Marketing")/GETPIVOTDATA("Industry",$I$53) -> 0.02970297
I63: Hospitality | J63: 5 | K63: =GETPIVOTDATA("Industry",$I$53,"Industry","Hospitality")/GETPIVOTDATA("Industry",$I$53) -> 0.024752475
I64: Financial Technology (FinTech) | J64: 5 | K64: =GETPIVOTDATA("Industry",$I$53,"Industry","Financial Technology (FinTech)")/GETPIVOTDATA("Industry",$I$53) -> 0.024752475
I65: Cybersecurity | J65: 4 | K65: =GETPIVOTDATA("Industry",$I$53,"Industry","Cybersecurity")/GETPIVOTDATA("Industry",$I$53) -> 0.01980198
I66: Airlines | J66: 4 | K66: =GETPIVOTDATA("Industry",$I$53,"Industry","Airlines")/GETPIVOTDATA("Industry",$I$53) -> 0.01980198
I67: Electronics | J67: 4 | K67: =GETPIVOTDATA("Industry",$I$53,"Industry","Electronics")/GETPIVOTDATA("Industry",$I$53) -> 0.01980198
I68: Automotive | J68: 3 | K68: =GETPIVOTDATA("Industry",$I$53,"Industry","Automotive")/GETPIVOTDATA("Industry",$I$53) -> 0.014851485 | M68: industry Breached
I69: Government | J69: 3 | K69: =GETPIVOTDATA("Industry",$I$53,"Industry","Government")/GETPIVOTDATA("Industry",$I$53) -> 0.014851485
I70: Transportation | J70: 3 | K70: =GETPIVOTDATA("Industry",$I$53,"Industry","Transportation")/GETPIVOTDATA("Industry",$I$53) -> 0.014851485 | M70: Mean | N70: 6.1212121
I71: Food Delivery | J71: 3 | K71: =GETPIVOTDATA("Industry",$I$53,"Industry","Food Delivery")/GETPIVOTDATA("Industry",$I$53) -> 0.014851485 | M71: Standard Error | N71: 1.6012292
I72: Education | J72: 2 | K72: =GETPIVOTDATA("Industry",$I$53,"Industry","Education")/GETPIVOTDATA("Industry",$I$53) -> 0.0099009901 | M72: Median | N72: 3
I73: Conglomerate | J73: 1 | M73: Mode | N73: 1
I74: Sports | J74: 1 | M74: Standard Deviation | N74: 9.1983612
I75: Analytics | J75: 1 | M75: Sample Variance | N75: 84.609848
I76: Professional Services | J76: 1 | M76: Kurtosis | N76: 9.0418673
I77: Humanitarian Services | J77: 1 | M77: Skewness | N77: 2.8553306
I78: Travel & Leisure | J78: 1 | M78: Range | N78: 43
I79: Design Software | J79: 1 | M79: Minimum | N79: 1
I80: Aerospace | J80: 1 | M80: Maximum | N80: 44
I81: Food & Beverage | J81: 1 | M81: Sum | N81: 202
I82: Consumer Goods | J82: 1 | M82: Count | N82: 33
I83: Media | J83: 1
I84: Video Games | J84: 1
I85: Food Processing | J85: 1
I86: Fundraising | J86: 1
I87: Grand Total | J87: 202

Sheet SAMPLES
A1: COMPANY | M1: DATA BREACH | Q1: COMPLIANCE | AA1: DATA CLASSIFICATION | AM1: YEARS MEASUREMENTS
A2: Name | B2: Industry | C2: Acquired | D2: Year Acquired | E2: Acquired by | F2: Is Inactive | G2: Date Inactive | H2: Is Public | I2: Year Public | J2: Net Worth | K2: Exchange | L2: Symbol | M2: Year Breached | N2: Records Exposed | O2: Type of Data Breached | P2: How the Breach Happened | Q2: Compliance Standards | R2: GDPR | S2: ISO | T2: PCI | U2: SOX | V2: GLBA | W2: HIPAA | X2: SOC | Y2: CCPA | Z2: RAMP | AA2: PII | AB2: is PII | AC2: PCI | AD2: is PCI | AE2: PHI | AF2: is PHI | AG2: Company Data | AH2: is Company | AI2: Technical Data | AJ2: is Technical | AK2: not disclosed | AL2: is not disclosed | AM2: acquired | AN2: public | AO2: breach | AP2: B2A | AQ2: B2A Years | AR2: B2P | AS2: B2P Years | AT2: B2GDPR | AU2: B2GDPR Yrs | AV2: B2D | AW2: RCA Vuln | AX2: RCA2GDPR | AY2: Company Name | AZ2: Compliance URL (subject to change)
A3: Aadhaar | B3: =VLOOKUP(A3,industry!A:B,2,FALSE) -> Government | C3: =VLOOKUP(A3,acquisitions!A:D,2,FALSE) -> No | D3: =VLOOKUP(A3,acquisitions!A:D,4,FALSE) -> N/A | E3: =VLOOKUP(A3,acquisitions!A:D,3,FALSE) -> N/A | F3: =VLOOKUP(A3,acquisitions!I:K,2,FALSE) -> Active | G3: =IF(F3="active","",VLOOKUP(A3,acquisitions!I:K,3,FALSE)) | H3: =VLOOKUP(A3,public!A:D,2,FALSE) -> No | I3: =VLOOKUP(A3,public!J:K,2,FALSE) -> #N/A | K3: =VLOOKUP(A3,public!A:D,3,FALSE) -> N/A | L3: =VLOOKUP(A3,public!A:D,4,FALSE) -> N/A | M3: 2018 | N3: 1100000000 | O3: Personal Identification Information | P3: Credential Stuffing | Q3: ISO 27001, GDPR | R3: yes | S3: yes | AA3: =COUNTIF(O3,"=*personal*")+COUNTIF(O3,"=*ssn*")++COUNTIF(O3,"=*license*")+COUNTIF(O3,"=*email*")+COUNTIF(O3,"=*vehic*")+COUNTIF(O3,"=*profile*")+COUNTIF(O3,"=*account*")+COUNTIF(O3,"=*image*")+COUNTIF(O3,"=*phone*")+COUNTIF(O3,"=*photo*") -> 1 | AB3: =IF(AA3>0,"yes","") -> yes | AC3: =COUNTIF(O3,"=*financ*")+COUNTIF(O3,"=*card*")+COUNTIF(O3,"=*crypto*")+COUNTIF(O3,"=*bank*")+COUNTIF(O3,"=*pay*") -> 0 | AD3: =IF(AC3>0,"yes","") | AE3: =COUNTIF(O3,"=*health*")+COUNTIF(O3,"=*bio*")+COUNTIF(O3,"=*medic*")+COUNTIF(O3,"=*patient*") -> 0 | AF3: =IF(AE3>0,"yes","") | AG3: =COUNTIF(O3,"=*customer*")+COUNTIF(O3,"=*employee*")+COUNTIF(O3,"=*guest*")+COUNTIF(O3,"=*passen*")+COUNTIF(O3,"=*applicant*")+COUNTIF(O3,"=*client*") -> 0 | AH3: =IF(AG3>0,"yes","") | AI3: =COUNTIF(O3,"=*user*")+COUNTIF(O3,"=*code*")+COUNTIF(O3,"=*software*")+COUNTIF(O3,"=*system*")+COUNTIF(O3,"=*text*")+COUNTIF(O3,"=*api*")+COUNTIF(O3,"=*cyber*") -> 0 | AJ3: =IF(AI3>0,"yes","") | AK3: =COUNTIF(O3,"=*not disclosed*") -> 0 | AL3: =IF(AK3>0,"yes","") | AM3: =IF(C3="yes",D3,"") | AN3: =IF(H3="yes",I3,"") | AO3: =M3 -> 2018 | AP3: =IF(C3="yes",IF(AO3=D3,"same year",IF(AO3<D3,"before",IF(AO3>D3,"after"))),"") | AQ3: =IF(C3="yes",IF(AP3="before",D3-AO3,IF(AP3="after",AO3-D3,IF(AP3="same year",0))),"") | AR3: =IF(H3="yes",IF(AO3=I3,"same year",IF(AO3<I3,"before",IF(AO3>I3,"after"))),"") | AS3: =IF(H3="yes",IF(AR3="same year",0,IF(AR3="before",I3-AO3,IF(AR3="after",AO3-I3))),"") | AT3: =IF(R3="yes",IF(AO3<2018,"before",IF(AO3=2018,"same year",IF(AO3>2018,"after"))),"") -> same year | AU3: =IF(R3="yes",IF(AT3="before",2018-AO3,IF(AT3="after",AO3-2018,IF(AT3="same year",0))),"") -> 0 | AV3: =IF(F3="defunct",IF(AO3=G3,"same year",IF(AO3<G3,"before",IF(AO3>=G3,"after"))),"") | AW3: =COUNTIF(P3,"=*vuln*") -> 0 | AX3: =COUNTIF(R3,"=yes") -> 1 | AY3: Aadhaar | AZ3: =VLOOKUP(A3,certs!U:V,2,FALSE) -> https://myaadhaar.uidai.gov.in/
A4: Accellion | B4: =VLOOKUP(A4,industry!A:B,2,FALSE) -> Technology | C4: =VLOOKUP(A4,acquisitions!A:D,2,FALSE) -> Yes | D4: =VLOOKUP(A4,acquisitions!A:D,4,FALSE) -> 2021 | E4: =VLOOKUP(A4,acquisitions!A:D,3,FALSE) -> Kiteworks | F4: =VLOOKUP(A4,acquisitions!I:K,2,FALSE) -> Active | G4: =IF(F4="active","",VLOOKUP(A4,acquisitions!I:K,3,FALSE)) | H4: =VLOOKUP(A4,public!A:D,2,FALSE) -> No | I4: =VLOOKUP(A4,public!J:K,2,FALSE) -> #N/A | K4: =VLOOKUP(A4,public!A:D,3,FALSE) -> N/A | L4: =VLOOKUP(A4,public!A:D,4,FALSE) -> N/A | M4: 2021 | N4: Not disclosed | O4: Data from universities, companies, governments, clients | P4: Vulnerability in legacy file transfer system | Q4: GDPR | R4: yes | AA4: =COUNTIF(O4,"=*personal*")+COUNTIF(O4,"=*ssn*")++COUNTIF(O4,"=*license*")+COUNTIF(O4,"=*email*")+COUNTIF(O4,"=*vehic*")+COUNTIF(O4,"=*profile*")+COUNTIF(O4,"=*account*")+COUNTIF(O4,"=*image*")+COUNTIF(O4,"=*phone*")+COUNTIF(O4,"=*photo*") -> 0 | AB4: =IF(AA4>0,"yes","") | AC4: =COUNTIF(O4,"=*financ*")+COUNTIF(O4,"=*card*")+COUNTIF(O4,"=*crypto*")+COUNTIF(O4,"=*bank*")+COUNTIF(O4,"=*pay*") -> 0 | AD4: =IF(AC4>0,"yes","") | AE4: =COUNTIF(O4,"=*health*")+COUNTIF(O4,"=*bio*")+COUNTIF(O4,"=*medic*")+COUNTIF(O4,"=*patient*") -> 0 | AF4: =IF(AE4>0,"yes","") | AG4: =COUNTIF(O4,"=*customer*")+COUNTIF(O4,"=*employee*")+COUNTIF(O4,"=*guest*")+COUNTIF(O4,"=*passen*")+COUNTIF(O4,"=*applicant*")+COUNTIF(O4,"=*client*") -> 1 | AH4: =IF(AG4>0,"yes","") -> yes | AI4: =COUNTIF(O4,"=*user*")+COUNTIF(O4,"=*code*")+COUNTIF(O4,"=*software*")+COUNTIF(O4,"=*system*")+COUNTIF(O4,"=*text*")+COUNTIF(O4,"=*api*")+COUNTIF(O4,"=*cyber*") -> 0 | AJ4: =IF(AI4>0,"yes","") | AK4: =COUNTIF(O4,"=*not disclosed*") -> 0 | AL4: =IF(AK4>0,"yes","") | AM4: =IF(C4="yes",D4,"") -> 2021 | AN4: =IF(H4="yes",I4,"") | AO4: =M4 -> 2021 | AP4: =IF(C4="yes",IF(AO4=D4,"same year",IF(AO4<D4,"before",IF(AO4>D4,"after"))),"") -> same year | AQ4: =IF(C4="yes",IF(AP4="before",D4-AO4,IF(AP4="after",AO4-D4,IF(AP4="same year",0))),"") -> 0 | AR4: =IF(H4="yes",IF(AO4=I4,"same year",IF(AO4<I4,"before",IF(AO4>I4,"after"))),"") | AS4: =IF(H4="yes",IF(AR4="same year",0,IF(AR4="before",I4-AO4,IF(AR4="after",AO4-I4))),"") | AT4: =IF(R4="yes",IF(AO4<2018,"before",IF(AO4=2018,"same year",IF(AO4>2018,"after"))),"") -> after | AU4: =IF(R4="yes",IF(AT4="before",2018-AO4,IF(AT4="after",AO4-2018,IF(AT4="same year",0))),"") -> 3 | AV4: =IF(F4="defunct",IF(AO4=G4,"same year",IF(AO4<G4,"before",IF(AO4>=G4,"after"))),"") | AW4: =COUNTIF(P4,"=*vuln*") -> 1 | AX4: =COUNTIF(R4,"=yes") -> 1 | AY4: Accellion | AZ4: =VLOOKUP(A4,certs!U:V,2,FALSE) -> https://www.kiteworks.com/
A5: ACER | B5: =VLOOKUP(A5,industry!A:B,2,FALSE) -> Electronics | C5: =VLOOKUP(A5,acquisitions!A:D,2,FALSE) -> No | D5: =VLOOKUP(A5,acquisitions!A:D,4,FALSE) -> N/A | E5: =VLOOKUP(A5,acquisitions!A:D,3,FALSE) -> N/A | F5: =VLOOKUP(A5,acquisitions!I:K,2,FALSE) -> Active | G5: =IF(F5="active","",VLOOKUP(A5,acquisitions!I:K,3,FALSE)) | H5: =VLOOKUP(A5,public!A:D,2,FALSE) -> Yes | I5: =VLOOKUP(A5,public!J:K,2,FALSE) -> 1988 | J5: =VLOOKUP(A5,'net worth'!B:C,2,FALSE) -> 4100000000 | K5: =VLOOKUP(A5,public!A:D,3,FALSE) -> TWSE | L5: =VLOOKUP(A5,public!A:D,4,FALSE) -> 2353 | M5: 2021 | N5: Unknown | O5: Financial and corporate data | P5: Ransomware | Q5: GDPR | R5: yes | AA5: =COUNTIF(O5,"=*personal*")+COUNTIF(O5,"=*ssn*")++COUNTIF(O5,"=*license*")+COUNTIF(O5,"=*email*")+COUNTIF(O5,"=*vehic*")+COUNTIF(O5,"=*profile*")+COUNTIF(O5,"=*account*")+COUNTIF(O5,"=*image*")+COUNTIF(O5,"=*phone*")+COUNTIF(O5,"=*photo*") -> 0 | AB5: =IF(AA5>0,"yes","") | AC5: =COUNTIF(O5,"=*financ*")+COUNTIF(O5,"=*card*")+COUNTIF(O5,"=*crypto*")+COUNTIF(O5,"=*bank*")+COUNTIF(O5,"=*pay*") -> 1 | AD5: =IF(AC5>0,"yes","") -> yes | AE5: =COUNTIF(O5,"=*health*")+COUNTIF(O5,"=*bio*")+COUNTIF(O5,"=*medic*")+COUNTIF(O5,"=*patient*") -> 0 | AF5: =IF(AE5>0,"yes","") | AG5: =COUNTIF(O5,"=*customer*")+COUNTIF(O5,"=*employee*")+COUNTIF(O5,"=*guest*")+COUNTIF(O5,"=*passen*")+COUNTIF(O5,"=*applicant*")+COUNTIF(O5,"=*client*") -> 0 | AH5: =IF(AG5>0,"yes","") | AI5: =COUNTIF(O5,"=*user*")+COUNTIF(O5,"=*code*")+COUNTIF(O5,"=*software*")+COUNTIF(O5,"=*system*")+COUNTIF(O5,"=*text*")+COUNTIF(O5,"=*api*")+COUNTIF(O5,"=*cyber*") -> 0 | AJ5: =IF(AI5>0,"yes","") | AK5: =COUNTIF(O5,"=*not disclosed*") -> 0 | AL5: =IF(AK5>0,"yes","") | AM5: =IF(C5="yes",D5,"") | AN5: =IF(H5="yes",I5,"") -> 1988 | AO5: =M5 -> 2021 | AP5: =IF(C5="yes",IF(AO5=D5,"same year",IF(AO5<D5,"before",IF(AO5>D5,"after"))),"") | AQ5: =IF(C5="yes",IF(AP5="before",D5-AO5,IF(AP5="after",AO5-D5,IF(AP5="same year",0))),"") | AR5: =IF(H5="yes",IF(AO5=I5,"same year",IF(AO5<I5,"before",IF(AO5>I5,"after"))),"") -> after | AS5: =IF(H5="yes",IF(AR5="same year",0,IF(AR5="before",I5-AO5,IF(AR5="after",AO5-I5))),"") -> 33 | AT5: =IF(R5="yes",IF(AO5<2018,"before",IF(AO5=2018,"same year",IF(AO5>2018,"after"))),"") -> after | AU5: =IF(R5="yes",IF(AT5="before",2018-AO5,IF(AT5="after",AO5-2018,IF(AT5="same year",0))),"") -> 3 | AV5: =IF(F5="defunct",IF(AO5=G5,"same year",IF(AO5<G5,"before",IF(AO5>=G5,"after"))),"") | AW5: =COUNTIF(P5,"=*vuln*") -> 0 | AX5: =COUNTIF(R5,"=yes") -> 1 | AY5: ACER | AZ5: =VLOOKUP(A5,certs!U:V,2,FALSE) -> https://www.acer.com/sustainability/en/esg-governance/information-security-and-privacy-protection/information-security
A6: Aditya Birla Fashion and Retail | B6: =VLOOKUP(A6,industry!A:B,2,FALSE) -> Retail | C6: =VLOOKUP(A6,acquisitions!A:D,2,FALSE) -> No | D6: =VLOOKUP(A6,acquisitions!A:D,4,FALSE) -> N/A | E6: =VLOOKUP(A6,acquisitions!A:D,3,FALSE) -> N/A | F6: =VLOOKUP(A6,acquisitions!I:K,2,FALSE) -> Active | G6: =IF(F6="active","",VLOOKUP(A6,acquisitions!I:K,3,FALSE)) | H6: =VLOOKUP(A6,public!A:D,2,FALSE) -> Yes | I6: =VLOOKUP(A6,public!J:K,2,FALSE) -> 2016 | J6: =VLOOKUP(A6,'net worth'!B:C,2,FALSE) -> 2100000000 | K6: =VLOOKUP(A6,public!A:D,3,FALSE) -> NSE | L6: =VLOOKUP(A6,public!A:D,4,FALSE) -> ABFRL | M6: 2021 | N6: 5400000 | O6: Customer data, contact information | P6: Phishing | Q6: GDPR | R6: yes | AA6: =COUNTIF(O6,"=*personal*")+COUNTIF(O6,"=*ssn*")++COUNTIF(O6,"=*license*")+COUNTIF(O6,"=*email*")+COUNTIF(O6,"=*vehic*")+COUNTIF(O6,"=*profile*")+COUNTIF(O6,"=*account*")+COUNTIF(O6,"=*image*")+COUNTIF(O6,"=*phone*")+COUNTIF(O6,"=*photo*") -> 0 | AB6: =IF(AA6>0,"yes","") | AC6: =COUNTIF(O6,"=*financ*")+COUNTIF(O6,"=*card*")+COUNTIF(O6,"=*crypto*")+COUNTIF(O6,"=*bank*")+COUNTIF(O6,"=*pay*") -> 0 | AD6: =IF(AC6>0,"yes","") | AE6: =COUNTIF(O6,"=*health*")+COUNTIF(O6,"=*bio*")+COUNTIF(O6,"=*medic*")+COUNTIF(O6,"=*patient*") -> 0 | AF6: =IF(AE6>0,"yes","") | AG6: =COUNTIF(O6,"=*customer*")+COUNTIF(O6,"=*employee*")+COUNTIF(O6,"=*guest*")+COUNTIF(O6,"=*passen*")+COUNTIF(O6,"=*applicant*")+COUNTIF(O6,"=*client*") -> 1 | AH6: =IF(AG6>0,"yes","") -> yes | AI6: =COUNTIF(O6,"=*user*")+COUNTIF(O6,"=*code*")+COUNTIF(O6,"=*software*")+COUNTIF(O6,"=*system*")+COUNTIF(O6,"=*text*")+COUNTIF(O6,"=*api*")+COUNTIF(O6,"=*cyber*") -> 0 | AJ6: =IF(AI6>0,"yes","") | AK6: =COUNTIF(O6,"=*not disclosed*") -> 0 | AL6: =IF(AK6>0,"yes","") | AM6: =IF(C6="yes",D6,"") | AN6: =IF(H6="yes",I6,"") -> 2016 | AO6: =M6 -> 2021 | AP6: =IF(C6="yes",IF(AO6=D6,"same year",IF(AO6<D6,"before",IF(AO6>D6,"after"))),"") | AQ6: =IF(C6="yes",IF(AP6="before",D6-AO6,IF(AP6="after",AO6-D6,IF(AP6="same year",0))),"") | AR6: =IF(H6="yes",IF(AO6=I6,"same year",IF(AO6<I6,"before",IF(AO6>I6,"after"))),"") -> after | AS6: =IF(H6="yes",IF(AR6="same year",0,IF(AR6="before",I6-AO6,IF(AR6="after",AO6-I6))),"") -> 5 | AT6: =IF(R6="yes",IF(AO6<2018,"before",IF(AO6=2018,"same year",IF(AO6>2018,"after"))),"") -> after | AU6: =IF(R6="yes",IF(AT6="before",2018-AO6,IF(AT6="after",AO6-2018,IF(AT6="same year",0))),"") -> 3 | AV6: =IF(F6="defunct",IF(AO6=G6,"same year",IF(AO6<G6,"before",IF(AO6>=G6,"after"))),"") | AW6: =COUNTIF(P6,"=*vuln*") -> 0 | AX6: =COUNTIF(R6,"=yes") -> 1 | AY6: Aditya Birla Fashion and Retail | AZ6: =VLOOKUP(A6,certs!U:V,2,FALSE) -> https://www.abfrl.com/corporate-governance/code-of-conduct/
A7: Adobe Creative Cloud | B7: =VLOOKUP(A7,industry!A:B,2,FALSE) -> Technology | C7: =VLOOKUP(A7,acquisitions!A:D,2,FALSE) -> No | D7: =VLOOKUP(A7,acquisitions!A:D,4,FALSE) -> N/A | E7: =VLOOKUP(A7,acquisitions!A:D,3,FALSE) -> N/A | F7: =VLOOKUP(A7,acquisitions!I:K,2,FALSE) -> Active | G7: =IF(F7="active","",VLOOKUP(A7,acquisitions!I:K,3,FALSE)) | H7: =VLOOKUP(A7,public!A:D,2,FALSE) -> Yes | I7: =VLOOKUP(A7,public!J:K,2,FALSE) -> 1986 | J7: =VLOOKUP(A7,'net worth'!B:C,2,FALSE) -> 210500000000 | K7: =VLOOKUP(A7,public!A:D,3,FALSE) -> NASDAQ | L7: =VLOOKUP(A7,public!A:D,4,FALSE) -> ADBE | M7: 2019 | N7: 7500000 | O7: User emails, account information | P7: Database Vulnerability Exploit | Q7: GDPR | R7: yes | AA7: =COUNTIF(O7,"=*personal*")+COUNTIF(O7,"=*ssn*")++COUNTIF(O7,"=*license*")+COUNTIF(O7,"=*email*")+COUNTIF(O7,"=*vehic*")+COUNTIF(O7,"=*profile*")+COUNTIF(O7,"=*account*")+COUNTIF(O7,"=*image*")+COUNTIF(O7,"=*phone*")+COUNTIF(O7,"=*photo*") -> 2 | AB7: =IF(AA7>0,"yes","") -> yes | AC7: =COUNTIF(O7,"=*financ*")+COUNTIF(O7,"=*card*")+COUNTIF(O7,"=*crypto*")+COUNTIF(O7,"=*bank*")+COUNTIF(O7,"=*pay*") -> 0 | AD7: =IF(AC7>0,"yes","") | AE7: =COUNTIF(O7,"=*health*")+COUNTIF(O7,"=*bio*")+COUNTIF(O7,"=*medic*")+COUNTIF(O7,"=*patient*") -> 0 | AF7: =IF(AE7>0,"yes","") | AG7: =COUNTIF(O7,"=*customer*")+COUNTIF(O7,"=*employee*")+COUNTIF(O7,"=*guest*")+COUNTIF(O7,"=*passen*")+COUNTIF(O7,"=*applicant*")+COUNTIF(O7,"=*client*") -> 0 | AH7: =IF(AG7>0,"yes","") | AI7: =COUNTIF(O7,"=*user*")+COUNTIF(O7,"=*code*")+COUNTIF(O7,"=*software*")+COUNTIF(O7,"=*system*")+COUNTIF(O7,"=*text*")+COUNTIF(O7,"=*api*")+COUNTIF(O7,"=*cyber*") -> 1 | AJ7: =IF(AI7>0,"yes","") -> yes | AK7: =COUNTIF(O7,"=*not disclosed*") -> 0 | AL7: =IF(AK7>0,"yes","") | AM7: =IF(C7="yes",D7,"") | AN7: =IF(H7="yes",I7,"") -> 1986 | AO7: =M7 -> 2019 | AP7: =IF(C7="yes",IF(AO7=D7,"same year",IF(AO7<D7,"before",IF(AO7>D7,"after"))),"") | AQ7: =IF(C7="yes",IF(AP7="before",D7-AO7,IF(AP7="after",AO7-D7,IF(AP7="same year",0))),"") | AR7: =IF(H7="yes",IF(AO7=I7,"same year",IF(AO7<I7,"before",IF(AO7>I7,"after"))),"") -> after | AS7: =IF(H7="yes",IF(AR7="same year",0,IF(AR7="before",I7-AO7,IF(AR7="after",AO7-I7))),"") -> 33 | AT7: =IF(R7="yes",IF(AO7<2018,"before",IF(AO7=2018,"same year",IF(AO7>2018,"after"))),"") -> after | AU7: =IF(R7="yes",IF(AT7="before",2018-AO7,IF(AT7="after",AO7-2018,IF(AT7="same year",0))),"") -> 1 | AV7: =IF(F7="defunct",IF(AO7=G7,"same year",IF(AO7<G7,"before",IF(AO7>=G7,"after"))),"") | AW7: =COUNTIF(P7,"=*vuln*") -> 1 | AX7: =COUNTIF(R7,"=yes") -> 1 | AY7: Adobe Creative Cloud | AZ7: =VLOOKUP(A7,certs!U:V,2,FALSE) -> https://www.adobe.com/trust/compliance.html
A8: Adult FriendFinder | B8: =VLOOKUP(A8,industry!A:B,2,FALSE) -> Entertainment | C8: =VLOOKUP(A8,acquisitions!A:D,2,FALSE) -> No | D8: =VLOOKUP(A8,acquisitions!A:D,4,FALSE) -> N/A | E8: =VLOOKUP(A8,acquisitions!A:D,3,FALSE) -> N/A | F8: =VLOOKUP(A8,acquisitions!I:K,2,FALSE) -> Active | G8: =IF(F8="active","",VLOOKUP(A8,acquisitions!I:K,3,FALSE)) | H8: =VLOOKUP(A8,public!A:D,2,FALSE) -> No | I8: =VLOOKUP(A8,public!J:K,2,FALSE) -> #N/A | K8: =VLOOKUP(A8,public!A:D,3,FALSE) -> N/A | L8: =VLOOKUP(A8,public!A:D,4,FALSE) -> N/A | M8: 2018 | N8: 412000000 | O8: User accounts, personal preferences | P8: Unsecured database | Q8: GDPR | R8: yes | AA8: =COUNTIF(O8,"=*personal*")+COUNTIF(O8,"=*ssn*")++COUNTIF(O8,"=*license*")+COUNTIF(O8,"=*email*")+COUNTIF(O8,"=*vehic*")+COUNTIF(O8,"=*profile*")+COUNTIF(O8,"=*account*")+COUNTIF(O8,"=*image*")+COUNTIF(O8,"=*phone*")+COUNTIF(O8,"=*photo*") -> 2 | AB8: =IF(AA8>0,"yes","") -> yes | AC8: =COUNTIF(O8,"=*financ*")+COUNTIF(O8,"=*card*")+COUNTIF(O8,"=*crypto*")+COUNTIF(O8,"=*bank*")+COUNTIF(O8,"=*pay*") -> 0 | AD8: =IF(AC8>0,"yes","") | AE8: =COUNTIF(O8,"=*health*")+COUNTIF(O8,"=*bio*")+COUNTIF(O8,"=*medic*")+COUNTIF(O8,"=*patient*") -> 0 | AF8: =IF(AE8>0,"yes","") | AG8: =COUNTIF(O8,"=*customer*")+COUNTIF(O8,"=*employee*")+COUNTIF(O8,"=*guest*")+COUNTIF(O8,"=*passen*")+COUNTIF(O8,"=*applicant*")+COUNTIF(O8,"=*client*") -> 0 | AH8: =IF(AG8>0,"yes","") | AI8: =COUNTIF(O8,"=*user*")+COUNTIF(O8,"=*code*")+COUNTIF(O8,"=*software*")+COUNTIF(O8,"=*system*")+COUNTIF(O8,"=*text*")+COUNTIF(O8,"=*api*")+COUNTIF(O8,"=*cyber*") -> 1 | AJ8: =IF(AI8>0,"yes","") -> yes | AK8: =COUNTIF(O8,"=*not disclosed*") -> 0 | AL8: =IF(AK8>0,"yes","") | AM8: =IF(C8="yes",D8,"") | AN8: =IF(H8="yes",I8,"") | AO8: =M8 -> 2018 | AP8: =IF(C8="yes",IF(AO8=D8,"same year",IF(AO8<D8,"before",IF(AO8>D8,"after"))),"") | AQ8: =IF(C8="yes",IF(AP8="before",D8-AO8,IF(AP8="after",AO8-D8,IF(AP8="same year",0))),"") | AR8: =IF(H8="yes",IF(AO8=I8,"same year",IF(AO8<I8,"before",IF(AO8>I8,"after"))),"") | AS8: =IF(H8="yes",IF(AR8="same year",0,IF(AR8="before",I8-AO8,IF(AR8="after",AO8-I8))),"") | AT8: =IF(R8="yes",IF(AO8<2018,"before",IF(AO8=2018,"same year",IF(AO8>2018,"after"))),"") -> same year | AU8: =IF(R8="yes",IF(AT8="before",2018-AO8,IF(AT8="after",AO8-2018,IF(AT8="same year",0))),"") -> 0 | AV8: =IF(F8="defunct",IF(AO8=G8,"same year",IF(AO8<G8,"before",IF(AO8>=G8,"after"))),"") | AW8: =COUNTIF(P8,"=*vuln*") -> 0 | AX8: =COUNTIF(R8,"=yes") -> 1 | AY8: Adult FriendFinder | AZ8: =VLOOKUP(A8,certs!U:V,2,FALSE) -> Not Available
A9: Advanced Info Service (AIS) | B9: =VLOOKUP(A9,industry!A:B,2,FALSE) -> Telecommunications | C9: =VLOOKUP(A9,acquisitions!A:D,2,FALSE) -> No | D9: =VLOOKUP(A9,acquisitions!A:D,4,FALSE) -> N/A | E9: =VLOOKUP(A9,acquisitions!A:D,3,FALSE) -> N/A | F9: =VLOOKUP(A9,acquisitions!I:K,2,FALSE) -> Active | G9: =IF(F9="active","",VLOOKUP(A9,acquisitions!I:K,3,FALSE)) | H9: =VLOOKUP(A9,public!A:D,2,FALSE) -> Yes | I9: =VLOOKUP(A9,public!J:K,2,FALSE) -> 1991 | J9: =VLOOKUP(A9,'net worth'!B:C,2,FALSE) -> 13600000000 | K9: =VLOOKUP(A9,public!A:D,3,FALSE) -> SET | L9: =VLOOKUP(A9,public!A:D,4,FALSE) -> ADVANC | M9: 2020 | N9: 8300000000 | O9: DNS query logs, user internet activity | P9: Misconfigured Database | Q9: Thailand PDPA | AA9: =COUNTIF(O9,"=*personal*")+COUNTIF(O9,"=*ssn*")++COUNTIF(O9,"=*license*")+COUNTIF(O9,"=*email*")+COUNTIF(O9,"=*vehic*")+COUNTIF(O9,"=*profile*")+COUNTIF(O9,"=*account*")+COUNTIF(O9,"=*image*")+COUNTIF(O9,"=*phone*")+COUNTIF(O9,"=*photo*") -> 0 | AB9: =IF(AA9>0,"yes","") | AC9: =COUNTIF(O9,"=*financ*")+COUNTIF(O9,"=*card*")+COUNTIF(O9,"=*crypto*")+COUNTIF(O9,"=*bank*")+COUNTIF(O9,"=*pay*") -> 0 | AD9: =IF(AC9>0,"yes","") | AE9: =COUNTIF(O9,"=*health*")+COUNTIF(O9,"=*bio*")+COUNTIF(O9,"=*medic*")+COUNTIF(O9,"=*patient*") -> 0 | AF9: =IF(AE9>0,"yes","") | AG9: =COUNTIF(O9,"=*customer*")+COUNTIF(O9,"=*employee*")+COUNTIF(O9,"=*guest*")+COUNTIF(O9,"=*passen*")+COUNTIF(O9,"=*applicant*")+COUNTIF(O9,"=*client*") -> 0 | AH9: =IF(AG9>0,"yes","") | AI9: =COUNTIF(O9,"=*user*")+COUNTIF(O9,"=*code*")+COUNTIF(O9,"=*software*")+COUNTIF(O9,"=*system*")+COUNTIF(O9,"=*text*")+COUNTIF(O9,"=*api*")+COUNTIF(O9,"=*cyber*") -> 1 | AJ9: =IF(AI9>0,"yes","") -> yes | AK9: =COUNTIF(O9,"=*not disclosed*") -> 0 | AL9: =IF(AK9>0,"yes","") | AM9: =IF(C9="yes",D9,"") | AN9: =IF(H9="yes",I9,"") -> 1991 | AO9: =M9 -> 2020 | AP9: =IF(C9="yes",IF(AO9=D9,"same year",IF(AO9<D9,"before",IF(AO9>D9,"after"))),"") | AQ9: =IF(C9="yes",IF(AP9="before",D9-AO9,IF(AP9="after",AO9-D9,IF(AP9="same year",0))),"") | AR9: =IF(H9="yes",IF(AO9=I9,"same year",IF(AO9<I9,"before",IF(AO9>I9,"after"))),"") -> after | AS9: =IF(H9="yes",IF(AR9="same year",0,IF(AR9="before",I9-AO9,IF(AR9="after",AO9-I9))),"") -> 29 | AT9: =IF(R9="yes",IF(AO9<2018,"before",IF(AO9=2018,"same year",IF(AO9>2018,"after"))),"") | AU9: =IF(R9="yes",IF(AT9="before",2018-AO9,IF(AT9="after",AO9-2018,IF(AT9="same year",0))),"") | AV9: =IF(F9="defunct",IF(AO9=G9,"same year",IF(AO9<G9,"before",IF(AO9>=G9,"after"))),"") | AW9: =COUNTIF(P9,"=*vuln*") -> 0 | AX9: =COUNTIF(R9,"=yes") -> 0 | AY9: Advanced Info Service (AIS) | AZ9: =VLOOKUP(A9,certs!U:V,2,FALSE) -> https://www.ais.co.th/en/compliance.html
A10: Afrihost | B10: =VLOOKUP(A10,industry!A:B,2,FALSE) -> Technology | C10: =VLOOKUP(A10,acquisitions!A:D,2,FALSE) -> No | D10: =VLOOKUP(A10,acquisitions!A:D,4,FALSE) -> N/A | E10: =VLOOKUP(A10,acquisitions!A:D,3,FALSE) -> N/A | F10: =VLOOKUP(A10,acquisitions!I:K,2,FALSE) -> Active | G10: =IF(F10="active","",VLOOKUP(A10,acquisitions!I:K,3,FALSE)) | H10: =VLOOKUP(A10,public!A:D,2,FALSE) -> No | I10: =VLOOKUP(A10,public!J:K,2,FALSE) -> #N/A | K10: =VLOOKUP(A10,public!A:D,3,FALSE) -> N/A | L10: =VLOOKUP(A10,public!A:D,4,FALSE) -> N/A | M10: 2020 | N10: Unknown | O10: Customer data, banking details | P10: Unsecured Database | Q10: POPIA (South Africa), GDPR | R10: yes | AA10: =COUNTIF(O10,"=*personal*")+COUNTIF(O10,"=*ssn*")++COUNTIF(O10,"=*license*")+COUNTIF(O10,"=*email*")+COUNTIF(O10,"=*vehic*")+COUNTIF(O10,"=*profile*")+COUNTIF(O10,"=*account*")+COUNTIF(O10,"=*image*")+COUNTIF(O10,"=*phone*")+COUNTIF(O10,"=*photo*") -> 0 | AB10: =IF(AA10>0,"yes","") | AC10: =COUNTIF(O10,"=*financ*")+COUNTIF(O10,"=*card*")+COUNTIF(O10,"=*crypto*")+COUNTIF(O10,"=*bank*")+COUNTIF(O10,"=*pay*") -> 1 | AD10: =IF(AC10>0,"yes","") -> yes | AE10: =COUNTIF(O10,"=*health*")+COUNTIF(O10,"=*bio*")+COUNTIF(O10,"=*medic*")+COUNTIF(O10,"=*patient*") -> 0 | AF10: =IF(AE10>0,"yes","") | AG10: =COUNTIF(O10,"=*customer*")+COUNTIF(O10,"=*employee*")+COUNTIF(O10,"=*guest*")+COUNTIF(O10,"=*passen*")+COUNTIF(O10,"=*applicant*")+COUNTIF(O10,"=*client*") -> 1 | AH10: =IF(AG10>0,"yes","") -> yes | AI10: =COUNTIF(O10,"=*user*")+COUNTIF(O10,"=*code*")+COUNTIF(O10,"=*software*")+COUNTIF(O10,"=*system*")+COUNTIF(O10,"=*text*")+COUNTIF(O10,"=*api*")+COUNTIF(O10,"=*cyber*") -> 0 | AJ10: =IF(AI10>0,"yes","") | AK10: =COUNTIF(O10,"=*not disclosed*") -> 0 | AL10: =IF(AK10>0,"yes","") | AM10: =IF(C10="yes",D10,"") | AN10: =IF(H10="yes",I10,"") | AO10: =M10 -> 2020 | AP10: =IF(C10="yes",IF(AO10=D10,"same year",IF(AO10<D10,"before",IF(AO10>D10,"after"))),"") | AQ10: =IF(C10="yes",IF(AP10="before",D10-AO10,IF(AP10="after",AO10-D10,IF(AP10="same year",0))),"") | AR10: =IF(H10="yes",IF(AO10=I10,"same year",IF(AO10<I10,"before",IF(AO10>I10,"after"))),"") | AS10: =IF(H10="yes",IF(AR10="same year",0,IF(AR10="before",I10-AO10,IF(AR10="after",AO10-I10))),"") | AT10: =IF(R10="yes",IF(AO10<2018,"before",IF(AO10=2018,"same year",IF(AO10>2018,"after"))),"") -> after | AU10: =IF(R10="yes",IF(AT10="before",2018-AO10,IF(AT10="after",AO10-2018,IF(AT10="same year",0))),"") -> 2 | AV10: =IF(F10="defunct",IF(AO10=G10,"same year",IF(AO10<G10,"before",IF(AO10>=G10,"after"))),"") | AW10: =COUNTIF(P10,"=*vuln*") -> 0 | AX10: =COUNTIF(R10,"=yes") -> 1 | AY10: Afrihost | AZ10: =VLOOKUP(A10,certs!U:V,2,FALSE) -> https://www.afrihost.com/site/page/legal
A11: American Airlines | B11: =VLOOKUP(A11,industry!A:B,2,FALSE) -> Airlines | C11: =VLOOKUP(A11,acquisitions!A:D,2,FALSE) -> No | D11: =VLOOKUP(A11,acquisitions!A:D,4,FALSE) -> N/A | E11: =VLOOKUP(A11,acquisitions!A:D,3,FALSE) -> N/A | F11: =VLOOKUP(A11,acquisitions!I:K,2,FALSE) -> Active | G11: =IF(F11="active","",VLOOKUP(A11,acquisitions!I:K,3,FALSE)) | H11: =VLOOKUP(A11,public!A:D,2,FALSE) -> Yes | I11: =VLOOKUP(A11,public!J:K,2,FALSE) -> 2013 | J11: =VLOOKUP(A11,'net worth'!B:C,2,FALSE) -> 12800000000 | K11: =VLOOKUP(A11,public!A:D,3,FALSE) -> NASDAQ | L11: =VLOOKUP(A11,public!A:D,4,FALSE) -> AAL | M11: 2022 | N11: 1708 | O11: Customer and employee data | P11: Compromised employee accounts | Q11: GDPR | R11: yes | AA11: =COUNTIF(O11,"=*personal*")+COUNTIF(O11,"=*ssn*")++COUNTIF(O11,"=*license*")+COUNTIF(O11,"=*email*")+COUNTIF(O11,"=*vehic*")+COUNTIF(O11,"=*profile*")+COUNTIF(O11,"=*account*")+COUNTIF(O11,"=*image*")+COUNTIF(O11,"=*phone*")+COUNTIF(O11,"=*photo*") -> 0 | AB11: =IF(AA11>0,"yes","") | AC11: =COUNTIF(O11,"=*financ*")+COUNTIF(O11,"=*card*")+COUNTIF(O11,"=*crypto*")+COUNTIF(O11,"=*bank*")+COUNTIF(O11,"=*pay*") -> 0 | AD11: =IF(AC11>0,"yes","") | AE11: =COUNTIF(O11,"=*health*")+COUNTIF(O11,"=*bio*")+COUNTIF(O11,"=*medic*")+COUNTIF(O11,"=*patient*") -> 0 | AF11: =IF(AE11>0,"yes","") | AG11: =COUNTIF(O11,"=*customer*")+COUNTIF(O11,"=*employee*")+COUNTIF(O11,"=*guest*")+COUNTIF(O11,"=*passen*")+COUNTIF(O11,"=*applicant*")+COUNTIF(O11,"=*client*") -> 2 | AH11: =IF(AG11>0,"yes","") -> yes | AI11: =COUNTIF(O11,"=*user*")+COUNTIF(O11,"=*code*")+COUNTIF(O11,"=*software*")+COUNTIF(O11,"=*system*")+COUNTIF(O11,"=*text*")+COUNTIF(O11,"=*api*")+COUNTIF(O11,"=*cyber*") -> 0 | AJ11: =IF(AI11>0,"yes","") | AK11: =COUNTIF(O11,"=*not disclosed*") -> 0 | AL11: =IF(AK11>0,"yes","") | AM11: =IF(C11="yes",D11,"") | AN11: =IF(H11="yes",I11,"") -> 2013 | AO11: =M11 -> 2022 | AP11: =IF(C11="yes",IF(AO11=D11,"same year",IF(AO11<D11,"before",IF(AO11>D11,"after"))),"") | AQ11: =IF(C11="yes",IF(AP11="before",D11-AO11,IF(AP11="after",AO11-D11,IF(AP11="same year",0))),"") | AR11: =IF(H11="yes",IF(AO11=I11,"same year",IF(AO11<I11,"before",IF(AO11>I11,"after"))),"") -> after | AS11: =IF(H11="yes",IF(AR11="same year",0,IF(AR11="before",I11-AO11,IF(AR11="after",AO11-I11))),"") -> 9 | AT11: =IF(R11="yes",IF(AO11<2018,"before",IF(AO11=2018,"same year",IF(AO11>2018,"after"))),"") -> after | AU11: =IF(R11="yes",IF(AT11="before",2018-AO11,IF(AT11="after",AO11-2018,IF(AT11="same year",0))),"") -> 4 | AV11: =IF(F11="defunct",IF(AO11=G11,"same year",IF(AO11<G11,"before",IF(AO11>=G11,"after"))),"") | AW11: =COUNTIF(P11,"=*vuln*") -> 0 | AX11: =COUNTIF(R11,"=yes") -> 1 | AY11: American Airlines | AZ11: =VLOOKUP(A11,certs!U:V,2,FALSE) -> https://www.aa.com/i18n/customer-service/customer-commitment.jsp
A12: Anico | B12: =VLOOKUP(A12,industry!A:B,2,FALSE) -> Insurance | C12: =VLOOKUP(A12,acquisitions!A:D,2,FALSE) -> No | D12: =VLOOKUP(A12,acquisitions!A:D,4,FALSE) -> N/A | E12: =VLOOKUP(A12,acquisitions!A:D,3,FALSE) -> N/A | F12: =VLOOKUP(A12,acquisitions!I:K,2,FALSE) -> Active | G12: =IF(F12="active","",VLOOKUP(A12,acquisitions!I:K,3,FALSE)) | H12: =VLOOKUP(A12,public!A:D,2,FALSE) -> No | I12: =VLOOKUP(A12,public!J:K,2,FALSE) -> #N/A | K12: =VLOOKUP(A12,public!A:D,3,FALSE) -> N/A | L12: =VLOOKUP(A12,public!A:D,4,FALSE) -> N/A | M12: 2023 | N12: 279332 | O12: Names, emails, addresses, SSNs | P12: Phishing | Q12: HIPAA, PCI DSS | T12: yes | W12: yes | AA12: =COUNTIF(O12,"=*personal*")+COUNTIF(O12,"=*ssn*")++COUNTIF(O12,"=*license*")+COUNTIF(O12,"=*email*")+COUNTIF(O12,"=*vehic*")+COUNTIF(O12,"=*profile*")+COUNTIF(O12,"=*account*")+COUNTIF(O12,"=*image*")+COUNTIF(O12,"=*phone*")+COUNTIF(O12,"=*photo*") -> 2 | AB12: =IF(AA12>0,"yes","") -> yes | AC12: =COUNTIF(O12,"=*financ*")+COUNTIF(O12,"=*card*")+COUNTIF(O12,"=*crypto*")+COUNTIF(O12,"=*bank*")+COUNTIF(O12,"=*pay*") -> 0 | AD12: =IF(AC12>0,"yes","") | AE12: =COUNTIF(O12,"=*health*")+COUNTIF(O12,"=*bio*")+COUNTIF(O12,"=*medic*")+COUNTIF(O12,"=*patient*") -> 0 | AF12: =IF(AE12>0,"yes","") | AG12: =COUNTIF(O12,"=*customer*")+COUNTIF(O12,"=*employee*")+COUNTIF(O12,"=*guest*")+COUNTIF(O12,"=*passen*")+COUNTIF(O12,"=*applicant*")+COUNTIF(O12,"=*client*") -> 0 | AH12: =IF(AG12>0,"yes","") | AI12: =COUNTIF(O12,"=*user*")+COUNTIF(O12,"=*code*")+COUNTIF(O12,"=*software*")+COUNTIF(O12,"=*system*")+COUNTIF(O12,"=*text*")+COUNTIF(O12,"=*api*")+COUNTIF(O12,"=*cyber*") -> 0 | AJ12: =IF(AI12>0,"yes","") | AK12: =COUNTIF(O12,"=*not disclosed*") -> 0 | AL12: =IF(AK12>0,"yes","") | AM12: =IF(C12="yes",D12,"") | AN12: =IF(H12="yes",I12,"") | AO12: =M12 -> 2023 | AP12: =IF(C12="yes",IF(AO12=D12,"same year",IF(AO12<D12,"before",IF(AO12>D12,"after"))),"") | AQ12: =IF(C12="yes",IF(AP12="before",D12-AO12,IF(AP12="after",AO12-D12,IF(AP12="same year",0))),"") | AR12: =IF(H12="yes",IF(AO12=I12,"same year",IF(AO12<I12,"before",IF(AO12>I12,"after"))),"") | AS12: =IF(H12="yes",IF(AR12="same year",0,IF(AR12="before",I12-AO12,IF(AR12="after",AO12-I12))),"") | AT12: =IF(R12="yes",IF(AO12<2018,"before",IF(AO12=2018,"same year",IF(AO12>2018,"after"))),"") | AU12: =IF(R12="yes",IF(AT12="before",2018-AO12,IF(AT12="after",AO12-2018,IF(AT12="same year",0))),"") | AV12: =IF(F12="defunct",IF(AO12=G12,"same year",IF(AO12<G12,"before",IF(AO12>=G12,"after"))),"") | AW12: =COUNTIF(P12,"=*vuln*") -> 0 | AX12: =COUNTIF(R12,"=yes") -> 0 | AY12: Anico | AZ12: =VLOOKUP(A12,certs!U:V,2,FALSE) -> https://www.american-national.com/wps/portal/an/home/legal-compliance
A13: Anthem Blue Cross | B13: =VLOOKUP(A13,industry!A:B,2,FALSE) -> Insurance | C13: =VLOOKUP(A13,acquisitions!A:D,2,FALSE) -> Yes | D13: =VLOOKUP(A13,acquisitions!A:D,4,FALSE) -> 2004 | E13: =VLOOKUP(A13,acquisitions!A:D,3,FALSE) -> Anthem, Inc. | F13: =VLOOKUP(A13,acquisitions!I:K,2,FALSE) -> Active | G13: =IF(F13="active","",VLOOKUP(A13,acquisitions!I:K,3,FALSE)) | H13: =VLOOKUP(A13,public!A:D,2,FALSE) -> No | I13: =VLOOKUP(A13,public!J:K,2,FALSE) -> #N/A | K13: =VLOOKUP(A13,public!A:D,3,FALSE) -> N/A | L13: =VLOOKUP(A13,public!A:D,4,FALSE) -> N/A | M13: 2023 | N13: Not disclosed | O13: Names, medical records, SSNs | P13: Ransomware | Q13: HIPAA | W13: yes | AA13: =COUNTIF(O13,"=*personal*")+COUNTIF(O13,"=*ssn*")++COUNTIF(O13,"=*license*")+COUNTIF(O13,"=*email*")+COUNTIF(O13,"=*vehic*")+COUNTIF(O13,"=*profile*")+COUNTIF(O13,"=*account*")+COUNTIF(O13,"=*image*")+COUNTIF(O13,"=*phone*")+COUNTIF(O13,"=*photo*") -> 1 | AB13: =IF(AA13>0,"yes","") -> yes | AC13: =COUNTIF(O13,"=*financ*")+COUNTIF(O13,"=*card*")+COUNTIF(O13,"=*crypto*")+COUNTIF(O13,"=*bank*")+COUNTIF(O13,"=*pay*") -> 0 | AD13: =IF(AC13>0,"yes","") | AE13: =COUNTIF(O13,"=*health*")+COUNTIF(O13,"=*bio*")+COUNTIF(O13,"=*medic*")+COUNTIF(O13,"=*patient*") -> 1 | AF13: =IF(AE13>0,"yes","") -> yes | AG13: =COUNTIF(O13,"=*customer*")+COUNTIF(O13,"=*employee*")+COUNTIF(O13,"=*guest*")+COUNTIF(O13,"=*passen*")+COUNTIF(O13,"=*applicant*")+COUNTIF(O13,"=*client*") -> 0 | AH13: =IF(AG13>0,"yes","") | AI13: =COUNTIF(O13,"=*user*")+COUNTIF(O13,"=*code*")+COUNTIF(O13,"=*software*")+COUNTIF(O13,"=*system*")+COUNTIF(O13,"=*text*")+COUNTIF(O13,"=*api*")+COUNTIF(O13,"=*cyber*") -> 0 | AJ13: =IF(AI13>0,"yes","") | AK13: =COUNTIF(O13,"=*not disclosed*") -> 0 | AL13: =IF(AK13>0,"yes","") | AM13: =IF(C13="yes",D13,"") -> 2004 | AN13: =IF(H13="yes",I13,"") | AO13: =M13 -> 2023 | AP13: =IF(C13="yes",IF(AO13=D13,"same year",IF(AO13<D13,"before",IF(AO13>D13,"after"))),"") -> after | AQ13: =IF(C13="yes",IF(AP13="before",D13-AO13,IF(AP13="after",AO13-D13,IF(AP13="same year",0))),"") -> 19 | AR13: =IF(H13="yes",IF(AO13=I13,"same year",IF(AO13<I13,"before",IF(AO13>I13,"after"))),"") | AS13: =IF(H13="yes",IF(AR13="same year",0,IF(AR13="before",I13-AO13,IF(AR13="after",AO13-I13))),"") | AT13: =IF(R13="yes",IF(AO13<2018,"before",IF(AO13=2018,"same year",IF(AO13>2018,"after"))),"") | AU13: =IF(R13="yes",IF(AT13="before",2018-AO13,IF(AT13="after",AO13-2018,IF(AT13="same year",0))),"") | AV13: =IF(F13="defunct",IF(AO13=G13,"same year",IF(AO13<G13,"before",IF(AO13>=G13,"after"))),"") | AW13: =COUNTIF(P13,"=*vuln*") -> 0 | AX13: =COUNTIF(R13,"=yes") -> 0 | AY13: Anthem Blue Cross | AZ13: =VLOOKUP(A13,certs!U:V,2,FALSE) -> https://www.anthem.com/legal-information
A14: Antheus Tecnologia | B14: =VLOOKUP(A14,industry!A:B,2,FALSE) -> Technology | C14: =VLOOKUP(A14,acquisitions!A:D,2,FALSE) -> Yes | D14: =VLOOKUP(A14,acquisitions!A:D,4,FALSE) -> 2020 | E14: =VLOOKUP(A14,acquisitions!A:D,3,FALSE) -> ISO | F14: =VLOOKUP(A14,acquisitions!I:K,2,FALSE) -> Active | G14: =IF(F14="active","",VLOOKUP(A14,acquisitions!I:K,3,FALSE)) | H14: =VLOOKUP(A14,public!A:D,2,FALSE) -> No | I14: =VLOOKUP(A14,public!J:K,2,FALSE) -> #N/A | K14: =VLOOKUP(A14,public!A:D,3,FALSE) -> N/A | L14: =VLOOKUP(A14,public!A:D,4,FALSE) -> N/A | M14: 2019 | N14: 76000 | O14: Biometric data, fingerprints | P14: Misconfigured Database | Q14: LGPD (Brazil), GDPR | R14: yes | AA14: =COUNTIF(O14,"=*personal*")+COUNTIF(O14,"=*ssn*")++COUNTIF(O14,"=*license*")+COUNTIF(O14,"=*email*")+COUNTIF(O14,"=*vehic*")+COUNTIF(O14,"=*profile*")+COUNTIF(O14,"=*account*")+COUNTIF(O14,"=*image*")+COUNTIF(O14,"=*phone*")+COUNTIF(O14,"=*photo*") -> 0 | AB14: =IF(AA14>0,"yes","") | AC14: =COUNTIF(O14,"=*financ*")+COUNTIF(O14,"=*card*")+COUNTIF(O14,"=*crypto*")+COUNTIF(O14,"=*bank*")+COUNTIF(O14,"=*pay*") -> 0 | AD14: =IF(AC14>0,"yes","") | AE14: =COUNTIF(O14,"=*health*")+COUNTIF(O14,"=*bio*")+COUNTIF(O14,"=*medic*")+COUNTIF(O14,"=*patient*") -> 1 | AF14: =IF(AE14>0,"yes","") -> yes | AG14: =COUNTIF(O14,"=*customer*")+COUNTIF(O14,"=*employee*")+COUNTIF(O14,"=*guest*")+COUNTIF(O14,"=*passen*")+COUNTIF(O14,"=*applicant*")+COUNTIF(O14,"=*client*") -> 0 | AH14: =IF(AG14>0,"yes","") | AI14: =COUNTIF(O14,"=*user*")+COUNTIF(O14,"=*code*")+COUNTIF(O14,"=*software*")+COUNTIF(O14,"=*system*")+COUNTIF(O14,"=*text*")+COUNTIF(O14,"=*api*")+COUNTIF(O14,"=*cyber*") -> 0 | AJ14: =IF(AI14>0,"yes","") | AK14: =COUNTIF(O14,"=*not disclosed*") -> 0 | AL14: =IF(AK14>0,"yes","") | AM14: =IF(C14="yes",D14,"") -> 2020 | AN14: =IF(H14="yes",I14,"") | AO14: =M14 -> 2019 | AP14: =IF(C14="yes",IF(AO14=D14,"same year",IF(AO14<D14,"before",IF(AO14>D14,"after"))),"") -> before | AQ14: =IF(C14="yes",IF(AP14="before",D14-AO14,IF(AP14="after",AO14-D14,IF(AP14="same year",0))),"") -> 1 | AR14: =IF(H14="yes",IF(AO14=I14,"same year",IF(AO14<I14,"before",IF(AO14>I14,"after"))),"") | AS14: =IF(H14="yes",IF(AR14="same year",0,IF(AR14="before",I14-AO14,IF(AR14="after",AO14-I14))),"") | AT14: =IF(R14="yes",IF(AO14<2018,"before",IF(AO14=2018,"same year",IF(AO14>2018,"after"))),"") -> after | AU14: =IF(R14="yes",IF(AT14="before",2018-AO14,IF(AT14="after",AO14-2018,IF(AT14="same year",0))),"") -> 1 | AV14: =IF(F14="defunct",IF(AO14=G14,"same year",IF(AO14<G14,"before",IF(AO14>=G14,"after"))),"") | AW14: =COUNTIF(P14,"=*vuln*") -> 0 | AX14: =COUNTIF(R14,"=yes") -> 1 | AY14: Antheus Tecnologia | AZ14: =VLOOKUP(A14,certs!U:V,2,FALSE) -> https://www.antheustecnologia.com.br/compliance
A15: Apodis Pharma | B15: =VLOOKUP(A15,industry!A:B,2,FALSE) -> Healthcare | C15: =VLOOKUP(A15,acquisitions!A:D,2,FALSE) -> No | D15: =VLOOKUP(A15,acquisitions!A:D,4,FALSE) -> N/A | E15: =VLOOKUP(A15,acquisitions!A:D,3,FALSE) -> N/A | F15: =VLOOKUP(A15,acquisitions!I:K,2,FALSE) -> Active | G15: =IF(F15="active","",VLOOKUP(A15,acquisitions!I:K,3,FALSE)) | H15: =VLOOKUP(A15,public!A:D,2,FALSE) -> No | I15: =VLOOKUP(A15,public!J:K,2,FALSE) -> #N/A | K15: =VLOOKUP(A15,public!A:D,3,FALSE) -> N/A | L15: =VLOOKUP(A15,public!A:D,4,FALSE) -> N/A | M15: 2020 | N15: 1000000 | O15: Customer data, prescription details | P15: Unsecured AWS S3 bucket | Q15: GDPR | R15: yes | AA15: =COUNTIF(O15,"=*personal*")+COUNTIF(O15,"=*ssn*")++COUNTIF(O15,"=*license*")+COUNTIF(O15,"=*email*")+COUNTIF(O15,"=*vehic*")+COUNTIF(O15,"=*profile*")+COUNTIF(O15,"=*account*")+COUNTIF(O15,"=*image*")+COUNTIF(O15,"=*phone*")+COUNTIF(O15,"=*photo*") -> 0 | AB15: =IF(AA15>0,"yes","") | AC15: =COUNTIF(O15,"=*financ*")+COUNTIF(O15,"=*card*")+COUNTIF(O15,"=*crypto*")+COUNTIF(O15,"=*bank*")+COUNTIF(O15,"=*pay*") -> 0 | AD15: =IF(AC15>0,"yes","") | AE15: =COUNTIF(O15,"=*health*")+COUNTIF(O15,"=*bio*")+COUNTIF(O15,"=*medic*")+COUNTIF(O15,"=*patient*") -> 0 | AF15: =IF(AE15>0,"yes","") | AG15: =COUNTIF(O15,"=*customer*")+COUNTIF(O15,"=*employee*")+COUNTIF(O15,"=*guest*")+COUNTIF(O15,"=*passen*")+COUNTIF(O15,"=*applicant*")+COUNTIF(O15,"=*client*") -> 1 | AH15: =IF(AG15>0,"yes","") -> yes | AI15: =COUNTIF(O15,"=*user*")+COUNTIF(O15,"=*code*")+COUNTIF(O15,"=*software*")+COUNTIF(O15,"=*system*")+COUNTIF(O15,"=*text*")+COUNTIF(O15,"=*api*")+COUNTIF(O15,"=*cyber*") -> 0 | AJ15: =IF(AI15>0,"yes","") | AK15: =COUNTIF(O15,"=*not disclosed*") -> 0 | AL15: =IF(AK15>0,"yes","") | AM15: =IF(C15="yes",D15,"") | AN15: =IF(H15="yes",I15,"") | AO15: =M15 -> 2020 | AP15: =IF(C15="yes",IF(AO15=D15,"same year",IF(AO15<D15,"before",IF(AO15>D15,"after"))),"") | AQ15: =IF(C15="yes",IF(AP15="before",D15-AO15,IF(AP15="after",AO15-D15,IF(AP15="same year",0))),"") | AR15: =IF(H15="yes",IF(AO15=I15,"same year",IF(AO15<I15,"before",IF(AO15>I15,"after"))),"") | AS15: =IF(H15="yes",IF(AR15="same year",0,IF(AR15="before",I15-AO15,IF(AR15="after",AO15-I15))),"") | AT15: =IF(R15="yes",IF(AO15<2018,"before",IF(AO15=2018,"same year",IF(AO15>2018,"after"))),"") -> after | AU15: =IF(R15="yes",IF(AT15="before",2018-AO15,IF(AT15="after",AO15-2018,IF(AT15="same year",0))),"") -> 2 | AV15: =IF(F15="defunct",IF(AO15=G15,"same year",IF(AO15<G15,"before",IF(AO15>=G15,"after"))),"") | AW15: =COUNTIF(P15,"=*vuln*") -> 0 | AX15: =COUNTIF(R15,"=yes") -> 1 | AY15: Apodis Pharma | AZ15: =VLOOKUP(A15,certs!U:V,2,FALSE) -> https://www.apodispharma.com/compliance/
A16: Apple | B16: =VLOOKUP(A16,industry!A:B,2,FALSE) -> Technology | C16: =VLOOKUP(A16,acquisitions!A:D,2,FALSE) -> No | D16: =VLOOKUP(A16,acquisitions!A:D,4,FALSE) -> N/A | E16: =VLOOKUP(A16,acquisitions!A:D,3,FALSE) -> N/A | F16: =VLOOKUP(A16,acquisitions!I:K,2,FALSE) -> Active | G16: =IF(F16="active","",VLOOKUP(A16,acquisitions!I:K,3,FALSE)) | H16: =VLOOKUP(A16,public!A:D,2,FALSE) -> Yes | I16: =VLOOKUP(A16,public!J:K,2,FALSE) -> 1980 | J16: =VLOOKUP(A16,'net worth'!B:C,2,FALSE) -> 2560000000000 | K16: =VLOOKUP(A16,public!A:D,3,FALSE) -> NASDAQ | L16: =VLOOKUP(A16,public!A:D,4,FALSE) -> AAPL | M16: 2022 | N16: Not disclosed | O16: User addresses, phone numbers | P16: Social engineering via forged legal requests | Q16: GDPR | R16: yes | AA16: =COUNTIF(O16,"=*personal*")+COUNTIF(O16,"=*ssn*")++COUNTIF(O16,"=*license*")+COUNTIF(O16,"=*email*")+COUNTIF(O16,"=*vehic*")+COUNTIF(O16,"=*profile*")+COUNTIF(O16,"=*account*")+COUNTIF(O16,"=*image*")+COUNTIF(O16,"=*phone*")+COUNTIF(O16,"=*photo*") -> 1 | AB16: =IF(AA16>0,"yes","") -> yes | AC16: =COUNTIF(O16,"=*financ*")+COUNTIF(O16,"=*card*")+COUNTIF(O16,"=*crypto*")+COUNTIF(O16,"=*bank*")+COUNTIF(O16,"=*pay*") -> 0 | AD16: =IF(AC16>0,"yes","") | AE16: =COUNTIF(O16,"=*health*")+COUNTIF(O16,"=*bio*")+COUNTIF(O16,"=*medic*")+COUNTIF(O16,"=*patient*") -> 0 | AF16: =IF(AE16>0,"yes","") | AG16: =COUNTIF(O16,"=*customer*")+COUNTIF(O16,"=*employee*")+COUNTIF(O16,"=*guest*")+COUNTIF(O16,"=*passen*")+COUNTIF(O16,"=*applicant*")+COUNTIF(O16,"=*client*") -> 0 | AH16: =IF(AG16>0,"yes","") | AI16: =COUNTIF(O16,"=*user*")+COUNTIF(O16,"=*code*")+COUNTIF(O16,"=*software*")+COUNTIF(O16,"=*system*")+COUNTIF(O16,"=*text*")+COUNTIF(O16,"=*api*")+COUNTIF(O16,"=*cyber*") -> 1 | AJ16: =IF(AI16>0,"yes","") -> yes | AK16: =COUNTIF(O16,"=*not disclosed*") -> 0 | AL16: =IF(AK16>0,"yes","") | AM16: =IF(C16="yes",D16,"") | AN16: =IF(H16="yes",I16,"") -> 1980 | AO16: =M16 -> 2022 | AP16: =IF(C16="yes",IF(AO16=D16,"same year",IF(AO16<D16,"before",IF(AO16>D16,"after"))),"") | AQ16: =IF(C16="yes",IF(AP16="before",D16-AO16,IF(AP16="after",AO16-D16,IF(AP16="same year",0))),"") | AR16: =IF(H16="yes",IF(AO16=I16,"same year",IF(AO16<I16,"before",IF(AO16>I16,"after"))),"") -> after | AS16: =IF(H16="yes",IF(AR16="same year",0,IF(AR16="before",I16-AO16,IF(AR16="after",AO16-I16))),"") -> 42 | AT16: =IF(R16="yes",IF(AO16<2018,"before",IF(AO16=2018,"same year",IF(AO16>2018,"after"))),"") -> after | AU16: =IF(R16="yes",IF(AT16="before",2018-AO16,IF(AT16="after",AO16-2018,IF(AT16="same year",0))),"") -> 4 | AV16: =IF(F16="defunct",IF(AO16=G16,"same year",IF(AO16<G16,"before",IF(AO16>=G16,"after"))),"") | AW16: =COUNTIF(P16,"=*vuln*") -> 0 | AX16: =COUNTIF(R16,"=yes") -> 1 | AY16: Apple | AZ16: =VLOOKUP(A16,certs!U:V,2,FALSE) -> https://www.apple.com/legal/compliance/
A17: ArdyssLife | B17: =VLOOKUP(A17,industry!A:B,2,FALSE) -> Healthcare | C17: =VLOOKUP(A17,acquisitions!A:D,2,FALSE) -> No | D17: =VLOOKUP(A17,acquisitions!A:D,4,FALSE) -> N/A | E17: =VLOOKUP(A17,acquisitions!A:D,3,FALSE) -> N/A | F17: =VLOOKUP(A17,acquisitions!I:K,2,FALSE) -> Active | G17: =IF(F17="active","",VLOOKUP(A17,acquisitions!I:K,3,FALSE)) | H17: =VLOOKUP(A17,public!A:D,2,FALSE) -> No | I17: =VLOOKUP(A17,public!J:K,2,FALSE) -> #N/A | K17: =VLOOKUP(A17,public!A:D,3,FALSE) -> N/A | L17: =VLOOKUP(A17,public!A:D,4,FALSE) -> N/A | M17: 2024 | N17: Not disclosed | O17: Names, addresses, phone numbers, SSNs | P17: System Vulnerability Exploit | Q17: PCI DSS, CCPA | T17: yes | Y17: yes | AA17: =COUNTIF(O17,"=*personal*")+COUNTIF(O17,"=*ssn*")++COUNTIF(O17,"=*license*")+COUNTIF(O17,"=*email*")+COUNTIF(O17,"=*vehic*")+COUNTIF(O17,"=*profile*")+COUNTIF(O17,"=*account*")+COUNTIF(O17,"=*image*")+COUNTIF(O17,"=*phone*")+COUNTIF(O17,"=*photo*") -> 2 | AB17: =IF(AA17>0,"yes","") -> yes | AC17: =COUNTIF(O17,"=*financ*")+COUNTIF(O17,"=*card*")+COUNTIF(O17,"=*crypto*")+COUNTIF(O17,"=*bank*")+COUNTIF(O17,"=*pay*") -> 0 | AD17: =IF(AC17>0,"yes","") | AE17: =COUNTIF(O17,"=*health*")+COUNTIF(O17,"=*bio*")+COUNTIF(O17,"=*medic*")+COUNTIF(O17,"=*patient*") -> 0 | AF17: =IF(AE17>0,"yes","") | AG17: =COUNTIF(O17,"=*customer*")+COUNTIF(O17,"=*employee*")+COUNTIF(O17,"=*guest*")+COUNTIF(O17,"=*passen*")+COUNTIF(O17,"=*applicant*")+COUNTIF(O17,"=*client*") -> 0 | AH17: =IF(AG17>0,"yes","") | AI17: =COUNTIF(O17,"=*user*")+COUNTIF(O17,"=*code*")+COUNTIF(O17,"=*software*")+COUNTIF(O17,"=*system*")+COUNTIF(O17,"=*text*")+COUNTIF(O17,"=*api*")+COUNTIF(O17,"=*cyber*") -> 0 | AJ17: =IF(AI17>0,"yes","") | AK17: =COUNTIF(O17,"=*not disclosed*") -> 0 | AL17: =IF(AK17>0,"yes","") | AM17: =IF(C17="yes",D17,"") | AN17: =IF(H17="yes",I17,"") | AO17: =M17 -> 2024 | AP17: =IF(C17="yes",IF(AO17=D17,"same year",IF(AO17<D17,"before",IF(AO17>D17,"after"))),"") | AQ17: =IF(C17="yes",IF(AP17="before",D17-AO17,IF(AP17="after",AO17-D17,IF(AP17="same year",0))),"") | AR17: =IF(H17="yes",IF(AO17=I17,"same year",IF(AO17<I17,"before",IF(AO17>I17,"after"))),"") | AS17: =IF(H17="yes",IF(AR17="same year",0,IF(AR17="before",I17-AO17,IF(AR17="after",AO17-I17))),"") | AT17: =IF(R17="yes",IF(AO17<2018,"before",IF(AO17=2018,"same year",IF(AO17>2018,"after"))),"") | AU17: =IF(R17="yes",IF(AT17="before",2018-AO17,IF(AT17="after",AO17-2018,IF(AT17="same year",0))),"") | AV17: =IF(F17="defunct",IF(AO17=G17,"same year",IF(AO17<G17,"before",IF(AO17>=G17,"after"))),"") | AW17: =COUNTIF(P17,"=*vuln*") -> 1 | AX17: =COUNTIF(R17,"=yes") -> 0 | AY17: ArdyssLife | AZ17: =VLOOKUP(A17,certs!U:V,2,FALSE) -> Not Available
A18: Artech Information Systems | B18: =VLOOKUP(A18,industry!A:B,2,FALSE) -> Technology | C18: =VLOOKUP(A18,acquisitions!A:D,2,FALSE) -> No | D18: =VLOOKUP(A18,acquisitions!A:D,4,FALSE) -> N/A | E18: =VLOOKUP(A18,acquisitions!A:D,3,FALSE) -> N/A | F18: =VLOOKUP(A18,acquisitions!I:K,2,FALSE) -> Active | G18: =IF(F18="active","",VLOOKUP(A18,acquisitions!I:K,3,FALSE)) | H18: =VLOOKUP(A18,public!A:D,2,FALSE) -> No | I18: =VLOOKUP(A18,public!J:K,2,FALSE) -> #N/A | K18: =VLOOKUP(A18,public!A:D,3,FALSE) -> N/A | L18: =VLOOKUP(A18,public!A:D,4,FALSE) -> N/A | M18: 2020 | N18: 30000 | O18: Personal and financial data | P18: Software Vulnerability Exploit | Q18: GDPR | R18: yes | AA18: =COUNTIF(O18,"=*personal*")+COUNTIF(O18,"=*ssn*")++COUNTIF(O18,"=*license*")+COUNTIF(O18,"=*email*")+COUNTIF(O18,"=*vehic*")+COUNTIF(O18,"=*profile*")+COUNTIF(O18,"=*account*")+COUNTIF(O18,"=*image*")+COUNTIF(O18,"=*phone*")+COUNTIF(O18,"=*photo*") -> 1 | AB18: =IF(AA18>0,"yes","") -> yes | AC18: =COUNTIF(O18,"=*financ*")+COUNTIF(O18,"=*card*")+COUNTIF(O18,"=*crypto*")+COUNTIF(O18,"=*bank*")+COUNTIF(O18,"=*pay*") -> 1 | AD18: =IF(AC18>0,"yes","") -> yes | AE18: =COUNTIF(O18,"=*health*")+COUNTIF(O18,"=*bio*")+COUNTIF(O18,"=*medic*")+COUNTIF(O18,"=*patient*") -> 0 | AF18: =IF(AE18>0,"yes","") | AG18: =COUNTIF(O18,"=*customer*")+COUNTIF(O18,"=*employee*")+COUNTIF(O18,"=*guest*")+COUNTIF(O18,"=*passen*")+COUNTIF(O18,"=*applicant*")+COUNTIF(O18,"=*client*") -> 0 | AH18: =IF(AG18>0,"yes","") | AI18: =COUNTIF(O18,"=*user*")+COUNTIF(O18,"=*code*")+COUNTIF(O18,"=*software*")+COUNTIF(O18,"=*system*")+COUNTIF(O18,"=*text*")+COUNTIF(O18,"=*api*")+COUNTIF(O18,"=*cyber*") -> 0 | AJ18: =IF(AI18>0,"yes","") | AK18: =COUNTIF(O18,"=*not disclosed*") -> 0 | AL18: =IF(AK18>0,"yes","") | AM18: =IF(C18="yes",D18,"") | AN18: =IF(H18="yes",I18,"") | AO18: =M18 -> 2020 | AP18: =IF(C18="yes",IF(AO18=D18,"same year",IF(AO18<D18,"before",IF(AO18>D18,"after"))),"") | AQ18: =IF(C18="yes",IF(AP18="before",D18-AO18,IF(AP18="after",AO18-D18,IF(AP18="same year",0))),"") | AR18: =IF(H18="yes",IF(AO18=I18,"same year",IF(AO18<I18,"before",IF(AO18>I18,"after"))),"") | AS18: =IF(H18="yes",IF(AR18="same year",0,IF(AR18="before",I18-AO18,IF(AR18="after",AO18-I18))),"") | AT18: =IF(R18="yes",IF(AO18<2018,"before",IF(AO18=2018,"same year",IF(AO18>2018,"after"))),"") -> after | AU18: =IF(R18="yes",IF(AT18="before",2018-AO18,IF(AT18="after",AO18-2018,IF(AT18="same year",0))),"") -> 2 | AV18: =IF(F18="defunct",IF(AO18=G18,"same year",IF(AO18<G18,"before",IF(AO18>=G18,"after"))),"") | AW18: =COUNTIF(P18,"=*vuln*") -> 1 | AX18: =COUNTIF(R18,"=yes") -> 1 | AY18: Artech Information Systems | AZ18: =VLOOKUP(A18,certs!U:V,2,FALSE) -> Not Available
A19: Astoria Company | B19: =VLOOKUP(A19,industry!A:B,2,FALSE) -> Marketing | C19: =VLOOKUP(A19,acquisitions!A:D,2,FALSE) -> No | D19: =VLOOKUP(A19,acquisitions!A:D,4,FALSE) -> N/A | E19: =VLOOKUP(A19,acquisitions!A:D,3,FALSE) -> N/A | F19: =VLOOKUP(A19,acquisitions!I:K,2,FALSE) -> Active | G19: =IF(F19="active","",VLOOKUP(A19,acquisitions!I:K,3,FALSE)) | H19: =VLOOKUP(A19,public!A:D,2,FALSE) -> No | I19: =VLOOKUP(A19,public!J:K,2,FALSE) -> #N/A | K19: =VLOOKUP(A19,public!A:D,3,FALSE) -> N/A | L19: =VLOOKUP(A19,public!A:D,4,FALSE) -> N/A | M19: 2018 | N19: 340000000 | O19: Personal data profiles | P19: Misonfigured Server | Q19: GDPR | R19: yes | AA19: =COUNTIF(O19,"=*personal*")+COUNTIF(O19,"=*ssn*")++COUNTIF(O19,"=*license*")+COUNTIF(O19,"=*email*")+COUNTIF(O19,"=*vehic*")+COUNTIF(O19,"=*profile*")+COUNTIF(O19,"=*account*")+COUNTIF(O19,"=*image*")+COUNTIF(O19,"=*phone*")+COUNTIF(O19,"=*photo*") -> 2 | AB19: =IF(AA19>0,"yes","") -> yes | AC19: =COUNTIF(O19,"=*financ*")+COUNTIF(O19,"=*card*")+COUNTIF(O19,"=*crypto*")+COUNTIF(O19,"=*bank*")+COUNTIF(O19,"=*pay*") -> 0 | AD19: =IF(AC19>0,"yes","") | AE19: =COUNTIF(O19,"=*health*")+COUNTIF(O19,"=*bio*")+COUNTIF(O19,"=*medic*")+COUNTIF(O19,"=*patient*") -> 0 | AF19: =IF(AE19>0,"yes","") | AG19: =COUNTIF(O19,"=*customer*")+COUNTIF(O19,"=*employee*")+COUNTIF(O19,"=*guest*")+COUNTIF(O19,"=*passen*")+COUNTIF(O19,"=*applicant*")+COUNTIF(O19,"=*client*") -> 0 | AH19: =IF(AG19>0,"yes","") | AI19: =COUNTIF(O19,"=*user*")+COUNTIF(O19,"=*code*")+COUNTIF(O19,"=*software*")+COUNTIF(O19,"=*system*")+COUNTIF(O19,"=*text*")+COUNTIF(O19,"=*api*")+COUNTIF(O19,"=*cyber*") -> 0 | AJ19: =IF(AI19>0,"yes","") | AK19: =COUNTIF(O19,"=*not disclosed*") -> 0 | AL19: =IF(AK19>0,"yes","") | AM19: =IF(C19="yes",D19,"") | AN19: =IF(H19="yes",I19,"") | AO19: =M19 -> 2018 | AP19: =IF(C19="yes",IF(AO19=D19,"same year",IF(AO19<D19,"before",IF(AO19>D19,"after"))),"") | AQ19: =IF(C19="yes",IF(AP19="before",D19-AO19,IF(AP19="after",AO19-D19,IF(AP19="same year",0))),"") | AR19: =IF(H19="yes",IF(AO19=I19,"same year",IF(AO19<I19,"before",IF(AO19>I19,"after"))),"") | AS19: =IF(H19="yes",IF(AR19="same year",0,IF(AR19="before",I19-AO19,IF(AR19="after",AO19-I19))),"") | AT19: =IF(R19="yes",IF(AO19<2018,"before",IF(AO19=2018,"same year",IF(AO19>2018,"after"))),"") -> same year | AU19: =IF(R19="yes",IF(AT19="before",2018-AO19,IF(AT19="after",AO19-2018,IF(AT19="same year",0))),"") -> 0 | AV19: =IF(F19="defunct",IF(AO19=G19,"same year",IF(AO19<G19,"before",IF(AO19>=G19,"after"))),"") | AW19: =COUNTIF(P19,"=*vuln*") -> 0 | AX19: =COUNTIF(R19,"=yes") -> 1 | AY19: Astoria Company | AZ19: =VLOOKUP(A19,certs!U:V,2,FALSE) -> https://astoria.company/legal/compliance
A20: Astoria Company | B20: =VLOOKUP(A20,industry!A:B,2,FALSE) -> Marketing | C20: =VLOOKUP(A20,acquisitions!A:D,2,FALSE) -> No | D20: =VLOOKUP(A20,acquisitions!A:D,4,FALSE) -> N/A | E20: =VLOOKUP(A20,acquisitions!A:D,3,FALSE) -> N/A | F20: =VLOOKUP(A20,acquisitions!I:K,2,FALSE) -> Active | G20: =IF(F20="active","",VLOOKUP(A20,acquisitions!I:K,3,FALSE)) | H20: =VLOOKUP(A20,public!A:D,2,FALSE) -> No | I20: =VLOOKUP(A20,public!J:K,2,FALSE) -> #N/A | K20: =VLOOKUP(A20,public!A:D,3,FALSE) -> N/A | L20: =VLOOKUP(A20,public!A:D,4,FALSE) -> N/A | M20: 2021 | N20: 30000000 | O20: Personal data profiles | P20: Malware | Q20: GDPR | R20: yes | AA20: =COUNTIF(O20,"=*personal*")+COUNTIF(O20,"=*ssn*")++COUNTIF(O20,"=*license*")+COUNTIF(O20,"=*email*")+COUNTIF(O20,"=*vehic*")+COUNTIF(O20,"=*profile*")+COUNTIF(O20,"=*account*")+COUNTIF(O20,"=*image*")+COUNTIF(O20,"=*phone*")+COUNTIF(O20,"=*photo*") -> 2 | AB20: =IF(AA20>0,"yes","") -> yes | AC20: =COUNTIF(O20,"=*financ*")+COUNTIF(O20,"=*card*")+COUNTIF(O20,"=*crypto*")+COUNTIF(O20,"=*bank*")+COUNTIF(O20,"=*pay*") -> 0 | AD20: =IF(AC20>0,"yes","") | AE20: =COUNTIF(O20,"=*health*")+COUNTIF(O20,"=*bio*")+COUNTIF(O20,"=*medic*")+COUNTIF(O20,"=*patient*") -> 0 | AF20: =IF(AE20>0,"yes","") | AG20: =COUNTIF(O20,"=*customer*")+COUNTIF(O20,"=*employee*")+COUNTIF(O20,"=*guest*")+COUNTIF(O20,"=*passen*")+COUNTIF(O20,"=*applicant*")+COUNTIF(O20,"=*client*") -> 0 | AH20: =IF(AG20>0,"yes","") | AI20: =COUNTIF(O20,"=*user*")+COUNTIF(O20,"=*code*")+COUNTIF(O20,"=*software*")+COUNTIF(O20,"=*system*")+COUNTIF(O20,"=*text*")+COUNTIF(O20,"=*api*")+COUNTIF(O20,"=*cyber*") -> 0 | AJ20: =IF(AI20>0,"yes","") | AK20: =COUNTIF(O20,"=*not disclosed*") -> 0 | AL20: =IF(AK20>0,"yes","") | AM20: =IF(C20="yes",D20,"") | AN20: =IF(H20="yes",I20,"") | AO20: =M20 -> 2021 | AP20: =IF(C20="yes",IF(AO20=D20,"same year",IF(AO20<D20,"before",IF(AO20>D20,"after"))),"") | AQ20: =IF(C20="yes",IF(AP20="before",D20-AO20,IF(AP20="after",AO20-D20,IF(AP20="same year",0))),"") | AR20: =IF(H20="yes",IF(AO20=I20,"same year",IF(AO20<I20,"before",IF(AO20>I20,"after"))),"") | AS20: =IF(H20="yes",IF(AR20="same year",0,IF(AR20="before",I20-AO20,IF(AR20="after",AO20-I20))),"") | AT20: =IF(R20="yes",IF(AO20<2018,"before",IF(AO20=2018,"same year",IF(AO20>2018,"after"))),"") -> after | AU20: =IF(R20="yes",IF(AT20="before",2018-AO20,IF(AT20="after",AO20-2018,IF(AT20="same year",0))),"") -> 3 | AV20: =IF(F20="defunct",IF(AO20=G20,"same year",IF(AO20<G20,"before",IF(AO20>=G20,"after"))),"") | AW20: =COUNTIF(P20,"=*vuln*") -> 0 | AX20: =COUNTIF(R20,"=yes") -> 1 | AY20: Astoria Company | AZ20: =VLOOKUP(A20,certs!U:V,2,FALSE) -> https://astoria.company/legal/compliance
A21: AT&T | B21: =VLOOKUP(A21,industry!A:B,2,FALSE) -> Telecommunications | C21: =VLOOKUP(A21,acquisitions!A:D,2,FALSE) -> No | D21: =VLOOKUP(A21,acquisitions!A:D,4,FALSE) -> N/A | E21: =VLOOKUP(A21,acquisitions!A:D,3,FALSE) -> N/A | F21: =VLOOKUP(A21,acquisitions!I:K,2,FALSE) -> Active | G21: =IF(F21="active","",VLOOKUP(A21,acquisitions!I:K,3,FALSE)) | H21: =VLOOKUP(A21,public!A:D,2,FALSE) -> Yes | I21: =VLOOKUP(A21,public!J:K,2,FALSE) -> 1984 | J21: =VLOOKUP(A21,'net worth'!B:C,2,FALSE) -> 198360000000 | K21: =VLOOKUP(A21,public!A:D,3,FALSE) -> NYSE | L21: =VLOOKUP(A21,public!A:D,4,FALSE) -> T | M21: 2021 | N21: Unknown | O21: Customer proprietary network information | P21: Misconfigured Cloud Storage | Q21: CCPA, GDPR | R21: yes | Y21: yes | AA21: =COUNTIF(O21,"=*personal*")+COUNTIF(O21,"=*ssn*")++COUNTIF(O21,"=*license*")+COUNTIF(O21,"=*email*")+COUNTIF(O21,"=*vehic*")+COUNTIF(O21,"=*profile*")+COUNTIF(O21,"=*account*")+COUNTIF(O21,"=*image*")+COUNTIF(O21,"=*phone*")+COUNTIF(O21,"=*photo*") -> 0 | AB21: =IF(AA21>0,"yes","") | AC21: =COUNTIF(O21,"=*financ*")+COUNTIF(O21,"=*card*")+COUNTIF(O21,"=*crypto*")+COUNTIF(O21,"=*bank*")+COUNTIF(O21,"=*pay*") -> 0 | AD21: =IF(AC21>0,"yes","") | AE21: =COUNTIF(O21,"=*health*")+COUNTIF(O21,"=*bio*")+COUNTIF(O21,"=*medic*")+COUNTIF(O21,"=*patient*") -> 0 | AF21: =IF(AE21>0,"yes","") | AG21: =COUNTIF(O21,"=*customer*")+COUNTIF(O21,"=*employee*")+COUNTIF(O21,"=*guest*")+COUNTIF(O21,"=*passen*")+COUNTIF(O21,"=*applicant*")+COUNTIF(O21,"=*client*") -> 1 | AH21: =IF(AG21>0,"yes","") -> yes | AI21: =COUNTIF(O21,"=*user*")+COUNTIF(O21,"=*code*")+COUNTIF(O21,"=*software*")+COUNTIF(O21,"=*system*")+COUNTIF(O21,"=*text*")+COUNTIF(O21,"=*api*")+COUNTIF(O21,"=*cyber*") -> 0 | AJ21: =IF(AI21>0,"yes","") | AK21: =COUNTIF(O21,"=*not disclosed*") -> 0 | AL21: =IF(AK21>0,"yes","") | AM21: =IF(C21="yes",D21,"") | AN21: =IF(H21="yes",I21,"") -> 1984 | AO21: =M21 -> 2021 | AP21: =IF(C21="yes",IF(AO21=D21,"same year",IF(AO21<D21,"before",IF(AO21>D21,"after"))),"") | AQ21: =IF(C21="yes",IF(AP21="before",D21-AO21,IF(AP21="after",AO21-D21,IF(AP21="same year",0))),"") | AR21: =IF(H21="yes",IF(AO21=I21,"same year",IF(AO21<I21,"before",IF(AO21>I21,"after"))),"") -> after | AS21: =IF(H21="yes",IF(AR21="same year",0,IF(AR21="before",I21-AO21,IF(AR21="after",AO21-I21))),"") -> 37 | AT21: =IF(R21="yes",IF(AO21<2018,"before",IF(AO21=2018,"same year",IF(AO21>2018,"after"))),"") -> after | AU21: =IF(R21="yes",IF(AT21="before",2018-AO21,IF(AT21="after",AO21-2018,IF(AT21="same year",0))),"") -> 3 | AV21: =IF(F21="defunct",IF(AO21=G21,"same year",IF(AO21<G21,"before",IF(AO21>=G21,"after"))),"") | AW21: =COUNTIF(P21,"=*vuln*") -> 0 | AX21: =COUNTIF(R21,"=yes") -> 1 | AY21: AT&T | AZ21: =VLOOKUP(A21,certs!U:V,2,FALSE) -> https://about.att.com/site/about/us/legal_and_compliance.html
A22: AT&T | B22: =VLOOKUP(A22,industry!A:B,2,FALSE) -> Telecommunications | C22: =VLOOKUP(A22,acquisitions!A:D,2,FALSE) -> No | D22: =VLOOKUP(A22,acquisitions!A:D,4,FALSE) -> N/A | E22: =VLOOKUP(A22,acquisitions!A:D,3,FALSE) -> N/A | F22: =VLOOKUP(A22,acquisitions!I:K,2,FALSE) -> Active | G22: =IF(F22="active","",VLOOKUP(A22,acquisitions!I:K,3,FALSE)) | H22: =VLOOKUP(A22,public!A:D,2,FALSE) -> Yes | I22: =VLOOKUP(A22,public!J:K,2,FALSE) -> 1984 | J22: =VLOOKUP(A22,'net worth'!B:C,2,FALSE) -> 198360000000 | K22: =VLOOKUP(A22,public!A:D,3,FALSE) -> NYSE | L22: =VLOOKUP(A22,public!A:D,4,FALSE) -> T | M22: 2024 | N22: 73000000 | O22: Call and text records | P22: Misconfigured Cloud Storage | Q22: PCI DSS, CCPA, GDPR | R22: yes | T22: yes | Y22: yes | AA22: =COUNTIF(O22,"=*personal*")+COUNTIF(O22,"=*ssn*")++COUNTIF(O22,"=*license*")+COUNTIF(O22,"=*email*")+COUNTIF(O22,"=*vehic*")+COUNTIF(O22,"=*profile*")+COUNTIF(O22,"=*account*")+COUNTIF(O22,"=*image*")+COUNTIF(O22,"=*phone*")+COUNTIF(O22,"=*photo*") -> 0 | AB22: =IF(AA22>0,"yes","") | AC22: =COUNTIF(O22,"=*financ*")+COUNTIF(O22,"=*card*")+COUNTIF(O22,"=*crypto*")+COUNTIF(O22,"=*bank*")+COUNTIF(O22,"=*pay*") -> 0 | AD22: =IF(AC22>0,"yes","") | AE22: =COUNTIF(O22,"=*health*")+COUNTIF(O22,"=*bio*")+COUNTIF(O22,"=*medic*")+COUNTIF(O22,"=*patient*") -> 0 | AF22: =IF(AE22>0,"yes","") | AG22: =COUNTIF(O22,"=*customer*")+COUNTIF(O22,"=*employee*")+COUNTIF(O22,"=*guest*")+COUNTIF(O22,"=*passen*")+COUNTIF(O22,"=*applicant*")+COUNTIF(O22,"=*client*") -> 0 | AH22: =IF(AG22>0,"yes","") | AI22: =COUNTIF(O22,"=*user*")+COUNTIF(O22,"=*code*")+COUNTIF(O22,"=*software*")+COUNTIF(O22,"=*system*")+COUNTIF(O22,"=*text*")+COUNTIF(O22,"=*api*")+COUNTIF(O22,"=*cyber*") -> 1 | AJ22: =IF(AI22>0,"yes","") -> yes | AK22: =COUNTIF(O22,"=*not disclosed*") -> 0 | AL22: =IF(AK22>0,"yes","") | AM22: =IF(C22="yes",D22,"") | AN22: =IF(H22="yes",I22,"") -> 1984 | AO22: =M22 -> 2024 | AP22: =IF(C22="yes",IF(AO22=D22,"same year",IF(AO22<D22,"before",IF(AO22>D22,"after"))),"") | AQ22: =IF(C22="yes",IF(AP22="before",D22-AO22,IF(AP22="after",AO22-D22,IF(AP22="same year",0))),"") | AR22: =IF(H22="yes",IF(AO22=I22,"same year",IF(AO22<I22,"before",IF(AO22>I22,"after"))),"") -> after | AS22: =IF(H22="yes",IF(AR22="same year",0,IF(AR22="before",I22-AO22,IF(AR22="after",AO22-I22))),"") -> 40 | AT22: =IF(R22="yes",IF(AO22<2018,"before",IF(AO22=2018,"same year",IF(AO22>2018,"after"))),"") -> after | AU22: =IF(R22="yes",IF(AT22="before",2018-AO22,IF(AT22="after",AO22-2018,IF(AT22="same year",0))),"") -> 6 | AV22: =IF(F22="defunct",IF(AO22=G22,"same year",IF(AO22<G22,"before",IF(AO22>=G22,"after"))),"") | AW22: =COUNTIF(P22,"=*vuln*") -> 0 | AX22: =COUNTIF(R22,"=yes") -> 1 | AY22: AT&T | AZ22: =VLOOKUP(A22,certs!U:V,2,FALSE) -> https://about.att.com/site/about/us/legal_and_compliance.html
A23: Belden | B23: =VLOOKUP(A23,industry!A:B,2,FALSE) -> Electronics | C23: =VLOOKUP(A23,acquisitions!A:D,2,FALSE) -> No | D23: =VLOOKUP(A23,acquisitions!A:D,4,FALSE) -> N/A | E23: =VLOOKUP(A23,acquisitions!A:D,3,FALSE) -> N/A | F23: =VLOOKUP(A23,acquisitions!I:K,2,FALSE) -> Active | G23: =IF(F23="active","",VLOOKUP(A23,acquisitions!I:K,3,FALSE)) | H23: =VLOOKUP(A23,public!A:D,2,FALSE) -> Yes | I23: =VLOOKUP(A23,public!J:K,2,FALSE) -> 1980 | J23: =VLOOKUP(A23,'net worth'!B:C,2,FALSE) -> 3620000000 | K23: =VLOOKUP(A23,public!A:D,3,FALSE) -> NYSE | L23: =VLOOKUP(A23,public!A:D,4,FALSE) -> BDC | M23: 2020 | N23: Unknown | O23: Employee and business data | P23: Phishing | Q23: GDPR | R23: yes | AA23: =COUNTIF(O23,"=*personal*")+COUNTIF(O23,"=*ssn*")++COUNTIF(O23,"=*license*")+COUNTIF(O23,"=*email*")+COUNTIF(O23,"=*vehic*")+COUNTIF(O23,"=*profile*")+COUNTIF(O23,"=*account*")+COUNTIF(O23,"=*image*")+COUNTIF(O23,"=*phone*")+COUNTIF(O23,"=*photo*") -> 0 | AB23: =IF(AA23>0,"yes","") | AC23: =COUNTIF(O23,"=*financ*")+COUNTIF(O23,"=*card*")+COUNTIF(O23,"=*crypto*")+COUNTIF(O23,"=*bank*")+COUNTIF(O23,"=*pay*") -> 0 | AD23: =IF(AC23>0,"yes","") | AE23: =COUNTIF(O23,"=*health*")+COUNTIF(O23,"=*bio*")+COUNTIF(O23,"=*medic*")+COUNTIF(O23,"=*patient*") -> 0 | AF23: =IF(AE23>0,"yes","") | AG23: =COUNTIF(O23,"=*customer*")+COUNTIF(O23,"=*employee*")+COUNTIF(O23,"=*guest*")+COUNTIF(O23,"=*passen*")+COUNTIF(O23,"=*applicant*")+COUNTIF(O23,"=*client*") -> 1 | AH23: =IF(AG23>0,"yes","") -> yes | AI23: =COUNTIF(O23,"=*user*")+COUNTIF(O23,"=*code*")+COUNTIF(O23,"=*software*")+COUNTIF(O23,"=*system*")+COUNTIF(O23,"=*text*")+COUNTIF(O23,"=*api*")+COUNTIF(O23,"=*cyber*") -> 0 | AJ23: =IF(AI23>0,"yes","") | AK23: =COUNTIF(O23,"=*not disclosed*") -> 0 | AL23: =IF(AK23>0,"yes","") | AM23: =IF(C23="yes",D23,"") | AN23: =IF(H23="yes",I23,"") -> 1980 | AO23: =M23 -> 2020 | AP23: =IF(C23="yes",IF(AO23=D23,"same year",IF(AO23<D23,"before",IF(AO23>D23,"after"))),"") | AQ23: =IF(C23="yes",IF(AP23="before",D23-AO23,IF(AP23="after",AO23-D23,IF(AP23="same year",0))),"") | AR23: =IF(H23="yes",IF(AO23=I23,"same year",IF(AO23<I23,"before",IF(AO23>I23,"after"))),"") -> after | AS23: =IF(H23="yes",IF(AR23="same year",0,IF(AR23="before",I23-AO23,IF(AR23="after",AO23-I23))),"") -> 40 | AT23: =IF(R23="yes",IF(AO23<2018,"before",IF(AO23=2018,"same year",IF(AO23>2018,"after"))),"") -> after | AU23: =IF(R23="yes",IF(AT23="before",2018-AO23,IF(AT23="after",AO23-2018,IF(AT23="same year",0))),"") -> 2 | AV23: =IF(F23="defunct",IF(AO23=G23,"same year",IF(AO23<G23,"before",IF(AO23>=G23,"after"))),"") | AW23: =COUNTIF(P23,"=*vuln*") -> 0 | AX23: =COUNTIF(R23,"=yes") -> 1 | AY23: Belden | AZ23: =VLOOKUP(A23,certs!U:V,2,FALSE) -> https://www.belden.com/legal/compliance
A24: bevital GmbH | B24: =VLOOKUP(A24,industry!A:B,2,FALSE) -> Healthcare | C24: =VLOOKUP(A24,acquisitions!A:D,2,FALSE) -> No | D24: =VLOOKUP(A24,acquisitions!A:D,4,FALSE) -> N/A | E24: =VLOOKUP(A24,acquisitions!A:D,3,FALSE) -> N/A | F24: =VLOOKUP(A24,acquisitions!I:K,2,FALSE) -> Active | G24: =IF(F24="active","",VLOOKUP(A24,acquisitions!I:K,3,FALSE)) | H24: =VLOOKUP(A24,public!A:D,2,FALSE) -> No | I24: =VLOOKUP(A24,public!J:K,2,FALSE) -> #N/A | K24: =VLOOKUP(A24,public!A:D,3,FALSE) -> N/A | L24: =VLOOKUP(A24,public!A:D,4,FALSE) -> N/A | M24: 2020 | N24: 20000 | O24: Customer personal and health data | P24: Ransomware | Q24: GDPR | R24: yes | AA24: =COUNTIF(O24,"=*personal*")+COUNTIF(O24,"=*ssn*")++COUNTIF(O24,"=*license*")+COUNTIF(O24,"=*email*")+COUNTIF(O24,"=*vehic*")+COUNTIF(O24,"=*profile*")+COUNTIF(O24,"=*account*")+COUNTIF(O24,"=*image*")+COUNTIF(O24,"=*phone*")+COUNTIF(O24,"=*photo*") -> 1 | AB24: =IF(AA24>0,"yes","") -> yes | AC24: =COUNTIF(O24,"=*financ*")+COUNTIF(O24,"=*card*")+COUNTIF(O24,"=*crypto*")+COUNTIF(O24,"=*bank*")+COUNTIF(O24,"=*pay*") -> 0 | AD24: =IF(AC24>0,"yes","") | AE24: =COUNTIF(O24,"=*health*")+COUNTIF(O24,"=*bio*")+COUNTIF(O24,"=*medic*")+COUNTIF(O24,"=*patient*") -> 1 | AF24: =IF(AE24>0,"yes","") -> yes | AG24: =COUNTIF(O24,"=*customer*")+COUNTIF(O24,"=*employee*")+COUNTIF(O24,"=*guest*")+COUNTIF(O24,"=*passen*")+COUNTIF(O24,"=*applicant*")+COUNTIF(O24,"=*client*") -> 1 | AH24: =IF(AG24>0,"yes","") -> yes | AI24: =COUNTIF(O24,"=*user*")+COUNTIF(O24,"=*code*")+COUNTIF(O24,"=*software*")+COUNTIF(O24,"=*system*")+COUNTIF(O24,"=*text*")+COUNTIF(O24,"=*api*")+COUNTIF(O24,"=*cyber*") -> 0 | AJ24: =IF(AI24>0,"yes","") | AK24: =COUNTIF(O24,"=*not disclosed*") -> 0 | AL24: =IF(AK24>0,"yes","") | AM24: =IF(C24="yes",D24,"") | AN24: =IF(H24="yes",I24,"") | AO24: =M24 -> 2020 | AP24: =IF(C24="yes",IF(AO24=D24,"same year",IF(AO24<D24,"before",IF(AO24>D24,"after"))),"") | AQ24: =IF(C24="yes",IF(AP24="before",D24-AO24,IF(AP24="after",AO24-D24,IF(AP24="same year",0))),"") | AR24: =IF(H24="yes",IF(AO24=I24,"same year",IF(AO24<I24,"before",IF(AO24>I24,"after"))),"") | AS24: =IF(H24="yes",IF(AR24="same year",0,IF(AR24="before",I24-AO24,IF(AR24="after",AO24-I24))),"") | AT24: =IF(R24="yes",IF(AO24<2018,"before",IF(AO24=2018,"same year",IF(AO24>2018,"after"))),"") -> after | AU24: =IF(R24="yes",IF(AT24="before",2018-AO24,IF(AT24="after",AO24-2018,IF(AT24="same year",0))),"") -> 2 | AV24: =IF(F24="defunct",IF(AO24=G24,"same year",IF(AO24<G24,"before",IF(AO24>=G24,"after"))),"") | AW24: =COUNTIF(P24,"=*vuln*") -> 0 | AX24: =COUNTIF(R24,"=yes") -> 1 | AY24: bevital GmbH | AZ24: =VLOOKUP(A24,certs!U:V,2,FALSE) -> Not Available
A25: BigBasket | B25: =VLOOKUP(A25,industry!A:B,2,FALSE) -> Retail | C25: =VLOOKUP(A25,acquisitions!A:D,2,FALSE) -> Yes | D25: =VLOOKUP(A25,acquisitions!A:D,4,FALSE) -> 2021 | E25: =VLOOKUP(A25,acquisitions!A:D,3,FALSE) -> Tata Group | F25: =VLOOKUP(A25,acquisitions!I:K,2,FALSE) -> Active | G25: =IF(F25="active","",VLOOKUP(A25,acquisitions!I:K,3,FALSE)) | H25: =VLOOKUP(A25,public!A:D,2,FALSE) -> No | I25: =VLOOKUP(A25,public!J:K,2,FALSE) -> #N/A | K25: =VLOOKUP(A25,public!A:D,3,FALSE) -> N/A | L25: =VLOOKUP(A25,public!A:D,4,FALSE) -> N/A | M25: 2020 | N25: 20000000 | O25: Customer data, emails, phone numbers | P25: Unsecured database | Q25: GDPR | R25: yes | AA25: =COUNTIF(O25,"=*personal*")+COUNTIF(O25,"=*ssn*")++COUNTIF(O25,"=*license*")+COUNTIF(O25,"=*email*")+COUNTIF(O25,"=*vehic*")+COUNTIF(O25,"=*profile*")+COUNTIF(O25,"=*account*")+COUNTIF(O25,"=*image*")+COUNTIF(O25,"=*phone*")+COUNTIF(O25,"=*photo*") -> 2 | AB25: =IF(AA25>0,"yes","") -> yes | AC25: =COUNTIF(O25,"=*financ*")+COUNTIF(O25,"=*card*")+COUNTIF(O25,"=*crypto*")+COUNTIF(O25,"=*bank*")+COUNTIF(O25,"=*pay*") -> 0 | AD25: =IF(AC25>0,"yes","") | AE25: =COUNTIF(O25,"=*health*")+COUNTIF(O25,"=*bio*")+COUNTIF(O25,"=*medic*")+COUNTIF(O25,"=*patient*") -> 0 | AF25: =IF(AE25>0,"yes","") | AG25: =COUNTIF(O25,"=*customer*")+COUNTIF(O25,"=*employee*")+COUNTIF(O25,"=*guest*")+COUNTIF(O25,"=*passen*")+COUNTIF(O25,"=*applicant*")+COUNTIF(O25,"=*client*") -> 1 | AH25: =IF(AG25>0,"yes","") -> yes | AI25: =COUNTIF(O25,"=*user*")+COUNTIF(O25,"=*code*")+COUNTIF(O25,"=*software*")+COUNTIF(O25,"=*system*")+COUNTIF(O25,"=*text*")+COUNTIF(O25,"=*api*")+COUNTIF(O25,"=*cyber*") -> 0 | AJ25: =IF(AI25>0,"yes","") | AK25: =COUNTIF(O25,"=*not disclosed*") -> 0 | AL25: =IF(AK25>0,"yes","") | AM25: =IF(C25="yes",D25,"") -> 2021 | AN25: =IF(H25="yes",I25,"") | AO25: =M25 -> 2020 | AP25: =IF(C25="yes",IF(AO25=D25,"same year",IF(AO25<D25,"before",IF(AO25>D25,"after"))),"") -> before | AQ25: =IF(C25="yes",IF(AP25="before",D25-AO25,IF(AP25="after",AO25-D25,IF(AP25="same year",0))),"") -> 1 | AR25: =IF(H25="yes",IF(AO25=I25,"same year",IF(AO25<I25,"before",IF(AO25>I25,"after"))),"") | AS25: =IF(H25="yes",IF(AR25="same year",0,IF(AR25="before",I25-AO25,IF(AR25="after",AO25-I25))),"") | AT25: =IF(R25="yes",IF(AO25<2018,"before",IF(AO25=2018,"same year",IF(AO25>2018,"after"))),"") -> after | AU25: =IF(R25="yes",IF(AT25="before",2018-AO25,IF(AT25="after",AO25-2018,IF(AT25="same year",0))),"") -> 2 | AV25: =IF(F25="defunct",IF(AO25=G25,"same year",IF(AO25<G25,"before",IF(AO25>=G25,"after"))),"") | AW25: =COUNTIF(P25,"=*vuln*") -> 0 | AX25: =COUNTIF(R25,"=yes") -> 1 | AY25: BigBasket | AZ25: =VLOOKUP(A25,certs!U:V,2,FALSE) -> https://www.bigbasket.com/compliance
A26: BioStar 2 | B26: =VLOOKUP(A26,industry!A:B,2,FALSE) -> Technology | C26: =VLOOKUP(A26,acquisitions!A:D,2,FALSE) -> No | D26: =VLOOKUP(A26,acquisitions!A:D,4,FALSE) -> N/A | E26: =VLOOKUP(A26,acquisitions!A:D,3,FALSE) -> N/A | F26: =VLOOKUP(A26,acquisitions!I:K,2,FALSE) -> Active | G26: =IF(F26="active","",VLOOKUP(A26,acquisitions!I:K,3,FALSE)) | H26: =VLOOKUP(A26,public!A:D,2,FALSE) -> No | I26: =VLOOKUP(A26,public!J:K,2,FALSE) -> #N/A | K26: =VLOOKUP(A26,public!A:D,3,FALSE) -> N/A | L26: =VLOOKUP(A26,public!A:D,4,FALSE) -> N/A | M26: 2019 | N26: 28000000 | O26: Biometric data (fingerprints, facial recognition) | P26: Database Vulnerability Exploit | Q26: GDPR | R26: yes | AA26: =COUNTIF(O26,"=*personal*")+COUNTIF(O26,"=*ssn*")++COUNTIF(O26,"=*license*")+COUNTIF(O26,"=*email*")+COUNTIF(O26,"=*vehic*")+COUNTIF(O26,"=*profile*")+COUNTIF(O26,"=*account*")+COUNTIF(O26,"=*image*")+COUNTIF(O26,"=*phone*")+COUNTIF(O26,"=*photo*") -> 0 | AB26: =IF(AA26>0,"yes","") | AC26: =COUNTIF(O26,"=*financ*")+COUNTIF(O26,"=*card*")+COUNTIF(O26,"=*crypto*")+COUNTIF(O26,"=*bank*")+COUNTIF(O26,"=*pay*") -> 0 | AD26: =IF(AC26>0,"yes","") | AE26: =COUNTIF(O26,"=*health*")+COUNTIF(O26,"=*bio*")+COUNTIF(O26,"=*medic*")+COUNTIF(O26,"=*patient*") -> 1 | AF26: =IF(AE26>0,"yes","") -> yes | AG26: =COUNTIF(O26,"=*customer*")+COUNTIF(O26,"=*employee*")+COUNTIF(O26,"=*guest*")+COUNTIF(O26,"=*passen*")+COUNTIF(O26,"=*applicant*")+COUNTIF(O26,"=*client*") -> 0 | AH26: =IF(AG26>0,"yes","") | AI26: =COUNTIF(O26,"=*user*")+COUNTIF(O26,"=*code*")+COUNTIF(O26,"=*software*")+COUNTIF(O26,"=*system*")+COUNTIF(O26,"=*text*")+COUNTIF(O26,"=*api*")+COUNTIF(O26,"=*cyber*") -> 0 | AJ26: =IF(AI26>0,"yes","") | AK26: =COUNTIF(O26,"=*not disclosed*") -> 0 | AL26: =IF(AK26>0,"yes","") | AM26: =IF(C26="yes",D26,"") | AN26: =IF(H26="yes",I26,"") | AO26: =M26 -> 2019 | AP26: =IF(C26="yes",IF(AO26=D26,"same year",IF(AO26<D26,"before",IF(AO26>D26,"after"))),"") | AQ26: =IF(C26="yes",IF(AP26="before",D26-AO26,IF(AP26="after",AO26-D26,IF(AP26="same year",0))),"") | AR26: =IF(H26="yes",IF(AO26=I26,"same year",IF(AO26<I26,"before",IF(AO26>I26,"after"))),"") | AS26: =IF(H26="yes",IF(AR26="same year",0,IF(AR26="before",I26-AO26,IF(AR26="after",AO26-I26))),"") | AT26: =IF(R26="yes",IF(AO26<2018,"before",IF(AO26=2018,"same year",IF(AO26>2018,"after"))),"") -> after | AU26: =IF(R26="yes",IF(AT26="before",2018-AO26,IF(AT26="after",AO26-2018,IF(AT26="same year",0))),"") -> 1 | AV26: =IF(F26="defunct",IF(AO26=G26,"same year",IF(AO26<G26,"before",IF(AO26>=G26,"after"))),"") | AW26: =COUNTIF(P26,"=*vuln*") -> 1 | AX26: =COUNTIF(R26,"=yes") -> 1 | AY26: BioStar 2 | AZ26: =VLOOKUP(A26,certs!U:V,2,FALSE) -> https://www.supremainc.com/en/util/compliance.asp
A27: BlueKai | B27: =VLOOKUP(A27,industry!A:B,2,FALSE) -> Technology | C27: =VLOOKUP(A27,acquisitions!A:D,2,FALSE) -> Yes | D27: =VLOOKUP(A27,acquisitions!A:D,4,FALSE) -> 2014 | E27: =VLOOKUP(A27,acquisitions!A:D,3,FALSE) -> Oracle | F27: =VLOOKUP(A27,acquisitions!I:K,2,FALSE) -> Active | G27: =IF(F27="active","",VLOOKUP(A27,acquisitions!I:K,3,FALSE)) | H27: =VLOOKUP(A27,public!A:D,2,FALSE) -> No | I27: =VLOOKUP(A27,public!J:K,2,FALSE) -> #N/A | K27: =VLOOKUP(A27,public!A:D,3,FALSE) -> N/A | L27: =VLOOKUP(A27,public!A:D,4,FALSE) -> N/A | M27: 2023 | N27: Not disclosed | O27: Names, emails, browsing data | P27: Misconfigured Database | Q27: CCPA, GDPR | R27: yes | Y27: yes | AA27: =COUNTIF(O27,"=*personal*")+COUNTIF(O27,"=*ssn*")++COUNTIF(O27,"=*license*")+COUNTIF(O27,"=*email*")+COUNTIF(O27,"=*vehic*")+COUNTIF(O27,"=*profile*")+COUNTIF(O27,"=*account*")+COUNTIF(O27,"=*image*")+COUNTIF(O27,"=*phone*")+COUNTIF(O27,"=*photo*") -> 1 | AB27: =IF(AA27>0,"yes","") -> yes | AC27: =COUNTIF(O27,"=*financ*")+COUNTIF(O27,"=*card*")+COUNTIF(O27,"=*crypto*")+COUNTIF(O27,"=*bank*")+COUNTIF(O27,"=*pay*") -> 0 | AD27: =IF(AC27>0,"yes","") | AE27: =COUNTIF(O27,"=*health*")+COUNTIF(O27,"=*bio*")+COUNTIF(O27,"=*medic*")+COUNTIF(O27,"=*patient*") -> 0 | AF27: =IF(AE27>0,"yes","") | AG27: =COUNTIF(O27,"=*customer*")+COUNTIF(O27,"=*employee*")+COUNTIF(O27,"=*guest*")+COUNTIF(O27,"=*passen*")+COUNTIF(O27,"=*applicant*")+COUNTIF(O27,"=*client*") -> 0 | AH27: =IF(AG27>0,"yes","") | AI27: =COUNTIF(O27,"=*user*")+COUNTIF(O27,"=*code*")+COUNTIF(O27,"=*software*")+COUNTIF(O27,"=*system*")+COUNTIF(O27,"=*text*")+COUNTIF(O27,"=*api*")+COUNTIF(O27,"=*cyber*") -> 0 | AJ27: =IF(AI27>0,"yes","") | AK27: =COUNTIF(O27,"=*not disclosed*") -> 0 | AL27: =IF(AK27>0,"yes","") | AM27: =IF(C27="yes",D27,"") -> 2014 | AN27: =IF(H27="yes",I27,"") | AO27: =M27 -> 2023 | AP27: =IF(C27="yes",IF(AO27=D27,"same year",IF(AO27<D27,"before",IF(AO27>D27,"after"))),"") -> after | AQ27: =IF(C27="yes",IF(AP27="before",D27-AO27,IF(AP27="after",AO27-D27,IF(AP27="same year",0))),"") -> 9 | AR27: =IF(H27="yes",IF(AO27=I27,"same year",IF(AO27<I27,"before",IF(AO27>I27,"after"))),"") | AS27: =IF(H27="yes",IF(AR27="same year",0,IF(AR27="before",I27-AO27,IF(AR27="after",AO27-I27))),"") | AT27: =IF(R27="yes",IF(AO27<2018,"before",IF(AO27=2018,"same year",IF(AO27>2018,"after"))),"") -> after | AU27: =IF(R27="yes",IF(AT27="before",2018-AO27,IF(AT27="after",AO27-2018,IF(AT27="same year",0))),"") -> 5 | AV27: =IF(F27="defunct",IF(AO27=G27,"same year",IF(AO27<G27,"before",IF(AO27>=G27,"after"))),"") | AW27: =COUNTIF(P27,"=*vuln*") -> 0 | AX27: =COUNTIF(R27,"=yes") -> 1 | AY27: BlueKai | AZ27: =VLOOKUP(A27,certs!U:V,2,FALSE) -> Not Available
A28: Bombardier | B28: =VLOOKUP(A28,industry!A:B,2,FALSE) -> Aerospace | C28: =VLOOKUP(A28,acquisitions!A:D,2,FALSE) -> No | D28: =VLOOKUP(A28,acquisitions!A:D,4,FALSE) -> N/A | E28: =VLOOKUP(A28,acquisitions!A:D,3,FALSE) -> N/A | F28: =VLOOKUP(A28,acquisitions!I:K,2,FALSE) -> Active | G28: =IF(F28="active","",VLOOKUP(A28,acquisitions!I:K,3,FALSE)) | H28: =VLOOKUP(A28,public!A:D,2,FALSE) -> Yes | I28: =VLOOKUP(A28,public!J:K,2,FALSE) -> 1969 | J28: =VLOOKUP(A28,'net worth'!B:C,2,FALSE) -> 9110000000 | K28: =VLOOKUP(A28,public!A:D,3,FALSE) -> TSX | L28: =VLOOKUP(A28,public!A:D,4,FALSE) -> BBD.B | M28: 2021 | N28: Unknown | O28: Confidential company data via Accellion breach | P28: System Vulnerability Exploit | Q28: GDPR | R28: yes | AA28: =COUNTIF(O28,"=*personal*")+COUNTIF(O28,"=*ssn*")++COUNTIF(O28,"=*license*")+COUNTIF(O28,"=*email*")+COUNTIF(O28,"=*vehic*")+COUNTIF(O28,"=*profile*")+COUNTIF(O28,"=*account*")+COUNTIF(O28,"=*image*")+COUNTIF(O28,"=*phone*")+COUNTIF(O28,"=*photo*") -> 0 | AB28: =IF(AA28>0,"yes","") | AC28: =COUNTIF(O28,"=*financ*")+COUNTIF(O28,"=*card*")+COUNTIF(O28,"=*crypto*")+COUNTIF(O28,"=*bank*")+COUNTIF(O28,"=*pay*") -> 0 | AD28: =IF(AC28>0,"yes","") | AE28: =COUNTIF(O28,"=*health*")+COUNTIF(O28,"=*bio*")+COUNTIF(O28,"=*medic*")+COUNTIF(O28,"=*patient*") -> 0 | AF28: =IF(AE28>0,"yes","") | AG28: =COUNTIF(O28,"=*customer*")+COUNTIF(O28,"=*employee*")+COUNTIF(O28,"=*guest*")+COUNTIF(O28,"=*passen*")+COUNTIF(O28,"=*applicant*")+COUNTIF(O28,"=*client*")+COUNTIF(O28,"=*company*") -> 1 | AH28: =IF(AG28>0,"yes","") -> yes | AI28: =COUNTIF(O28,"=*user*")+COUNTIF(O28,"=*code*")+COUNTIF(O28,"=*software*")+COUNTIF(O28,"=*system*")+COUNTIF(O28,"=*text*")+COUNTIF(O28,"=*api*")+COUNTIF(O28,"=*cyber*") -> 0 | AJ28: =IF(AI28>0,"yes","") | AK28: =COUNTIF(O28,"=*not disclosed*") -> 0 | AL28: =IF(AK28>0,"yes","") | AM28: =IF(C28="yes",D28,"") | AN28: =IF(H28="yes",I28,"") -> 1969 | AO28: =M28 -> 2021 | AP28: =IF(C28="yes",IF(AO28=D28,"same year",IF(AO28<D28,"before",IF(AO28>D28,"after"))),"") | AQ28: =IF(C28="yes",IF(AP28="before",D28-AO28,IF(AP28="after",AO28-D28,IF(AP28="same year",0))),"") | AR28: =IF(H28="yes",IF(AO28=I28,"same year",IF(AO28<I28,"before",IF(AO28>I28,"after"))),"") -> after | AS28: =IF(H28="yes",IF(AR28="same year",0,IF(AR28="before",I28-AO28,IF(AR28="after",AO28-I28))),"") -> 52 | AT28: =IF(R28="yes",IF(AO28<2018,"before",IF(AO28=2018,"same year",IF(AO28>2018,"after"))),"") -> after | AU28: =IF(R28="yes",IF(AT28="before",2018-AO28,IF(AT28="after",AO28-2018,IF(AT28="same year",0))),"") -> 3 | AV28: =IF(F28="defunct",IF(AO28=G28,"same year",IF(AO28<G28,"before",IF(AO28>=G28,"after"))),"") | AW28: =COUNTIF(P28,"=*vuln*") -> 1 | AX28: =COUNTIF(R28,"=yes") -> 1 | AY28: Bombardier | AZ28: =VLOOKUP(A28,certs!U:V,2,FALSE) -> https://www.bombardier.com/en/legal/compliance.html
A29: Bonobos | B29: =VLOOKUP(A29,industry!A:B,2,FALSE) -> Retail | C29: =VLOOKUP(A29,acquisitions!A:D,2,FALSE) -> Yes | D29: =VLOOKUP(A29,acquisitions!A:D,4,FALSE) -> 2017 | E29: =VLOOKUP(A29,acquisitions!A:D,3,FALSE) -> Walmart | F29: =VLOOKUP(A29,acquisitions!I:K,2,FALSE) -> Active | G29: =IF(F29="active","",VLOOKUP(A29,acquisitions!I:K,3,FALSE)) | H29: =VLOOKUP(A29,public!A:D,2,FALSE) -> No | I29: =VLOOKUP(A29,public!J:K,2,FALSE) -> #N/A | K29: =VLOOKUP(A29,public!A:D,3,FALSE) -> N/A | L29: =VLOOKUP(A29,public!A:D,4,FALSE) -> N/A | M29: 2021 | N29: 7000000 | O29: Customer records, order information | P29: Credential Stuffing | Q29: GDPR | R29: yes | AA29: =COUNTIF(O29,"=*personal*")+COUNTIF(O29,"=*ssn*")++COUNTIF(O29,"=*license*")+COUNTIF(O29,"=*email*")+COUNTIF(O29,"=*vehic*")+COUNTIF(O29,"=*profile*")+COUNTIF(O29,"=*account*")+COUNTIF(O29,"=*image*")+COUNTIF(O29,"=*phone*")+COUNTIF(O29,"=*photo*") -> 0 | AB29: =IF(AA29>0,"yes","") | AC29: =COUNTIF(O29,"=*financ*")+COUNTIF(O29,"=*card*")+COUNTIF(O29,"=*crypto*")+COUNTIF(O29,"=*bank*")+COUNTIF(O29,"=*pay*") -> 0 | AD29: =IF(AC29>0,"yes","") | AE29: =COUNTIF(O29,"=*health*")+COUNTIF(O29,"=*bio*")+COUNTIF(O29,"=*medic*")+COUNTIF(O29,"=*patient*") -> 0 | AF29: =IF(AE29>0,"yes","") | AG29: =COUNTIF(O29,"=*customer*")+COUNTIF(O29,"=*employee*")+COUNTIF(O29,"=*guest*")+COUNTIF(O29,"=*passen*")+COUNTIF(O29,"=*applicant*")+COUNTIF(O29,"=*client*") -> 1 | AH29: =IF(AG29>0,"yes","") -> yes | AI29: =COUNTIF(O29,"=*user*")+COUNTIF(O29,"=*code*")+COUNTIF(O29,"=*software*")+COUNTIF(O29,"=*system*")+COUNTIF(O29,"=*text*")+COUNTIF(O29,"=*api*")+COUNTIF(O29,"=*cyber*") -> 0 | AJ29: =IF(AI29>0,"yes","") | AK29: =COUNTIF(O29,"=*not disclosed*") -> 0 | AL29: =IF(AK29>0,"yes","") | AM29: =IF(C29="yes",D29,"") -> 2017 | AN29: =IF(H29="yes",I29,"") | AO29: =M29 -> 2021 | AP29: =IF(C29="yes",IF(AO29=D29,"same year",IF(AO29<D29,"before",IF(AO29>D29,"after"))),"") -> after | AQ29: =IF(C29="yes",IF(AP29="before",D29-AO29,IF(AP29="after",AO29-D29,IF(AP29="same year",0))),"") -> 4 | AR29: =IF(H29="yes",IF(AO29=I29,"same year",IF(AO29<I29,"before",IF(AO29>I29,"after"))),"") | AS29: =IF(H29="yes",IF(AR29="same year",0,IF(AR29="before",I29-AO29,IF(AR29="after",AO29-I29))),"") | AT29: =IF(R29="yes",IF(AO29<2018,"before",IF(AO29=2018,"same year",IF(AO29>2018,"after"))),"") -> after | AU29: =IF(R29="yes",IF(AT29="before",2018-AO29,IF(AT29="after",AO29-2018,IF(AT29="same year",0))),"") -> 3 | AV29: =IF(F29="defunct",IF(AO29=G29,"same year",IF(AO29<G29,"before",IF(AO29>=G29,"after"))),"") | AW29: =COUNTIF(P29,"=*vuln*") -> 0 | AX29: =COUNTIF(R29,"=yes") -> 1 | AY29: Bonobos | AZ29: =VLOOKUP(A29,certs!U:V,2,FALSE) -> Not Available
A30: Boulder Community Health | B30: =VLOOKUP(A30,industry!A:B,2,FALSE) -> Healthcare | C30: =VLOOKUP(A30,acquisitions!A:D,2,FALSE) -> No | D30: =VLOOKUP(A30,acquisitions!A:D,4,FALSE) -> N/A | E30: =VLOOKUP(A30,acquisitions!A:D,3,FALSE) -> N/A | F30: =VLOOKUP(A30,acquisitions!I:K,2,FALSE) -> Active | G30: =IF(F30="active","",VLOOKUP(A30,acquisitions!I:K,3,FALSE)) | H30: =VLOOKUP(A30,public!A:D,2,FALSE) -> No | I30: =VLOOKUP(A30,public!J:K,2,FALSE) -> #N/A | K30: =VLOOKUP(A30,public!A:D,3,FALSE) -> N/A | L30: =VLOOKUP(A30,public!A:D,4,FALSE) -> N/A | M30: 2020 | N30: 30000 | O30: Patient data, medical records | P30: Phishing | Q30: HIPAA, GDPR | R30: yes | W30: yes | AA30: =COUNTIF(O30,"=*personal*")+COUNTIF(O30,"=*ssn*")++COUNTIF(O30,"=*license*")+COUNTIF(O30,"=*email*")+COUNTIF(O30,"=*vehic*")+COUNTIF(O30,"=*profile*")+COUNTIF(O30,"=*account*")+COUNTIF(O30,"=*image*")+COUNTIF(O30,"=*phone*")+COUNTIF(O30,"=*photo*") -> 0 | AB30: =IF(AA30>0,"yes","") | AC30: =COUNTIF(O30,"=*financ*")+COUNTIF(O30,"=*card*")+COUNTIF(O30,"=*crypto*")+COUNTIF(O30,"=*bank*")+COUNTIF(O30,"=*pay*") -> 0 | AD30: =IF(AC30>0,"yes","") | AE30: =COUNTIF(O30,"=*health*")+COUNTIF(O30,"=*bio*")+COUNTIF(O30,"=*medic*")+COUNTIF(O30,"=*patient*") -> 2 | AF30: =IF(AE30>0,"yes","") -> yes | AG30: =COUNTIF(O30,"=*customer*")+COUNTIF(O30,"=*employee*")+COUNTIF(O30,"=*guest*")+COUNTIF(O30,"=*passen*")+COUNTIF(O30,"=*applicant*")+COUNTIF(O30,"=*client*") -> 0 | AH30: =IF(AG30>0,"yes","") | AI30: =COUNTIF(O30,"=*user*")+COUNTIF(O30,"=*code*")+COUNTIF(O30,"=*software*")+COUNTIF(O30,"=*system*")+COUNTIF(O30,"=*text*")+COUNTIF(O30,"=*api*")+COUNTIF(O30,"=*cyber*") -> 0 | AJ30: =IF(AI30>0,"yes","") | AK30: =COUNTIF(O30,"=*not disclosed*") -> 0 | AL30: =IF(AK30>0,"yes","") | AM30: =IF(C30="yes",D30,"") | AN30: =IF(H30="yes",I30,"") | AO30: =M30 -> 2020 | AP30: =IF(C30="yes",IF(AO30=D30,"same year",IF(AO30<D30,"before",IF(AO30>D30,"after"))),"") | AQ30: =IF(C30="yes",IF(AP30="before",D30-AO30,IF(AP30="after",AO30-D30,IF(AP30="same year",0))),"") | AR30: =IF(H30="yes",IF(AO30=I30,"same year",IF(AO30<I30,"before",IF(AO30>I30,"after"))),"") | AS30: =IF(H30="yes",IF(AR30="same year",0,IF(AR30="before",I30-AO30,IF(AR30="after",AO30-I30))),"") | AT30: =IF(R30="yes",IF(AO30<2018,"before",IF(AO30=2018,"same year",IF(AO30>2018,"after"))),"") -> after | AU30: =IF(R30="yes",IF(AT30="before",2018-AO30,IF(AT30="after",AO30-2018,IF(AT30="same year",0))),"") -> 2 | AV30: =IF(F30="defunct",IF(AO30=G30,"same year",IF(AO30<G30,"before",IF(AO30>=G30,"after"))),"") | AW30: =COUNTIF(P30,"=*vuln*") -> 0 | AX30: =COUNTIF(R30,"=yes") -> 1 | AY30: Boulder Community Health | AZ30: =VLOOKUP(A30,certs!U:V,2,FALSE) -> https://www.bch.org/compliance
A31: British Airways | B31: =VLOOKUP(A31,industry!A:B,2,FALSE) -> Airlines | C31: =VLOOKUP(A31,acquisitions!A:D,2,FALSE) -> No | D31: =VLOOKUP(A31,acquisitions!A:D,4,FALSE) -> N/A | E31: =VLOOKUP(A31,acquisitions!A:D,3,FALSE) -> N/A | F31: =VLOOKUP(A31,acquisitions!I:K,2,FALSE) -> Active | G31: =IF(F31="active","",VLOOKUP(A31,acquisitions!I:K,3,FALSE)) | H31: =VLOOKUP(A31,public!A:D,2,FALSE) -> No | I31: =VLOOKUP(A31,public!J:K,2,FALSE) -> #N/A | K31: =VLOOKUP(A31,public!A:D,3,FALSE) -> N/A | L31: =VLOOKUP(A31,public!A:D,4,FALSE) -> N/A | M31: 2018 | N31: 380000 | O31: Payment card details, personal information | P31: Vulnerability in website and mobile app | Q31: GDPR, PCI DSS | R31: yes | T31: yes | AA31: =COUNTIF(O31,"=*personal*")+COUNTIF(O31,"=*ssn*")++COUNTIF(O31,"=*license*")+COUNTIF(O31,"=*email*")+COUNTIF(O31,"=*vehic*")+COUNTIF(O31,"=*profile*")+COUNTIF(O31,"=*account*")+COUNTIF(O31,"=*image*")+COUNTIF(O31,"=*phone*")+COUNTIF(O31,"=*photo*") -> 1 | AB31: =IF(AA31>0,"yes","") -> yes | AC31: =COUNTIF(O31,"=*financ*")+COUNTIF(O31,"=*card*")+COUNTIF(O31,"=*crypto*")+COUNTIF(O31,"=*bank*")+COUNTIF(O31,"=*pay*") -> 2 | AD31: =IF(AC31>0,"yes","") -> yes | AE31: =COUNTIF(O31,"=*health*")+COUNTIF(O31,"=*bio*")+COUNTIF(O31,"=*medic*")+COUNTIF(O31,"=*patient*") -> 0 | AF31: =IF(AE31>0,"yes","") | AG31: =COUNTIF(O31,"=*customer*")+COUNTIF(O31,"=*employee*")+COUNTIF(O31,"=*guest*")+COUNTIF(O31,"=*passen*")+COUNTIF(O31,"=*applicant*")+COUNTIF(O31,"=*client*") -> 0 | AH31: =IF(AG31>0,"yes","") | AI31: =COUNTIF(O31,"=*user*")+COUNTIF(O31,"=*code*")+COUNTIF(O31,"=*software*")+COUNTIF(O31,"=*system*")+COUNTIF(O31,"=*text*")+COUNTIF(O31,"=*api*")+COUNTIF(O31,"=*cyber*") -> 0 | AJ31: =IF(AI31>0,"yes","") | AK31: =COUNTIF(O31,"=*not disclosed*") -> 0 | AL31: =IF(AK31>0,"yes","") | AM31: =IF(C31="yes",D31,"") | AN31: =IF(H31="yes",I31,"") | AO31: =M31 -> 2018 | AP31: =IF(C31="yes",IF(AO31=D31,"same year",IF(AO31<D31,"before",IF(AO31>D31,"after"))),"") | AQ31: =IF(C31="yes",IF(AP31="before",D31-AO31,IF(AP31="after",AO31-D31,IF(AP31="same year",0))),"") | AR31: =IF(H31="yes",IF(AO31=I31,"same year",IF(AO31<I31,"before",IF(AO31>I31,"after"))),"") | AS31: =IF(H31="yes",IF(AR31="same year",0,IF(AR31="before",I31-AO31,IF(AR31="after",AO31-I31))),"") | AT31: =IF(R31="yes",IF(AO31<2018,"before",IF(AO31=2018,"same year",IF(AO31>2018,"after"))),"") -> same year | AU31: =IF(R31="yes",IF(AT31="before",2018-AO31,IF(AT31="after",AO31-2018,IF(AT31="same year",0))),"") -> 0 | AV31: =IF(F31="defunct",IF(AO31=G31,"same year",IF(AO31<G31,"before",IF(AO31>=G31,"after"))),"") | AW31: =COUNTIF(P31,"=*vuln*") -> 1 | AX31: =COUNTIF(R31,"=yes") -> 1 | AY31: British Airways | AZ31: =VLOOKUP(A31,certs!U:V,2,FALSE) -> https://www.britishairways.com/en-us/information/legal
A32: Broadvoice | B32: =VLOOKUP(A32,industry!A:B,2,FALSE) -> Telecommunications | C32: =VLOOKUP(A32,acquisitions!A:D,2,FALSE) -> No | D32: =VLOOKUP(A32,acquisitions!A:D,4,FALSE) -> N/A | E32: =VLOOKUP(A32,acquisitions!A:D,3,FALSE) -> N/A | F32: =VLOOKUP(A32,acquisitions!I:K,2,FALSE) -> Active | G32: =IF(F32="active","",VLOOKUP(A32,acquisitions!I:K,3,FALSE)) | H32: =VLOOKUP(A32,public!A:D,2,FALSE) -> No | I32: =VLOOKUP(A32,public!J:K,2,FALSE) -> #N/A | K32: =VLOOKUP(A32,public!A:D,3,FALSE) -> N/A | L32: =VLOOKUP(A32,public!A:D,4,FALSE) -> N/A | M32: 2020 | N32: 350000000 | O32: Voicemail transcripts, caller data | P32: Ransomware | Q32: GDPR | R32: yes | AA32: =COUNTIF(O32,"=*personal*")+COUNTIF(O32,"=*ssn*")++COUNTIF(O32,"=*license*")+COUNTIF(O32,"=*email*")+COUNTIF(O32,"=*vehic*")+COUNTIF(O32,"=*profile*")+COUNTIF(O32,"=*account*")+COUNTIF(O32,"=*image*")+COUNTIF(O32,"=*phone*")+COUNTIF(O32,"=*photo*") -> 1 | AB32: =IF(AA32>0,"yes","") -> yes | AC32: =COUNTIF(O32,"=*financ*")+COUNTIF(O32,"=*card*")+COUNTIF(O32,"=*crypto*")+COUNTIF(O32,"=*bank*")+COUNTIF(O32,"=*pay*") -> 0 | AD32: =IF(AC32>0,"yes","") | AE32: =COUNTIF(O32,"=*health*")+COUNTIF(O32,"=*bio*")+COUNTIF(O32,"=*medic*")+COUNTIF(O32,"=*patient*") -> 0 | AF32: =IF(AE32>0,"yes","") | AG32: =COUNTIF(O32,"=*customer*")+COUNTIF(O32,"=*employee*")+COUNTIF(O32,"=*guest*")+COUNTIF(O32,"=*passen*")+COUNTIF(O32,"=*applicant*")+COUNTIF(O32,"=*client*") -> 0 | AH32: =IF(AG32>0,"yes","") | AI32: =COUNTIF(O32,"=*user*")+COUNTIF(O32,"=*code*")+COUNTIF(O32,"=*software*")+COUNTIF(O32,"=*system*")+COUNTIF(O32,"=*text*")+COUNTIF(O32,"=*api*")+COUNTIF(O32,"=*cyber*") -> 0 | AJ32: =IF(AI32>0,"yes","") | AK32: =COUNTIF(O32,"=*not disclosed*") -> 0 | AL32: =IF(AK32>0,"yes","") | AM32: =IF(C32="yes",D32,"") | AN32: =IF(H32="yes",I32,"") | AO32: =M32 -> 2020 | AP32: =IF(C32="yes",IF(AO32=D32,"same year",IF(AO32<D32,"before",IF(AO32>D32,"after"))),"") | AQ32: =IF(C32="yes",IF(AP32="before",D32-AO32,IF(AP32="after",AO32-D32,IF(AP32="same year",0))),"") | AR32: =IF(H32="yes",IF(AO32=I32,"same year",IF(AO32<I32,"before",IF(AO32>I32,"after"))),"") | AS32: =IF(H32="yes",IF(AR32="same year",0,IF(AR32="before",I32-AO32,IF(AR32="after",AO32-I32))),"") | AT32: =IF(R32="yes",IF(AO32<2018,"before",IF(AO32=2018,"same year",IF(AO32>2018,"after"))),"") -> after | AU32: =IF(R32="yes",IF(AT32="before",2018-AO32,IF(AT32="after",AO32-2018,IF(AT32="same year",0))),"") -> 2 | AV32: =IF(F32="defunct",IF(AO32=G32,"same year",IF(AO32<G32,"before",IF(AO32>=G32,"after"))),"") | AW32: =COUNTIF(P32,"=*vuln*") -> 0 | AX32: =COUNTIF(R32,"=yes") -> 1 | AY32: Broadvoice | AZ32: =VLOOKUP(A32,certs!U:V,2,FALSE) -> https://www.broadvoice.com/legal/compliance/
A33: CafePress | B33: =VLOOKUP(A33,industry!A:B,2,FALSE) -> Retail | C33: =VLOOKUP(A33,acquisitions!A:D,2,FALSE) -> Yes | D33: =VLOOKUP(A33,acquisitions!A:D,4,FALSE) -> 2020 | E33: =VLOOKUP(A33,acquisitions!A:D,3,FALSE) -> PlanetArt | F33: =VLOOKUP(A33,acquisitions!I:K,2,FALSE) -> Active | G33: =IF(F33="active","",VLOOKUP(A33,acquisitions!I:K,3,FALSE)) | H33: =VLOOKUP(A33,public!A:D,2,FALSE) -> Yes | I33: =VLOOKUP(A33,public!J:K,2,FALSE) -> 2012 | J33: =VLOOKUP(A33,'net worth'!B:C,2,FALSE) -> 76300000 | K33: =VLOOKUP(A33,public!A:D,3,FALSE) -> NASDAQ | L33: =VLOOKUP(A33,public!A:D,4,FALSE) -> PRSS | M33: 2019 | N33: 23000000 | O33: Usernames, emails, passwords | P33: Unsecured database | Q33: GDPR | R33: yes | AA33: =COUNTIF(O33,"=*personal*")+COUNTIF(O33,"=*ssn*")++COUNTIF(O33,"=*license*")+COUNTIF(O33,"=*email*")+COUNTIF(O33,"=*vehic*")+COUNTIF(O33,"=*profile*")+COUNTIF(O33,"=*account*")+COUNTIF(O33,"=*image*")+COUNTIF(O33,"=*phone*")+COUNTIF(O33,"=*photo*") -> 1 | AB33: =IF(AA33>0,"yes","") -> yes | AC33: =COUNTIF(O33,"=*financ*")+COUNTIF(O33,"=*card*")+COUNTIF(O33,"=*crypto*")+COUNTIF(O33,"=*bank*")+COUNTIF(O33,"=*pay*") -> 0 | AD33: =IF(AC33>0,"yes","") | AE33: =COUNTIF(O33,"=*health*")+COUNTIF(O33,"=*bio*")+COUNTIF(O33,"=*medic*")+COUNTIF(O33,"=*patient*") -> 0 | AF33: =IF(AE33>0,"yes","") | AG33: =COUNTIF(O33,"=*customer*")+COUNTIF(O33,"=*employee*")+COUNTIF(O33,"=*guest*")+COUNTIF(O33,"=*passen*")+COUNTIF(O33,"=*applicant*")+COUNTIF(O33,"=*client*") -> 0 | AH33: =IF(AG33>0,"yes","") | AI33: =COUNTIF(O33,"=*user*")+COUNTIF(O33,"=*code*")+COUNTIF(O33,"=*software*")+COUNTIF(O33,"=*system*")+COUNTIF(O33,"=*text*")+COUNTIF(O33,"=*api*")+COUNTIF(O33,"=*cyber*") -> 1 | AJ33: =IF(AI33>0,"yes","") -> yes | AK33: =COUNTIF(O33,"=*not disclosed*") -> 0 | AL33: =IF(AK33>0,"yes","") | AM33: =IF(C33="yes",D33,"") -> 2020 | AN33: =IF(H33="yes",I33,"") -> 2012 | AO33: =M33 -> 2019 | AP33: =IF(C33="yes",IF(AO33=D33,"same year",IF(AO33<D33,"before",IF(AO33>D33,"after"))),"") -> before | AQ33: =IF(C33="yes",IF(AP33="before",D33-AO33,IF(AP33="after",AO33-D33,IF(AP33="same year",0))),"") -> 1 | AR33: =IF(H33="yes",IF(AO33=I33,"same year",IF(AO33<I33,"before",IF(AO33>I33,"after"))),"") -> after | AS33: =IF(H33="yes",IF(AR33="same year",0,IF(AR33="before",I33-AO33,IF(AR33="after",AO33-I33))),"") -> 7 | AT33: =IF(R33="yes",IF(AO33<2018,"before",IF(AO33=2018,"same year",IF(AO33>2018,"after"))),"") -> after | AU33: =IF(R33="yes",IF(AT33="before",2018-AO33,IF(AT33="after",AO33-2018,IF(AT33="same year",0))),"") -> 1 | AV33: =IF(F33="defunct",IF(AO33=G33,"same year",IF(AO33<G33,"before",IF(AO33>=G33,"after"))),"") | AW33: =COUNTIF(P33,"=*vuln*") -> 0 | AX33: =COUNTIF(R33,"=yes") -> 1 | AY33: CafePress | AZ33: =VLOOKUP(A33,certs!U:V,2,FALSE) -> https://www.cafepress.com/cp/info/help/policies.aspx
A34: California Department of Motor Vehicles | B34: =VLOOKUP(A34,industry!A:B,2,FALSE) -> Government | C34: =VLOOKUP(A34,acquisitions!A:D,2,FALSE) -> No | D34: =VLOOKUP(A34,acquisitions!A:D,4,FALSE) -> N/A | E34: =VLOOKUP(A34,acquisitions!A:D,3,FALSE) -> N/A | F34: =VLOOKUP(A34,acquisitions!I:K,2,FALSE) -> Active | G34: =IF(F34="active","",VLOOKUP(A34,acquisitions!I:K,3,FALSE)) | H34: =VLOOKUP(A34,public!A:D,2,FALSE) -> No | I34: =VLOOKUP(A34,public!J:K,2,FALSE) -> #N/A | K34: =VLOOKUP(A34,public!A:D,3,FALSE) -> N/A | L34: =VLOOKUP(A34,public!A:D,4,FALSE) -> N/A | M34: 2021 | N34: 38000000 | O34: Vehicle registration records | P34: System Vulnerability Exploit | Q34: CCPA, GDPR | R34: yes | Y34: yes | AA34: =COUNTIF(O34,"=*personal*")+COUNTIF(O34,"=*ssn*")++COUNTIF(O34,"=*license*")+COUNTIF(O34,"=*email*")+COUNTIF(O34,"=*vehic*")+COUNTIF(O34,"=*profile*")+COUNTIF(O34,"=*account*")+COUNTIF(O34,"=*image*")+COUNTIF(O34,"=*phone*")+COUNTIF(O34,"=*photo*") -> 1 | AB34: =IF(AA34>0,"yes","") -> yes | AC34: =COUNTIF(O34,"=*financ*")+COUNTIF(O34,"=*card*")+COUNTIF(O34,"=*crypto*")+COUNTIF(O34,"=*bank*")+COUNTIF(O34,"=*pay*") -> 0 | AD34: =IF(AC34>0,"yes","") | AE34: =COUNTIF(O34,"=*health*")+COUNTIF(O34,"=*bio*")+COUNTIF(O34,"=*medic*")+COUNTIF(O34,"=*patient*") -> 0 | AF34: =IF(AE34>0,"yes","") | AG34: =COUNTIF(O34,"=*customer*")+COUNTIF(O34,"=*employee*")+COUNTIF(O34,"=*guest*")+COUNTIF(O34,"=*passen*")+COUNTIF(O34,"=*applicant*")+COUNTIF(O34,"=*client*") -> 0 | AH34: =IF(AG34>0,"yes","") | AI34: =COUNTIF(O34,"=*user*")+COUNTIF(O34,"=*code*")+COUNTIF(O34,"=*software*")+COUNTIF(O34,"=*system*")+COUNTIF(O34,"=*text*")+COUNTIF(O34,"=*api*")+COUNTIF(O34,"=*cyber*") -> 0 | AJ34: =IF(AI34>0,"yes","") | AK34: =COUNTIF(O34,"=*not disclosed*") -> 0 | AL34: =IF(AK34>0,"yes","") | AM34: =IF(C34="yes",D34,"") | AN34: =IF(H34="yes",I34,"") | AO34: =M34 -> 2021 | AP34: =IF(C34="yes",IF(AO34=D34,"same year",IF(AO34<D34,"before",IF(AO34>D34,"after"))),"") | AQ34: =IF(C34="yes",IF(AP34="before",D34-AO34,IF(AP34="after",AO34-D34,IF(AP34="same year",0))),"") | AR34: =IF(H34="yes",IF(AO34=I34,"same year",IF(AO34<I34,"before",IF(AO34>I34,"after"))),"") | AS34: =IF(H34="yes",IF(AR34="same year",0,IF(AR34="before",I34-AO34,IF(AR34="after",AO34-I34))),"") | AT34: =IF(R34="yes",IF(AO34<2018,"before",IF(AO34=2018,"same year",IF(AO34>2018,"after"))),"") -> after | AU34: =IF(R34="yes",IF(AT34="before",2018-AO34,IF(AT34="after",AO34-2018,IF(AT34="same year",0))),"") -> 3 | AV34: =IF(F34="defunct",IF(AO34=G34,"same year",IF(AO34<G34,"before",IF(AO34>=G34,"after"))),"") | AW34: =COUNTIF(P34,"=*vuln*") -> 1 | AX34: =COUNTIF(R34,"=yes") -> 1 | AY34: California Department of Motor Vehicles | AZ34: =VLOOKUP(A34,certs!U:V,2,FALSE) -> https://www.dmv.ca.gov/portal/about-the-dmv/legal-compliance/
A35: CAM4 | B35: =VLOOKUP(A35,industry!A:B,2,FALSE) -> Entertainment | C35: =VLOOKUP(A35,acquisitions!A:D,2,FALSE) -> No | D35: =VLOOKUP(A35,acquisitions!A:D,4,FALSE) -> N/A | E35: =VLOOKUP(A35,acquisitions!A:D,3,FALSE) -> N/A | F35: =VLOOKUP(A35,acquisitions!I:K,2,FALSE) -> Active | G35: =IF(F35="active","",VLOOKUP(A35,acquisitions!I:K,3,FALSE)) | H35: =VLOOKUP(A35,public!A:D,2,FALSE) -> No | I35: =VLOOKUP(A35,public!J:K,2,FALSE) -> #N/A | K35: =VLOOKUP(A35,public!A:D,3,FALSE) -> N/A | L35: =VLOOKUP(A35,public!A:D,4,FALSE) -> N/A | M35: 2020 | N35: 10880000000 | O35: User logs, chat transcripts | P35: Misconfigured Database | Q35: GDPR | R35: yes | AA35: =COUNTIF(O35,"=*personal*")+COUNTIF(O35,"=*ssn*")++COUNTIF(O35,"=*license*")+COUNTIF(O35,"=*email*")+COUNTIF(O35,"=*vehic*")+COUNTIF(O35,"=*profile*")+COUNTIF(O35,"=*account*")+COUNTIF(O35,"=*image*")+COUNTIF(O35,"=*phone*")+COUNTIF(O35,"=*photo*") -> 0 | AB35: =IF(AA35>0,"yes","") | AC35: =COUNTIF(O35,"=*financ*")+COUNTIF(O35,"=*card*")+COUNTIF(O35,"=*crypto*")+COUNTIF(O35,"=*bank*")+COUNTIF(O35,"=*pay*") -> 0 | AD35: =IF(AC35>0,"yes","") | AE35: =COUNTIF(O35,"=*health*")+COUNTIF(O35,"=*bio*")+COUNTIF(O35,"=*medic*")+COUNTIF(O35,"=*patient*") -> 0 | AF35: =IF(AE35>0,"yes","") | AG35: =COUNTIF(O35,"=*customer*")+COUNTIF(O35,"=*employee*")+COUNTIF(O35,"=*guest*")+COUNTIF(O35,"=*passen*")+COUNTIF(O35,"=*applicant*")+COUNTIF(O35,"=*client*") -> 0 | AH35: =IF(AG35>0,"yes","") | AI35: =COUNTIF(O35,"=*user*")+COUNTIF(O35,"=*code*")+COUNTIF(O35,"=*software*")+COUNTIF(O35,"=*system*")+COUNTIF(O35,"=*text*")+COUNTIF(O35,"=*api*")+COUNTIF(O35,"=*cyber*") -> 1 | AJ35: =IF(AI35>0,"yes","") -> yes | AK35: =COUNTIF(O35,"=*not disclosed*") -> 0 | AL35: =IF(AK35>0,"yes","") | AM35: =IF(C35="yes",D35,"") | AN35: =IF(H35="yes",I35,"") | AO35: =M35 -> 2020 | AP35: =IF(C35="yes",IF(AO35=D35,"same year",IF(AO35<D35,"before",IF(AO35>D35,"after"))),"") | AQ35: =IF(C35="yes",IF(AP35="before",D35-AO35,IF(AP35="after",AO35-D35,IF(AP35="same year",0))),"") | AR35: =IF(H35="yes",IF(AO35=I35,"same year",IF(AO35<I35,"before",IF(AO35>I35,"after"))),"") | AS35: =IF(H35="yes",IF(AR35="same year",0,IF(AR35="before",I35-AO35,IF(AR35="after",AO35-I35))),"") | AT35: =IF(R35="yes",IF(AO35<2018,"before",IF(AO35=2018,"same year",IF(AO35>2018,"after"))),"") -> after | AU35: =IF(R35="yes",IF(AT35="before",2018-AO35,IF(AT35="after",AO35-2018,IF(AT35="same year",0))),"") -> 2 | AV35: =IF(F35="defunct",IF(AO35=G35,"same year",IF(AO35<G35,"before",IF(AO35>=G35,"after"))),"") | AW35: =COUNTIF(P35,"=*vuln*") -> 0 | AX35: =COUNTIF(R35,"=yes") -> 1 | AY35: CAM4 | AZ35: =VLOOKUP(A35,certs!U:V,2,FALSE) -> Not Available
A36: Cancer Care Group | B36: =VLOOKUP(A36,industry!A:B,2,FALSE) -> Healthcare | C36: =VLOOKUP(A36,acquisitions!A:D,2,FALSE) -> No | D36: =VLOOKUP(A36,acquisitions!A:D,4,FALSE) -> N/A | E36: =VLOOKUP(A36,acquisitions!A:D,3,FALSE) -> N/A | F36: =VLOOKUP(A36,acquisitions!I:K,2,FALSE) -> Active | G36: =IF(F36="active","",VLOOKUP(A36,acquisitions!I:K,3,FALSE)) | H36: =VLOOKUP(A36,public!A:D,2,FALSE) -> No | I36: =VLOOKUP(A36,public!J:K,2,FALSE) -> #N/A | K36: =VLOOKUP(A36,public!A:D,3,FALSE) -> N/A | L36: =VLOOKUP(A36,public!A:D,4,FALSE) -> N/A | M36: 2021 | N36: 50000 | O36: Patient information | P36: Ransomware | Q36: HIPAA, GDPR | R36: yes | W36: yes | AA36: =COUNTIF(O36,"=*personal*")+COUNTIF(O36,"=*ssn*")++COUNTIF(O36,"=*license*")+COUNTIF(O36,"=*email*")+COUNTIF(O36,"=*vehic*")+COUNTIF(O36,"=*profile*")+COUNTIF(O36,"=*account*")+COUNTIF(O36,"=*image*")+COUNTIF(O36,"=*phone*")+COUNTIF(O36,"=*photo*") -> 0 | AB36: =IF(AA36>0,"yes","") | AC36: =COUNTIF(O36,"=*financ*")+COUNTIF(O36,"=*card*")+COUNTIF(O36,"=*crypto*")+COUNTIF(O36,"=*bank*")+COUNTIF(O36,"=*pay*") -> 0 | AD36: =IF(AC36>0,"yes","") | AE36: =COUNTIF(O36,"=*health*")+COUNTIF(O36,"=*bio*")+COUNTIF(O36,"=*medic*")+COUNTIF(O36,"=*patient*") -> 1 | AF36: =IF(AE36>0,"yes","") -> yes | AG36: =COUNTIF(O36,"=*customer*")+COUNTIF(O36,"=*employee*")+COUNTIF(O36,"=*guest*")+COUNTIF(O36,"=*passen*")+COUNTIF(O36,"=*applicant*")+COUNTIF(O36,"=*client*") -> 0 | AH36: =IF(AG36>0,"yes","") | AI36: =COUNTIF(O36,"=*user*")+COUNTIF(O36,"=*code*")+COUNTIF(O36,"=*software*")+COUNTIF(O36,"=*system*")+COUNTIF(O36,"=*text*")+COUNTIF(O36,"=*api*")+COUNTIF(O36,"=*cyber*") -> 0 | AJ36: =IF(AI36>0,"yes","") | AK36: =COUNTIF(O36,"=*not disclosed*") -> 0 | AL36: =IF(AK36>0,"yes","") | AM36: =IF(C36="yes",D36,"") | AN36: =IF(H36="yes",I36,"") | AO36: =M36 -> 2021 | AP36: =IF(C36="yes",IF(AO36=D36,"same year",IF(AO36<D36,"before",IF(AO36>D36,"after"))),"") | AQ36: =IF(C36="yes",IF(AP36="before",D36-AO36,IF(AP36="after",AO36-D36,IF(AP36="same year",0))),"") | AR36: =IF(H36="yes",IF(AO36=I36,"same year",IF(AO36<I36,"before",IF(AO36>I36,"after"))),"") | AS36: =IF(H36="yes",IF(AR36="same year",0,IF(AR36="before",I36-AO36,IF(AR36="after",AO36-I36))),"") | AT36: =IF(R36="yes",IF(AO36<2018,"before",IF(AO36=2018,"same year",IF(AO36>2018,"after"))),"") -> after | AU36: =IF(R36="yes",IF(AT36="before",2018-AO36,IF(AT36="after",AO36-2018,IF(AT36="same year",0))),"") -> 3 | AV36: =IF(F36="defunct",IF(AO36=G36,"same year",IF(AO36<G36,"before",IF(AO36>=G36,"after"))),"") | AW36: =COUNTIF(P36,"=*vuln*") -> 0 | AX36: =COUNTIF(R36,"=yes") -> 1 | AY36: Cancer Care Group | AZ36: =VLOOKUP(A36,certs!U:V,2,FALSE) -> Not Available
A37: Cancer Treatment Centers of America | B37: =VLOOKUP(A37,industry!A:B,2,FALSE) -> Healthcare | C37: =VLOOKUP(A37,acquisitions!A:D,2,FALSE) -> Yes | D37: =VLOOKUP(A37,acquisitions!A:D,4,FALSE) -> 2022 | E37: =VLOOKUP(A37,acquisitions!A:D,3,FALSE) -> City of Hope | F37: =VLOOKUP(A37,acquisitions!I:K,2,FALSE) -> Active | G37: =IF(F37="active","",VLOOKUP(A37,acquisitions!I:K,3,FALSE)) | H37: =VLOOKUP(A37,public!A:D,2,FALSE) -> No | I37: =VLOOKUP(A37,public!J:K,2,FALSE) -> #N/A | K37: =VLOOKUP(A37,public!A:D,3,FALSE) -> N/A | L37: =VLOOKUP(A37,public!A:D,4,FALSE) -> N/A | M37: 2021 | N37: 104808 | O37: Patient data, medical records | P37: Malware | Q37: HIPAA, GDPR | R37: yes | W37: yes | AA37: =COUNTIF(O37,"=*personal*")+COUNTIF(O37,"=*ssn*")++COUNTIF(O37,"=*license*")+COUNTIF(O37,"=*email*")+COUNTIF(O37,"=*vehic*")+COUNTIF(O37,"=*profile*")+COUNTIF(O37,"=*account*")+COUNTIF(O37,"=*image*")+COUNTIF(O37,"=*phone*")+COUNTIF(O37,"=*photo*") -> 0 | AB37: =IF(AA37>0,"yes","") | AC37: =COUNTIF(O37,"=*financ*")+COUNTIF(O37,"=*card*")+COUNTIF(O37,"=*crypto*")+COUNTIF(O37,"=*bank*")+COUNTIF(O37,"=*pay*") -> 0 | AD37: =IF(AC37>0,"yes","") | AE37: =COUNTIF(O37,"=*health*")+COUNTIF(O37,"=*bio*")+COUNTIF(O37,"=*medic*")+COUNTIF(O37,"=*patient*") -> 2 | AF37: =IF(AE37>0,"yes","") -> yes | AG37: =COUNTIF(O37,"=*customer*")+COUNTIF(O37,"=*employee*")+COUNTIF(O37,"=*guest*")+COUNTIF(O37,"=*passen*")+COUNTIF(O37,"=*applicant*")+COUNTIF(O37,"=*client*") -> 0 | AH37: =IF(AG37>0,"yes","") | AI37: =COUNTIF(O37,"=*user*")+COUNTIF(O37,"=*code*")+COUNTIF(O37,"=*software*")+COUNTIF(O37,"=*system*")+COUNTIF(O37,"=*text*")+COUNTIF(O37,"=*api*")+COUNTIF(O37,"=*cyber*") -> 0 | AJ37: =IF(AI37>0,"yes","") | AK37: =COUNTIF(O37,"=*not disclosed*") -> 0 | AL37: =IF(AK37>0,"yes","") | AM37: =IF(C37="yes",D37,"") -> 2022 | AN37: =IF(H37="yes",I37,"") | AO37: =M37 -> 2021 | AP37: =IF(C37="yes",IF(AO37=D37,"same year",IF(AO37<D37,"before",IF(AO37>D37,"after"))),"") -> before | AQ37: =IF(C37="yes",IF(AP37="before",D37-AO37,IF(AP37="after",AO37-D37,IF(AP37="same year",0))),"") -> 1 | AR37: =IF(H37="yes",IF(AO37=I37,"same year",IF(AO37<I37,"before",IF(AO37>I37,"after"))),"") | AS37: =IF(H37="yes",IF(AR37="same year",0,IF(AR37="before",I37-AO37,IF(AR37="after",AO37-I37))),"") | AT37: =IF(R37="yes",IF(AO37<2018,"before",IF(AO37=2018,"same year",IF(AO37>2018,"after"))),"") -> after | AU37: =IF(R37="yes",IF(AT37="before",2018-AO37,IF(AT37="after",AO37-2018,IF(AT37="same year",0))),"") -> 3 | AV37: =IF(F37="defunct",IF(AO37=G37,"same year",IF(AO37<G37,"before",IF(AO37>=G37,"after"))),"") | AW37: =COUNTIF(P37,"=*vuln*") -> 0 | AX37: =COUNTIF(R37,"=yes") -> 1 | AY37: Cancer Treatment Centers of America | AZ37: =VLOOKUP(A37,certs!U:V,2,FALSE) -> https://www.cancercenter.com/legal/compliance
A38: Canva | B38: =VLOOKUP(A38,industry!A:B,2,FALSE) -> Design Software | C38: =VLOOKUP(A38,acquisitions!A:D,2,FALSE) -> No | D38: =VLOOKUP(A38,acquisitions!A:D,4,FALSE) -> N/A | E38: =VLOOKUP(A38,acquisitions!A:D,3,FALSE) -> N/A | F38: =VLOOKUP(A38,acquisitions!I:K,2,FALSE) -> Active | G38: =IF(F38="active","",VLOOKUP(A38,acquisitions!I:K,3,FALSE)) | H38: =VLOOKUP(A38,public!A:D,2,FALSE) -> No | I38: =VLOOKUP(A38,public!J:K,2,FALSE) -> #N/A | K38: =VLOOKUP(A38,public!A:D,3,FALSE) -> N/A | L38: =VLOOKUP(A38,public!A:D,4,FALSE) -> N/A | M38: 2019 | N38: 137000000 | O38: Usernames, emails, hashed passwords | P38: Unsecured Database | Q38: GDPR | R38: yes | AA38: =COUNTIF(O38,"=*personal*")+COUNTIF(O38,"=*ssn*")++COUNTIF(O38,"=*license*")+COUNTIF(O38,"=*email*")+COUNTIF(O38,"=*vehic*")+COUNTIF(O38,"=*profile*")+COUNTIF(O38,"=*account*")+COUNTIF(O38,"=*image*")+COUNTIF(O38,"=*phone*")+COUNTIF(O38,"=*photo*") -> 1 | AB38: =IF(AA38>0,"yes","") -> yes | AC38: =COUNTIF(O38,"=*financ*")+COUNTIF(O38,"=*card*")+COUNTIF(O38,"=*crypto*")+COUNTIF(O38,"=*bank*")+COUNTIF(O38,"=*pay*") -> 0 | AD38: =IF(AC38>0,"yes","") | AE38: =COUNTIF(O38,"=*health*")+COUNTIF(O38,"=*bio*")+COUNTIF(O38,"=*medic*")+COUNTIF(O38,"=*patient*") -> 0 | AF38: =IF(AE38>0,"yes","") | AG38: =COUNTIF(O38,"=*customer*")+COUNTIF(O38,"=*employee*")+COUNTIF(O38,"=*guest*")+COUNTIF(O38,"=*passen*")+COUNTIF(O38,"=*applicant*")+COUNTIF(O38,"=*client*") -> 0 | AH38: =IF(AG38>0,"yes","") | AI38: =COUNTIF(O38,"=*user*")+COUNTIF(O38,"=*code*")+COUNTIF(O38,"=*software*")+COUNTIF(O38,"=*system*")+COUNTIF(O38,"=*text*")+COUNTIF(O38,"=*api*")+COUNTIF(O38,"=*cyber*") -> 1 | AJ38: =IF(AI38>0,"yes","") -> yes | AK38: =COUNTIF(O38,"=*not disclosed*") -> 0 | AL38: =IF(AK38>0,"yes","") | AM38: =IF(C38="yes",D38,"") | AN38: =IF(H38="yes",I38,"") | AO38: =M38 -> 2019 | AP38: =IF(C38="yes",IF(AO38=D38,"same year",IF(AO38<D38,"before",IF(AO38>D38,"after"))),"") | AQ38: =IF(C38="yes",IF(AP38="before",D38-AO38,IF(AP38="after",AO38-D38,IF(AP38="same year",0))),"") | AR38: =IF(H38="yes",IF(AO38=I38,"same year",IF(AO38<I38,"before",IF(AO38>I38,"after"))),"") | AS38: =IF(H38="yes",IF(AR38="same year",0,IF(AR38="before",I38-AO38,IF(AR38="after",AO38-I38))),"") | AT38: =IF(R38="yes",IF(AO38<2018,"before",IF(AO38=2018,"same year",IF(AO38>2018,"after"))),"") -> after | AU38: =IF(R38="yes",IF(AT38="before",2018-AO38,IF(AT38="after",AO38-2018,IF(AT38="same year",0))),"") -> 1 | AV38: =IF(F38="defunct",IF(AO38=G38,"same year",IF(AO38<G38,"before",IF(AO38>=G38,"after"))),"") | AW38: =COUNTIF(P38,"=*vuln*") -> 0 | AX38: =COUNTIF(R38,"=yes") -> 1 | AY38: Canva | AZ38: =VLOOKUP(A38,certs!U:V,2,FALSE) -> https://www.canva.com/legal/compliance
A39: Capital One | B39: =VLOOKUP(A39,industry!A:B,2,FALSE) -> Financial Services | C39: =VLOOKUP(A39,acquisitions!A:D,2,FALSE) -> No | D39: =VLOOKUP(A39,acquisitions!A:D,4,FALSE) -> N/A | E39: =VLOOKUP(A39,acquisitions!A:D,3,FALSE) -> N/A | F39: =VLOOKUP(A39,acquisitions!I:K,2,FALSE) -> Active | G39: =IF(F39="active","",VLOOKUP(A39,acquisitions!I:K,3,FALSE)) | H39: =VLOOKUP(A39,public!A:D,2,FALSE) -> Yes | I39: =VLOOKUP(A39,public!J:K,2,FALSE) -> 1994 | J39: =VLOOKUP(A39,'net worth'!B:C,2,FALSE) -> 37250000000 | K39: =VLOOKUP(A39,public!A:D,3,FALSE) -> NYSE | L39: =VLOOKUP(A39,public!A:D,4,FALSE) -> COF | M39: 2019 | N39: 106000000 | O39: Personal and financial data | P39: Credential Stuffing | Q39: PCI DSS, GLBA | T39: yes | V39: yes | AA39: =COUNTIF(O39,"=*personal*")+COUNTIF(O39,"=*ssn*")++COUNTIF(O39,"=*license*")+COUNTIF(O39,"=*email*")+COUNTIF(O39,"=*vehic*")+COUNTIF(O39,"=*profile*")+COUNTIF(O39,"=*account*")+COUNTIF(O39,"=*image*")+COUNTIF(O39,"=*phone*")+COUNTIF(O39,"=*photo*") -> 1 | AB39: =IF(AA39>0,"yes","") -> yes | AC39: =COUNTIF(O39,"=*financ*")+COUNTIF(O39,"=*card*")+COUNTIF(O39,"=*crypto*")+COUNTIF(O39,"=*bank*")+COUNTIF(O39,"=*pay*") -> 1 | AD39: =IF(AC39>0,"yes","") -> yes | AE39: =COUNTIF(O39,"=*health*")+COUNTIF(O39,"=*bio*")+COUNTIF(O39,"=*medic*")+COUNTIF(O39,"=*patient*") -> 0 | AF39: =IF(AE39>0,"yes","") | AG39: =COUNTIF(O39,"=*customer*")+COUNTIF(O39,"=*employee*")+COUNTIF(O39,"=*guest*")+COUNTIF(O39,"=*passen*")+COUNTIF(O39,"=*applicant*")+COUNTIF(O39,"=*client*") -> 0 | AH39: =IF(AG39>0,"yes","") | AI39: =COUNTIF(O39,"=*user*")+COUNTIF(O39,"=*code*")+COUNTIF(O39,"=*software*")+COUNTIF(O39,"=*system*")+COUNTIF(O39,"=*text*")+COUNTIF(O39,"=*api*")+COUNTIF(O39,"=*cyber*") -> 0 | AJ39: =IF(AI39>0,"yes","") | AK39: =COUNTIF(O39,"=*not disclosed*") -> 0 | AL39: =IF(AK39>0,"yes","") | AM39: =IF(C39="yes",D39,"") | AN39: =IF(H39="yes",I39,"") -> 1994 | AO39: =M39 -> 2019 | AP39: =IF(C39="yes",IF(AO39=D39,"same year",IF(AO39<D39,"before",IF(AO39>D39,"after"))),"") | AQ39: =IF(C39="yes",IF(AP39="before",D39-AO39,IF(AP39="after",AO39-D39,IF(AP39="same year",0))),"") | AR39: =IF(H39="yes",IF(AO39=I39,"same year",IF(AO39<I39,"before",IF(AO39>I39,"after"))),"") -> after | AS39: =IF(H39="yes",IF(AR39="same year",0,IF(AR39="before",I39-AO39,IF(AR39="after",AO39-I39))),"") -> 25 | AT39: =IF(R39="yes",IF(AO39<2018,"before",IF(AO39=2018,"same year",IF(AO39>2018,"after"))),"") | AU39: =IF(R39="yes",IF(AT39="before",2018-AO39,IF(AT39="after",AO39-2018,IF(AT39="same year",0))),"") | AV39: =IF(F39="defunct",IF(AO39=G39,"same year",IF(AO39<G39,"before",IF(AO39>=G39,"after"))),"") | AW39: =COUNTIF(P39,"=*vuln*") -> 0 | AX39: =COUNTIF(R39,"=yes") -> 0 | AY39: Capital One | AZ39: =VLOOKUP(A39,certs!U:V,2,FALSE) -> https://www.capitalone.com/compliance
A40: Carnival Corporation | B40: =VLOOKUP(A40,industry!A:B,2,FALSE) -> Travel & Leisure | C40: =VLOOKUP(A40,acquisitions!A:D,2,FALSE) -> No | D40: =VLOOKUP(A40,acquisitions!A:D,4,FALSE) -> N/A | E40: =VLOOKUP(A40,acquisitions!A:D,3,FALSE) -> N/A | F40: =VLOOKUP(A40,acquisitions!I:K,2,FALSE) -> Active | G40: =IF(F40="active","",VLOOKUP(A40,acquisitions!I:K,3,FALSE)) | H40: =VLOOKUP(A40,public!A:D,2,FALSE) -> Yes | I40: =VLOOKUP(A40,public!J:K,2,FALSE) -> 1987 | J40: =VLOOKUP(A40,'net worth'!B:C,2,FALSE) -> 20290000000 | K40: =VLOOKUP(A40,public!A:D,3,FALSE) -> NYSE | L40: =VLOOKUP(A40,public!A:D,4,FALSE) -> CCL | M40: 2020 | N40: Unknown | O40: Personal data, health information | P40: Unsecured Database | Q40: HIPAA, GDPR | R40: yes | W40: yes | AA40: =COUNTIF(O40,"=*personal*")+COUNTIF(O40,"=*ssn*")++COUNTIF(O40,"=*license*")+COUNTIF(O40,"=*email*")+COUNTIF(O40,"=*vehic*")+COUNTIF(O40,"=*profile*")+COUNTIF(O40,"=*account*")+COUNTIF(O40,"=*image*")+COUNTIF(O40,"=*phone*")+COUNTIF(O40,"=*photo*") -> 1 | AB40: =IF(AA40>0,"yes","") -> yes | AC40: =COUNTIF(O40,"=*financ*")+COUNTIF(O40,"=*card*")+COUNTIF(O40,"=*crypto*")+COUNTIF(O40,"=*bank*")+COUNTIF(O40,"=*pay*") -> 0 | AD40: =IF(AC40>0,"yes","") | AE40: =COUNTIF(O40,"=*health*")+COUNTIF(O40,"=*bio*")+COUNTIF(O40,"=*medic*")+COUNTIF(O40,"=*patient*") -> 1 | AF40: =IF(AE40>0,"yes","") -> yes | AG40: =COUNTIF(O40,"=*customer*")+COUNTIF(O40,"=*employee*")+COUNTIF(O40,"=*guest*")+COUNTIF(O40,"=*passen*")+COUNTIF(O40,"=*applicant*")+COUNTIF(O40,"=*client*") -> 0 | AH40: =IF(AG40>0,"yes","") | AI40: =COUNTIF(O40,"=*user*")+COUNTIF(O40,"=*code*")+COUNTIF(O40,"=*software*")+COUNTIF(O40,"=*system*")+COUNTIF(O40,"=*text*")+COUNTIF(O40,"=*api*")+COUNTIF(O40,"=*cyber*") -> 0 | AJ40: =IF(AI40>0,"yes","") | AK40: =COUNTIF(O40,"=*not disclosed*") -> 0 | AL40: =IF(AK40>0,"yes","") | AM40: =IF(C40="yes",D40,"") | AN40: =IF(H40="yes",I40,"") -> 1987 | AO40: =M40 -> 2020 | AP40: =IF(C40="yes",IF(AO40=D40,"same year",IF(AO40<D40,"before",IF(AO40>D40,"after"))),"") | AQ40: =IF(C40="yes",IF(AP40="before",D40-AO40,IF(AP40="after",AO40-D40,IF(AP40="same year",0))),"") | AR40: =IF(H40="yes",IF(AO40=I40,"same year",IF(AO40<I40,"before",IF(AO40>I40,"after"))),"") -> after | AS40: =IF(H40="yes",IF(AR40="same year",0,IF(AR40="before",I40-AO40,IF(AR40="after",AO40-I40))),"") -> 33 | AT40: =IF(R40="yes",IF(AO40<2018,"before",IF(AO40=2018,"same year",IF(AO40>2018,"after"))),"") -> after | AU40: =IF(R40="yes",IF(AT40="before",2018-AO40,IF(AT40="after",AO40-2018,IF(AT40="same year",0))),"") -> 2 | AV40: =IF(F40="defunct",IF(AO40=G40,"same year",IF(AO40<G40,"before",IF(AO40>=G40,"after"))),"") | AW40: =COUNTIF(P40,"=*vuln*") -> 0 | AX40: =COUNTIF(R40,"=yes") -> 1 | AY40: Carnival Corporation | AZ40: =VLOOKUP(A40,certs!U:V,2,FALSE) -> https://www.carnivalcorp.com/legal-compliance
A41: Cash App (Block) | B41: =VLOOKUP(A41,industry!A:B,2,FALSE) -> Financial Technology (FinTech) | C41: =VLOOKUP(A41,acquisitions!A:D,2,FALSE) -> No | D41: =VLOOKUP(A41,acquisitions!A:D,4,FALSE) -> N/A | E41: =VLOOKUP(A41,acquisitions!A:D,3,FALSE) -> N/A | F41: =VLOOKUP(A41,acquisitions!I:K,2,FALSE) -> Active | G41: =IF(F41="active","",VLOOKUP(A41,acquisitions!I:K,3,FALSE)) | H41: =VLOOKUP(A41,public!A:D,2,FALSE) -> Yes | I41: =VLOOKUP(A41,public!J:K,2,FALSE) -> 2015 | J41: =VLOOKUP(A41,'net worth'!B:C,2,FALSE) -> 42490000000 | K41: =VLOOKUP(A41,public!A:D,3,FALSE) -> NYSE | L41: =VLOOKUP(A41,public!A:D,4,FALSE) -> SQ | M41: 2022 | N41: 8000000 | O41: Customer names, portfolio values | P41: Unauthorized access by a former employee | Q41: GDPR | R41: yes | AA41: =COUNTIF(O41,"=*personal*")+COUNTIF(O41,"=*ssn*")++COUNTIF(O41,"=*license*")+COUNTIF(O41,"=*email*")+COUNTIF(O41,"=*vehic*")+COUNTIF(O41,"=*profile*")+COUNTIF(O41,"=*account*")+COUNTIF(O41,"=*image*")+COUNTIF(O41,"=*phone*")+COUNTIF(O41,"=*photo*") -> 0 | AB41: =IF(AA41>0,"yes","") | AC41: =COUNTIF(O41,"=*financ*")+COUNTIF(O41,"=*card*")+COUNTIF(O41,"=*crypto*")+COUNTIF(O41,"=*bank*")+COUNTIF(O41,"=*pay*") -> 0 | AD41: =IF(AC41>0,"yes","") | AE41: =COUNTIF(O41,"=*health*")+COUNTIF(O41,"=*bio*")+COUNTIF(O41,"=*medic*")+COUNTIF(O41,"=*patient*") -> 0 | AF41: =IF(AE41>0,"yes","") | AG41: =COUNTIF(O41,"=*customer*")+COUNTIF(O41,"=*employee*")+COUNTIF(O41,"=*guest*")+COUNTIF(O41,"=*passen*")+COUNTIF(O41,"=*applicant*")+COUNTIF(O41,"=*client*") -> 1 | AH41: =IF(AG41>0,"yes","") -> yes | AI41: =COUNTIF(O41,"=*user*")+COUNTIF(O41,"=*code*")+COUNTIF(O41,"=*software*")+COUNTIF(O41,"=*system*")+COUNTIF(O41,"=*text*")+COUNTIF(O41,"=*api*")+COUNTIF(O41,"=*cyber*") -> 0 | AJ41: =IF(AI41>0,"yes","") | AK41: =COUNTIF(O41,"=*not disclosed*") -> 0 | AL41: =IF(AK41>0,"yes","") | AM41: =IF(C41="yes",D41,"") | AN41: =IF(H41="yes",I41,"") -> 2015 | AO41: =M41 -> 2022 | AP41: =IF(C41="yes",IF(AO41=D41,"same year",IF(AO41<D41,"before",IF(AO41>D41,"after"))),"") | AQ41: =IF(C41="yes",IF(AP41="before",D41-AO41,IF(AP41="after",AO41-D41,IF(AP41="same year",0))),"") | AR41: =IF(H41="yes",IF(AO41=I41,"same year",IF(AO41<I41,"before",IF(AO41>I41,"after"))),"") -> after | AS41: =IF(H41="yes",IF(AR41="same year",0,IF(AR41="before",I41-AO41,IF(AR41="after",AO41-I41))),"") -> 7 | AT41: =IF(R41="yes",IF(AO41<2018,"before",IF(AO41=2018,"same year",IF(AO41>2018,"after"))),"") -> after | AU41: =IF(R41="yes",IF(AT41="before",2018-AO41,IF(AT41="after",AO41-2018,IF(AT41="same year",0))),"") -> 4 | AV41: =IF(F41="defunct",IF(AO41=G41,"same year",IF(AO41<G41,"before",IF(AO41>=G41,"after"))),"") | AW41: =COUNTIF(P41,"=*vuln*") -> 0 | AX41: =COUNTIF(R41,"=yes") -> 1 | AY41: Cash App (Block) | AZ41: =VLOOKUP(A41,certs!U:V,2,FALSE) -> https://www.cash.app/legal/compliance
A42: Cathay Pacific Airways | B42: =VLOOKUP(A42,industry!A:B,2,FALSE) -> Airlines | C42: =VLOOKUP(A42,acquisitions!A:D,2,FALSE) -> No | D42: =VLOOKUP(A42,acquisitions!A:D,4,FALSE) -> N/A | E42: =VLOOKUP(A42,acquisitions!A:D,3,FALSE) -> N/A | F42: =VLOOKUP(A42,acquisitions!I:K,2,FALSE) -> Active | G42: =IF(F42="active","",VLOOKUP(A42,acquisitions!I:K,3,FALSE)) | H42: =VLOOKUP(A42,public!A:D,2,FALSE) -> No | I42: =VLOOKUP(A42,public!J:K,2,FALSE) -> #N/A | K42: =VLOOKUP(A42,public!A:D,3,FALSE) -> N/A | L42: =VLOOKUP(A42,public!A:D,4,FALSE) -> N/A | M42: 2018 | N42: 9400000 | O42: Passenger data, identity details | P42: System Vulnerability Exploit | Q42: GDPR | R42: yes | AA42: =COUNTIF(O42,"=*personal*")+COUNTIF(O42,"=*ssn*")++COUNTIF(O42,"=*license*")+COUNTIF(O42,"=*email*")+COUNTIF(O42,"=*vehic*")+COUNTIF(O42,"=*profile*")+COUNTIF(O42,"=*account*")+COUNTIF(O42,"=*image*")+COUNTIF(O42,"=*phone*")+COUNTIF(O42,"=*photo*") -> 0 | AB42: =IF(AA42>0,"yes","") | AC42: =COUNTIF(O42,"=*financ*")+COUNTIF(O42,"=*card*")+COUNTIF(O42,"=*crypto*")+COUNTIF(O42,"=*bank*")+COUNTIF(O42,"=*pay*") -> 0 | AD42: =IF(AC42>0,"yes","") | AE42: =COUNTIF(O42,"=*health*")+COUNTIF(O42,"=*bio*")+COUNTIF(O42,"=*medic*")+COUNTIF(O42,"=*patient*") -> 0 | AF42: =IF(AE42>0,"yes","") | AG42: =COUNTIF(O42,"=*customer*")+COUNTIF(O42,"=*employee*")+COUNTIF(O42,"=*guest*")+COUNTIF(O42,"=*passen*")+COUNTIF(O42,"=*applicant*")+COUNTIF(O42,"=*client*") -> 1 | AH42: =IF(AG42>0,"yes","") -> yes | AI42: =COUNTIF(O42,"=*user*")+COUNTIF(O42,"=*code*")+COUNTIF(O42,"=*software*")+COUNTIF(O42,"=*system*")+COUNTIF(O42,"=*text*")+COUNTIF(O42,"=*api*")+COUNTIF(O42,"=*cyber*") -> 0 | AJ42: =IF(AI42>0,"yes","") | AK42: =COUNTIF(O42,"=*not disclosed*") -> 0 | AL42: =IF(AK42>0,"yes","") | AM42: =IF(C42="yes",D42,"") | AN42: =IF(H42="yes",I42,"") | AO42: =M42 -> 2018 | AP42: =IF(C42="yes",IF(AO42=D42,"same year",IF(AO42<D42,"before",IF(AO42>D42,"after"))),"") | AQ42: =IF(C42="yes",IF(AP42="before",D42-AO42,IF(AP42="after",AO42-D42,IF(AP42="same year",0))),"") | AR42: =IF(H42="yes",IF(AO42=I42,"same year",IF(AO42<I42,"before",IF(AO42>I42,"after"))),"") | AS42: =IF(H42="yes",IF(AR42="same year",0,IF(AR42="before",I42-AO42,IF(AR42="after",AO42-I42))),"") | AT42: =IF(R42="yes",IF(AO42<2018,"before",IF(AO42=2018,"same year",IF(AO42>2018,"after"))),"") -> same year | AU42: =IF(R42="yes",IF(AT42="before",2018-AO42,IF(AT42="after",AO42-2018,IF(AT42="same year",0))),"") -> 0 | AV42: =IF(F42="defunct",IF(AO42=G42,"same year",IF(AO42<G42,"before",IF(AO42>=G42,"after"))),"") | AW42: =COUNTIF(P42,"=*vuln*") -> 1 | AX42: =COUNTIF(R42,"=yes") -> 1 | AY42: Cathay Pacific Airways | AZ42: =VLOOKUP(A42,certs!U:V,2,FALSE) -> https://www.cathaypacific.com/legal/compliance
A43: Change Healthcare | B43: =VLOOKUP(A43,industry!A:B,2,FALSE) -> Healthcare | C43: =VLOOKUP(A43,acquisitions!A:D,2,FALSE) -> Yes | D43: =VLOOKUP(A43,acquisitions!A:D,4,FALSE) -> 2022 | E43: =VLOOKUP(A43,acquisitions!A:D,3,FALSE) -> Optum | F43: =VLOOKUP(A43,acquisitions!I:K,2,FALSE) -> Active | G43: =IF(F43="active","",VLOOKUP(A43,acquisitions!I:K,3,FALSE)) | H43: =VLOOKUP(A43,public!A:D,2,FALSE) -> Yes | I43: =VLOOKUP(A43,public!J:K,2,FALSE) -> 2019 | J43: =VLOOKUP(A43,'net worth'!B:C,2,FALSE) -> 10430000000 | K43: =VLOOKUP(A43,public!A:D,3,FALSE) -> NASDAQ | L43: =VLOOKUP(A43,public!A:D,4,FALSE) -> CHNG | M43: 2024 | N43: 190000000 | O43: Protected health information | P43: Ransomware | Q43: HIPAA, PCI DSS | T43: yes | W43: yes | AA43: =COUNTIF(O43,"=*personal*")+COUNTIF(O43,"=*ssn*")++COUNTIF(O43,"=*license*")+COUNTIF(O43,"=*email*")+COUNTIF(O43,"=*vehic*")+COUNTIF(O43,"=*profile*")+COUNTIF(O43,"=*account*")+COUNTIF(O43,"=*image*")+COUNTIF(O43,"=*phone*")+COUNTIF(O43,"=*photo*") -> 0 | AB43: =IF(AA43>0,"yes","") | AC43: =COUNTIF(O43,"=*financ*")+COUNTIF(O43,"=*card*")+COUNTIF(O43,"=*crypto*")+COUNTIF(O43,"=*bank*")+COUNTIF(O43,"=*pay*") -> 0 | AD43: =IF(AC43>0,"yes","") | AE43: =COUNTIF(O43,"=*health*")+COUNTIF(O43,"=*bio*")+COUNTIF(O43,"=*medic*")+COUNTIF(O43,"=*patient*") -> 1 | AF43: =IF(AE43>0,"yes","") -> yes | AG43: =COUNTIF(O43,"=*customer*")+COUNTIF(O43,"=*employee*")+COUNTIF(O43,"=*guest*")+COUNTIF(O43,"=*passen*")+COUNTIF(O43,"=*applicant*")+COUNTIF(O43,"=*client*") -> 0 | AH43: =IF(AG43>0,"yes","") | AI43: =COUNTIF(O43,"=*user*")+COUNTIF(O43,"=*code*")+COUNTIF(O43,"=*software*")+COUNTIF(O43,"=*system*")+COUNTIF(O43,"=*text*")+COUNTIF(O43,"=*api*")+COUNTIF(O43,"=*cyber*") -> 0 | AJ43: =IF(AI43>0,"yes","") | AK43: =COUNTIF(O43,"=*not disclosed*") -> 0 | AL43: =IF(AK43>0,"yes","") | AM43: =IF(C43="yes",D43,"") -> 2022 | AN43: =IF(H43="yes",I43,"") -> 2019 | AO43: =M43 -> 2024 | AP43: =IF(C43="yes",IF(AO43=D43,"same year",IF(AO43<D43,"before",IF(AO43>D43,"after"))),"") -> after | AQ43: =IF(C43="yes",IF(AP43="before",D43-AO43,IF(AP43="after",AO43-D43,IF(AP43="same year",0))),"") -> 2 | AR43: =IF(H43="yes",IF(AO43=I43,"same year",IF(AO43<I43,"before",IF(AO43>I43,"after"))),"") -> after | AS43: =IF(H43="yes",IF(AR43="same year",0,IF(AR43="before",I43-AO43,IF(AR43="after",AO43-I43))),"") -> 5 | AT43: =IF(R43="yes",IF(AO43<2018,"before",IF(AO43=2018,"same year",IF(AO43>2018,"after"))),"") | AU43: =IF(R43="yes",IF(AT43="before",2018-AO43,IF(AT43="after",AO43-2018,IF(AT43="same year",0))),"") | AV43: =IF(F43="defunct",IF(AO43=G43,"same year",IF(AO43<G43,"before",IF(AO43>=G43,"after"))),"") | AW43: =COUNTIF(P43,"=*vuln*") -> 0 | AX43: =COUNTIF(R43,"=yes") -> 0 | AY43: Change Healthcare | AZ43: =VLOOKUP(A43,certs!U:V,2,FALSE) -> https://www.changehealthcare.com/legal/compliance
A44: ChatGPT (OpenAI) | B44: =VLOOKUP(A44,industry!A:B,2,FALSE) -> Technology | C44: =VLOOKUP(A44,acquisitions!A:D,2,FALSE) -> No | D44: =VLOOKUP(A44,acquisitions!A:D,4,FALSE) -> N/A | E44: =VLOOKUP(A44,acquisitions!A:D,3,FALSE) -> N/A | F44: =VLOOKUP(A44,acquisitions!I:K,2,FALSE) -> Active | G44: =IF(F44="active","",VLOOKUP(A44,acquisitions!I:K,3,FALSE)) | H44: =VLOOKUP(A44,public!A:D,2,FALSE) -> No | I44: =VLOOKUP(A44,public!J:K,2,FALSE) -> #N/A | K44: =VLOOKUP(A44,public!A:D,3,FALSE) -> N/A | L44: =VLOOKUP(A44,public!A:D,4,FALSE) -> N/A | M44: 2023 | N44: Not disclosed | O44: Names, email addresses | P44: API Vulnerability Exploit | Q44: GDPR, CCPA | R44: yes | Y44: yes | AA44: =COUNTIF(O44,"=*personal*")+COUNTIF(O44,"=*ssn*")++COUNTIF(O44,"=*license*")+COUNTIF(O44,"=*email*")+COUNTIF(O44,"=*vehic*")+COUNTIF(O44,"=*profile*")+COUNTIF(O44,"=*account*")+COUNTIF(O44,"=*image*")+COUNTIF(O44,"=*phone*")+COUNTIF(O44,"=*photo*") -> 1 | AB44: =IF(AA44>0,"yes","") -> yes | AC44: =COUNTIF(O44,"=*financ*")+COUNTIF(O44,"=*card*")+COUNTIF(O44,"=*crypto*")+COUNTIF(O44,"=*bank*")+COUNTIF(O44,"=*pay*") -> 0 | AD44: =IF(AC44>0,"yes","") | AE44: =COUNTIF(O44,"=*health*")+COUNTIF(O44,"=*bio*")+COUNTIF(O44,"=*medic*")+COUNTIF(O44,"=*patient*") -> 0 | AF44: =IF(AE44>0,"yes","") | AG44: =COUNTIF(O44,"=*customer*")+COUNTIF(O44,"=*employee*")+COUNTIF(O44,"=*guest*")+COUNTIF(O44,"=*passen*")+COUNTIF(O44,"=*applicant*")+COUNTIF(O44,"=*client*") -> 0 | AH44: =IF(AG44>0,"yes","") | AI44: =COUNTIF(O44,"=*user*")+COUNTIF(O44,"=*code*")+COUNTIF(O44,"=*software*")+COUNTIF(O44,"=*system*")+COUNTIF(O44,"=*text*")+COUNTIF(O44,"=*api*")+COUNTIF(O44,"=*cyber*") -> 0 | AJ44: =IF(AI44>0,"yes","") | AK44: =COUNTIF(O44,"=*not disclosed*") -> 0 | AL44: =IF(AK44>0,"yes","") | AM44: =IF(C44="yes",D44,"") | AN44: =IF(H44="yes",I44,"") | AO44: =M44 -> 2023 | AP44: =IF(C44="yes",IF(AO44=D44,"same year",IF(AO44<D44,"before",IF(AO44>D44,"after"))),"") | AQ44: =IF(C44="yes",IF(AP44="before",D44-AO44,IF(AP44="after",AO44-D44,IF(AP44="same year",0))),"") | AR44: =IF(H44="yes",IF(AO44=I44,"same year",IF(AO44<I44,"before",IF(AO44>I44,"after"))),"") | AS44: =IF(H44="yes",IF(AR44="same year",0,IF(AR44="before",I44-AO44,IF(AR44="after",AO44-I44))),"") | AT44: =IF(R44="yes",IF(AO44<2018,"before",IF(AO44=2018,"same year",IF(AO44>2018,"after"))),"") -> after | AU44: =IF(R44="yes",IF(AT44="before",2018-AO44,IF(AT44="after",AO44-2018,IF(AT44="same year",0))),"") -> 5 | AV44: =IF(F44="defunct",IF(AO44=G44,"same year",IF(AO44<G44,"before",IF(AO44>=G44,"after"))),"") | AW44: =COUNTIF(P44,"=*vuln*") -> 1 | AX44: =COUNTIF(R44,"=yes") -> 1 | AY44: ChatGPT (OpenAI) | AZ44: =VLOOKUP(A44,certs!U:V,2,FALSE) -> https://openai.com/legal/compliance
A45: CheckPeople | B45: =VLOOKUP(A45,industry!A:B,2,FALSE) -> Technology | C45: =VLOOKUP(A45,acquisitions!A:D,2,FALSE) -> No | D45: =VLOOKUP(A45,acquisitions!A:D,4,FALSE) -> N/A | E45: =VLOOKUP(A45,acquisitions!A:D,3,FALSE) -> N/A | F45: =VLOOKUP(A45,acquisitions!I:K,2,FALSE) -> Active | G45: =IF(F45="active","",VLOOKUP(A45,acquisitions!I:K,3,FALSE)) | H45: =VLOOKUP(A45,public!A:D,2,FALSE) -> No | I45: =VLOOKUP(A45,public!J:K,2,FALSE) -> #N/A | K45: =VLOOKUP(A45,public!A:D,3,FALSE) -> N/A | L45: =VLOOKUP(A45,public!A:D,4,FALSE) -> N/A | M45: 2019 | N45: 56000000 | O45: Personal details from public records | P45: Misconfigured Firewall | Q45: GDPR | R45: yes | AA45: =COUNTIF(O45,"=*personal*")+COUNTIF(O45,"=*ssn*")++COUNTIF(O45,"=*license*")+COUNTIF(O45,"=*email*")+COUNTIF(O45,"=*vehic*")+COUNTIF(O45,"=*profile*")+COUNTIF(O45,"=*account*")+COUNTIF(O45,"=*image*")+COUNTIF(O45,"=*phone*")+COUNTIF(O45,"=*photo*") -> 1 | AB45: =IF(AA45>0,"yes","") -> yes | AC45: =COUNTIF(O45,"=*financ*")+COUNTIF(O45,"=*card*")+COUNTIF(O45,"=*crypto*")+COUNTIF(O45,"=*bank*")+COUNTIF(O45,"=*pay*") -> 0 | AD45: =IF(AC45>0,"yes","") | AE45: =COUNTIF(O45,"=*health*")+COUNTIF(O45,"=*bio*")+COUNTIF(O45,"=*medic*")+COUNTIF(O45,"=*patient*") -> 0 | AF45: =IF(AE45>0,"yes","") | AG45: =COUNTIF(O45,"=*customer*")+COUNTIF(O45,"=*employee*")+COUNTIF(O45,"=*guest*")+COUNTIF(O45,"=*passen*")+COUNTIF(O45,"=*applicant*")+COUNTIF(O45,"=*client*") -> 0 | AH45: =IF(AG45>0,"yes","") | AI45: =COUNTIF(O45,"=*user*")+COUNTIF(O45,"=*code*")+COUNTIF(O45,"=*software*")+COUNTIF(O45,"=*system*")+COUNTIF(O45,"=*text*")+COUNTIF(O45,"=*api*")+COUNTIF(O45,"=*cyber*") -> 0 | AJ45: =IF(AI45>0,"yes","") | AK45: =COUNTIF(O45,"=*not disclosed*") -> 0 | AL45: =IF(AK45>0,"yes","") | AM45: =IF(C45="yes",D45,"") | AN45: =IF(H45="yes",I45,"") | AO45: =M45 -> 2019 | AP45: =IF(C45="yes",IF(AO45=D45,"same year",IF(AO45<D45,"before",IF(AO45>D45,"after"))),"") | AQ45: =IF(C45="yes",IF(AP45="before",D45-AO45,IF(AP45="after",AO45-D45,IF(AP45="same year",0))),"") | AR45: =IF(H45="yes",IF(AO45=I45,"same year",IF(AO45<I45,"before",IF(AO45>I45,"after"))),"") | AS45: =IF(H45="yes",IF(AR45="same year",0,IF(AR45="before",I45-AO45,IF(AR45="after",AO45-I45))),"") | AT45: =IF(R45="yes",IF(AO45<2018,"before",IF(AO45=2018,"same year",IF(AO45>2018,"after"))),"") -> after | AU45: =IF(R45="yes",IF(AT45="before",2018-AO45,IF(AT45="after",AO45-2018,IF(AT45="same year",0))),"") -> 1 | AV45: =IF(F45="defunct",IF(AO45=G45,"same year",IF(AO45<G45,"before",IF(AO45>=G45,"after"))),"") | AW45: =COUNTIF(P45,"=*vuln*") -> 0 | AX45: =COUNTIF(R45,"=yes") -> 1 | AY45: CheckPeople | AZ45: =VLOOKUP(A45,certs!U:V,2,FALSE) -> https://www.checkpeople.com/legal/compliance
A46: Chowbus | B46: =VLOOKUP(A46,industry!A:B,2,FALSE) -> Food Delivery | C46: =VLOOKUP(A46,acquisitions!A:D,2,FALSE) -> No | D46: =VLOOKUP(A46,acquisitions!A:D,4,FALSE) -> N/A | E46: =VLOOKUP(A46,acquisitions!A:D,3,FALSE) -> N/A | F46: =VLOOKUP(A46,acquisitions!I:K,2,FALSE) -> Active | G46: =IF(F46="active","",VLOOKUP(A46,acquisitions!I:K,3,FALSE)) | H46: =VLOOKUP(A46,public!A:D,2,FALSE) -> No | I46: =VLOOKUP(A46,public!J:K,2,FALSE) -> #N/A | K46: =VLOOKUP(A46,public!A:D,3,FALSE) -> N/A | L46: =VLOOKUP(A46,public!A:D,4,FALSE) -> N/A | M46: 2020 | N46: 800000 | O46: Customer names, emails, addresses | P46: Ransomware | Q46: GDPR | R46: yes | AA46: =COUNTIF(O46,"=*personal*")+COUNTIF(O46,"=*ssn*")++COUNTIF(O46,"=*license*")+COUNTIF(O46,"=*email*")+COUNTIF(O46,"=*vehic*")+COUNTIF(O46,"=*profile*")+COUNTIF(O46,"=*account*")+COUNTIF(O46,"=*image*")+COUNTIF(O46,"=*phone*")+COUNTIF(O46,"=*photo*") -> 1 | AB46: =IF(AA46>0,"yes","") -> yes | AC46: =COUNTIF(O46,"=*financ*")+COUNTIF(O46,"=*card*")+COUNTIF(O46,"=*crypto*")+COUNTIF(O46,"=*bank*")+COUNTIF(O46,"=*pay*") -> 0 | AD46: =IF(AC46>0,"yes","") | AE46: =COUNTIF(O46,"=*health*")+COUNTIF(O46,"=*bio*")+COUNTIF(O46,"=*medic*")+COUNTIF(O46,"=*patient*") -> 0 | AF46: =IF(AE46>0,"yes","") | AG46: =COUNTIF(O46,"=*customer*")+COUNTIF(O46,"=*employee*")+COUNTIF(O46,"=*guest*")+COUNTIF(O46,"=*passen*")+COUNTIF(O46,"=*applicant*")+COUNTIF(O46,"=*client*") -> 1 | AH46: =IF(AG46>0,"yes","") -> yes | AI46: =COUNTIF(O46,"=*user*")+COUNTIF(O46,"=*code*")+COUNTIF(O46,"=*software*")+COUNTIF(O46,"=*system*")+COUNTIF(O46,"=*text*")+COUNTIF(O46,"=*api*")+COUNTIF(O46,"=*cyber*") -> 0 | AJ46: =IF(AI46>0,"yes","") | AK46: =COUNTIF(O46,"=*not disclosed*") -> 0 | AL46: =IF(AK46>0,"yes","") | AM46: =IF(C46="yes",D46,"") | AN46: =IF(H46="yes",I46,"") | AO46: =M46 -> 2020 | AP46: =IF(C46="yes",IF(AO46=D46,"same year",IF(AO46<D46,"before",IF(AO46>D46,"after"))),"") | AQ46: =IF(C46="yes",IF(AP46="before",D46-AO46,IF(AP46="after",AO46-D46,IF(AP46="same year",0))),"") | AR46: =IF(H46="yes",IF(AO46=I46,"same year",IF(AO46<I46,"before",IF(AO46>I46,"after"))),"") | AS46: =IF(H46="yes",IF(AR46="same year",0,IF(AR46="before",I46-AO46,IF(AR46="after",AO46-I46))),"") | AT46: =IF(R46="yes",IF(AO46<2018,"before",IF(AO46=2018,"same year",IF(AO46>2018,"after"))),"") -> after | AU46: =IF(R46="yes",IF(AT46="before",2018-AO46,IF(AT46="after",AO46-2018,IF(AT46="same year",0))),"") -> 2 | AV46: =IF(F46="defunct",IF(AO46=G46,"same year",IF(AO46<G46,"before",IF(AO46>=G46,"after"))),"") | AW46: =COUNTIF(P46,"=*vuln*") -> 0 | AX46: =COUNTIF(R46,"=yes") -> 1 | AY46: Chowbus | AZ46: =VLOOKUP(A46,certs!U:V,2,FALSE) -> https://www.chowbus.com/legal/compliance
A47: City of Durham, NC | B47: =VLOOKUP(A47,industry!A:B,2,FALSE) -> Government | C47: =VLOOKUP(A47,acquisitions!A:D,2,FALSE) -> No | D47: =VLOOKUP(A47,acquisitions!A:D,4,FALSE) -> N/A | E47: =VLOOKUP(A47,acquisitions!A:D,3,FALSE) -> N/A | F47: =VLOOKUP(A47,acquisitions!I:K,2,FALSE) -> Active | G47: =IF(F47="active","",VLOOKUP(A47,acquisitions!I:K,3,FALSE)) | H47: =VLOOKUP(A47,public!A:D,2,FALSE) -> No | I47: =VLOOKUP(A47,public!J:K,2,FALSE) -> #N/A | K47: =VLOOKUP(A47,public!A:D,3,FALSE) -> N/A | L47: =VLOOKUP(A47,public!A:D,4,FALSE) -> N/A | M47: 2020 | N47: Unknown | O47: Employee and citizen data | P47: Unsecured Cloud Storage | Q47: GDPR | R47: yes | AA47: =COUNTIF(O47,"=*personal*")+COUNTIF(O47,"=*ssn*")++COUNTIF(O47,"=*license*")+COUNTIF(O47,"=*email*")+COUNTIF(O47,"=*vehic*")+COUNTIF(O47,"=*profile*")+COUNTIF(O47,"=*account*")+COUNTIF(O47,"=*image*")+COUNTIF(O47,"=*phone*")+COUNTIF(O47,"=*photo*") -> 0 | AB47: =IF(AA47>0,"yes","") | AC47: =COUNTIF(O47,"=*financ*")+COUNTIF(O47,"=*card*")+COUNTIF(O47,"=*crypto*")+COUNTIF(O47,"=*bank*")+COUNTIF(O47,"=*pay*") -> 0 | AD47: =IF(AC47>0,"yes","") | AE47: =COUNTIF(O47,"=*health*")+COUNTIF(O47,"=*bio*")+COUNTIF(O47,"=*medic*")+COUNTIF(O47,"=*patient*") -> 0 | AF47: =IF(AE47>0,"yes","") | AG47: =COUNTIF(O47,"=*customer*")+COUNTIF(O47,"=*employee*")+COUNTIF(O47,"=*guest*")+COUNTIF(O47,"=*passen*")+COUNTIF(O47,"=*applicant*")+COUNTIF(O47,"=*client*") -> 1 | AH47: =IF(AG47>0,"yes","") -> yes | AI47: =COUNTIF(O47,"=*user*")+COUNTIF(O47,"=*code*")+COUNTIF(O47,"=*software*")+COUNTIF(O47,"=*system*")+COUNTIF(O47,"=*text*")+COUNTIF(O47,"=*api*")+COUNTIF(O47,"=*cyber*") -> 0 | AJ47: =IF(AI47>0,"yes","") | AK47: =COUNTIF(O47,"=*not disclosed*") -> 0 | AL47: =IF(AK47>0,"yes","") | AM47: =IF(C47="yes",D47,"") | AN47: =IF(H47="yes",I47,"") | AO47: =M47 -> 2020 | AP47: =IF(C47="yes",IF(AO47=D47,"same year",IF(AO47<D47,"before",IF(AO47>D47,"after"))),"") | AQ47: =IF(C47="yes",IF(AP47="before",D47-AO47,IF(AP47="after",AO47-D47,IF(AP47="same year",0))),"") | AR47: =IF(H47="yes",IF(AO47=I47,"same year",IF(AO47<I47,"before",IF(AO47>I47,"after"))),"") | AS47: =IF(H47="yes",IF(AR47="same year",0,IF(AR47="before",I47-AO47,IF(AR47="after",AO47-I47))),"") | AT47: =IF(R47="yes",IF(AO47<2018,"before",IF(AO47=2018,"same year",IF(AO47>2018,"after"))),"") -> after | AU47: =IF(R47="yes",IF(AT47="before",2018-AO47,IF(AT47="after",AO47-2018,IF(AT47="same year",0))),"") -> 2 | AV47: =IF(F47="defunct",IF(AO47=G47,"same year",IF(AO47<G47,"before",IF(AO47>=G47,"after"))),"") | AW47: =COUNTIF(P47,"=*vuln*") -> 0 | AX47: =COUNTIF(R47,"=yes") -> 1 | AY47: City of Durham, NC | AZ47: =VLOOKUP(A47,certs!U:V,2,FALSE) -> https://www.durhamnc.gov/legal/compliance
A48: Clairvia (by Cerner) | B48: =VLOOKUP(A48,industry!A:B,2,FALSE) -> Healthcare | C48: =VLOOKUP(A48,acquisitions!A:D,2,FALSE) -> Yes | D48: =VLOOKUP(A48,acquisitions!A:D,4,FALSE) -> 2011 | E48: =VLOOKUP(A48,acquisitions!A:D,3,FALSE) -> Cerner | F48: =VLOOKUP(A48,acquisitions!I:K,2,FALSE) -> Active | G48: =IF(F48="active","",VLOOKUP(A48,acquisitions!I:K,3,FALSE)) | H48: =VLOOKUP(A48,public!A:D,2,FALSE) -> No | I48: =VLOOKUP(A48,public!J:K,2,FALSE) -> #N/A | K48: =VLOOKUP(A48,public!A:D,3,FALSE) -> N/A | L48: =VLOOKUP(A48,public!A:D,4,FALSE) -> N/A | M48: 2021 | N48: Unknown | O48: Healthcare staffing information | P48: Software Vulnerability Exploit | Q48: HIPAA, GDPR | R48: yes | W48: yes | AA48: =COUNTIF(O48,"=*personal*")+COUNTIF(O48,"=*ssn*")++COUNTIF(O48,"=*license*")+COUNTIF(O48,"=*email*")+COUNTIF(O48,"=*vehic*")+COUNTIF(O48,"=*profile*")+COUNTIF(O48,"=*account*")+COUNTIF(O48,"=*image*")+COUNTIF(O48,"=*phone*")+COUNTIF(O48,"=*photo*") -> 0 | AB48: =IF(AA48>0,"yes","") | AC48: =COUNTIF(O48,"=*financ*")+COUNTIF(O48,"=*card*")+COUNTIF(O48,"=*crypto*")+COUNTIF(O48,"=*bank*")+COUNTIF(O48,"=*pay*") -> 0 | AD48: =IF(AC48>0,"yes","") | AE48: =COUNTIF(O48,"=*health*")+COUNTIF(O48,"=*bio*")+COUNTIF(O48,"=*medic*")+COUNTIF(O48,"=*patient*") -> 1 | AF48: =IF(AE48>0,"yes","") -> yes | AG48: =COUNTIF(O48,"=*customer*")+COUNTIF(O48,"=*employee*")+COUNTIF(O48,"=*guest*")+COUNTIF(O48,"=*passen*")+COUNTIF(O48,"=*applicant*")+COUNTIF(O48,"=*client*") -> 0 | AH48: =IF(AG48>0,"yes","") | AI48: =COUNTIF(O48,"=*user*")+COUNTIF(O48,"=*code*")+COUNTIF(O48,"=*software*")+COUNTIF(O48,"=*system*")+COUNTIF(O48,"=*text*")+COUNTIF(O48,"=*api*")+COUNTIF(O48,"=*cyber*") -> 0 | AJ48: =IF(AI48>0,"yes","") | AK48: =COUNTIF(O48,"=*not disclosed*") -> 0 | AL48: =IF(AK48>0,"yes","") | AM48: =IF(C48="yes",D48,"") -> 2011 | AN48: =IF(H48="yes",I48,"") | AO48: =M48 -> 2021 | AP48: =IF(C48="yes",IF(AO48=D48,"same year",IF(AO48<D48,"before",IF(AO48>D48,"after"))),"") -> after | AQ48: =IF(C48="yes",IF(AP48="before",D48-AO48,IF(AP48="after",AO48-D48,IF(AP48="same year",0))),"") -> 10 | AR48: =IF(H48="yes",IF(AO48=I48,"same year",IF(AO48<I48,"before",IF(AO48>I48,"after"))),"") | AS48: =IF(H48="yes",IF(AR48="same year",0,IF(AR48="before",I48-AO48,IF(AR48="after",AO48-I48))),"") | AT48: =IF(R48="yes",IF(AO48<2018,"before",IF(AO48=2018,"same year",IF(AO48>2018,"after"))),"") -> after | AU48: =IF(R48="yes",IF(AT48="before",2018-AO48,IF(AT48="after",AO48-2018,IF(AT48="same year",0))),"") -> 3 | AV48: =IF(F48="defunct",IF(AO48=G48,"same year",IF(AO48<G48,"before",IF(AO48>=G48,"after"))),"") | AW48: =COUNTIF(P48,"=*vuln*") -> 1 | AX48: =COUNTIF(R48,"=yes") -> 1 | AY48: Clairvia (by Cerner) | AZ48: =VLOOKUP(A48,certs!U:V,2,FALSE) -> https://www.cerner.com/legal/compliance
A49: Clearview AI | B49: =VLOOKUP(A49,industry!A:B,2,FALSE) -> Technology | C49: =VLOOKUP(A49,acquisitions!A:D,2,FALSE) -> No | D49: =VLOOKUP(A49,acquisitions!A:D,4,FALSE) -> N/A | E49: =VLOOKUP(A49,acquisitions!A:D,3,FALSE) -> N/A | F49: =VLOOKUP(A49,acquisitions!I:K,2,FALSE) -> Active | G49: =IF(F49="active","",VLOOKUP(A49,acquisitions!I:K,3,FALSE)) | H49: =VLOOKUP(A49,public!A:D,2,FALSE) -> No | I49: =VLOOKUP(A49,public!J:K,2,FALSE) -> #N/A | K49: =VLOOKUP(A49,public!A:D,3,FALSE) -> N/A | L49: =VLOOKUP(A49,public!A:D,4,FALSE) -> N/A | M49: 2020 | N49: 3000000000 | O49: Facial images scraped from the web | P49: Ransomware | Q49: GDPR | R49: yes | AA49: =COUNTIF(O49,"=*personal*")+COUNTIF(O49,"=*ssn*")++COUNTIF(O49,"=*license*")+COUNTIF(O49,"=*email*")+COUNTIF(O49,"=*vehic*")+COUNTIF(O49,"=*profile*")+COUNTIF(O49,"=*account*")+COUNTIF(O49,"=*image*")+COUNTIF(O49,"=*phone*")+COUNTIF(O49,"=*photo*") -> 1 | AB49: =IF(AA49>0,"yes","") -> yes | AC49: =COUNTIF(O49,"=*financ*")+COUNTIF(O49,"=*card*")+COUNTIF(O49,"=*crypto*")+COUNTIF(O49,"=*bank*")+COUNTIF(O49,"=*pay*") -> 0 | AD49: =IF(AC49>0,"yes","") | AE49: =COUNTIF(O49,"=*health*")+COUNTIF(O49,"=*bio*")+COUNTIF(O49,"=*medic*")+COUNTIF(O49,"=*patient*") -> 0 | AF49: =IF(AE49>0,"yes","") | AG49: =COUNTIF(O49,"=*customer*")+COUNTIF(O49,"=*employee*")+COUNTIF(O49,"=*guest*")+COUNTIF(O49,"=*passen*")+COUNTIF(O49,"=*applicant*")+COUNTIF(O49,"=*client*") -> 0 | AH49: =IF(AG49>0,"yes","") | AI49: =COUNTIF(O49,"=*user*")+COUNTIF(O49,"=*code*")+COUNTIF(O49,"=*software*")+COUNTIF(O49,"=*system*")+COUNTIF(O49,"=*text*")+COUNTIF(O49,"=*api*")+COUNTIF(O49,"=*cyber*") -> 0 | AJ49: =IF(AI49>0,"yes","") | AK49: =COUNTIF(O49,"=*not disclosed*") -> 0 | AL49: =IF(AK49>0,"yes","") | AM49: =IF(C49="yes",D49,"") | AN49: =IF(H49="yes",I49,"") | AO49: =M49 -> 2020 | AP49: =IF(C49="yes",IF(AO49=D49,"same year",IF(AO49<D49,"before",IF(AO49>D49,"after"))),"") | AQ49: =IF(C49="yes",IF(AP49="before",D49-AO49,IF(AP49="after",AO49-D49,IF(AP49="same year",0))),"") | AR49: =IF(H49="yes",IF(AO49=I49,"same year",IF(AO49<I49,"before",IF(AO49>I49,"after"))),"") | AS49: =IF(H49="yes",IF(AR49="same year",0,IF(AR49="before",I49-AO49,IF(AR49="after",AO49-I49))),"") | AT49: =IF(R49="yes",IF(AO49<2018,"before",IF(AO49=2018,"same year",IF(AO49>2018,"after"))),"") -> after | AU49: =IF(R49="yes",IF(AT49="before",2018-AO49,IF(AT49="after",AO49-2018,IF(AT49="same year",0))),"") -> 2 | AV49: =IF(F49="defunct",IF(AO49=G49,"same year",IF(AO49<G49,"before",IF(AO49>=G49,"after"))),"") | AW49: =COUNTIF(P49,"=*vuln*") -> 0 | AX49: =COUNTIF(R49,"=yes") -> 1 | AY49: Clearview AI | AZ49: =VLOOKUP(A49,certs!U:V,2,FALSE) -> https://www.clearview.ai/legal/compliance
A50: ClearVoice Surveys | B50: =VLOOKUP(A50,industry!A:B,2,FALSE) -> Marketing | C50: =VLOOKUP(A50,acquisitions!A:D,2,FALSE) -> No | D50: =VLOOKUP(A50,acquisitions!A:D,4,FALSE) -> N/A | E50: =VLOOKUP(A50,acquisitions!A:D,3,FALSE) -> N/A | F50: =VLOOKUP(A50,acquisitions!I:K,2,FALSE) -> Active | G50: =IF(F50="active","",VLOOKUP(A50,acquisitions!I:K,3,FALSE)) | H50: =VLOOKUP(A50,public!A:D,2,FALSE) -> No | I50: =VLOOKUP(A50,public!J:K,2,FALSE) -> #N/A | K50: =VLOOKUP(A50,public!A:D,3,FALSE) -> N/A | L50: =VLOOKUP(A50,public!A:D,4,FALSE) -> N/A | M50: 2020 | N50: 15000000 | O50: Usernames, emails, hashed passwords | P50: Data Scraping | Q50: GDPR | R50: yes | AA50: =COUNTIF(O50,"=*personal*")+COUNTIF(O50,"=*ssn*")++COUNTIF(O50,"=*license*")+COUNTIF(O50,"=*email*")+COUNTIF(O50,"=*vehic*")+COUNTIF(O50,"=*profile*")+COUNTIF(O50,"=*account*")+COUNTIF(O50,"=*image*")+COUNTIF(O50,"=*phone*")+COUNTIF(O50,"=*photo*") -> 1 | AB50: =IF(AA50>0,"yes","") -> yes | AC50: =COUNTIF(O50,"=*financ*")+COUNTIF(O50,"=*card*")+COUNTIF(O50,"=*crypto*")+COUNTIF(O50,"=*bank*")+COUNTIF(O50,"=*pay*") -> 0 | AD50: =IF(AC50>0,"yes","") | AE50: =COUNTIF(O50,"=*health*")+COUNTIF(O50,"=*bio*")+COUNTIF(O50,"=*medic*")+COUNTIF(O50,"=*patient*") -> 0 | AF50: =IF(AE50>0,"yes","") | AG50: =COUNTIF(O50,"=*customer*")+COUNTIF(O50,"=*employee*")+COUNTIF(O50,"=*guest*")+COUNTIF(O50,"=*passen*")+COUNTIF(O50,"=*applicant*")+COUNTIF(O50,"=*client*") -> 0 | AH50: =IF(AG50>0,"yes","") | AI50: =COUNTIF(O50,"=*user*")+COUNTIF(O50,"=*code*")+COUNTIF(O50,"=*software*")+COUNTIF(O50,"=*system*")+COUNTIF(O50,"=*text*")+COUNTIF(O50,"=*api*")+COUNTIF(O50,"=*cyber*") -> 1 | AJ50: =IF(AI50>0,"yes","") -> yes | AK50: =COUNTIF(O50,"=*not disclosed*") -> 0 | AL50: =IF(AK50>0,"yes","") | AM50: =IF(C50="yes",D50,"") | AN50: =IF(H50="yes",I50,"") | AO50: =M50 -> 2020 | AP50: =IF(C50="yes",IF(AO50=D50,"same year",IF(AO50<D50,"before",IF(AO50>D50,"after"))),"") | AQ50: =IF(C50="yes",IF(AP50="before",D50-AO50,IF(AP50="after",AO50-D50,IF(AP50="same year",0))),"") | AR50: =IF(H50="yes",IF(AO50=I50,"same year",IF(AO50<I50,"before",IF(AO50>I50,"after"))),"") | AS50: =IF(H50="yes",IF(AR50="same year",0,IF(AR50="before",I50-AO50,IF(AR50="after",AO50-I50))),"") | AT50: =IF(R50="yes",IF(AO50<2018,"before",IF(AO50=2018,"same year",IF(AO50>2018,"after"))),"") -> after | AU50: =IF(R50="yes",IF(AT50="before",2018-AO50,IF(AT50="after",AO50-2018,IF(AT50="same year",0))),"") -> 2 | AV50: =IF(F50="defunct",IF(AO50=G50,"same year",IF(AO50<G50,"before",IF(AO50>=G50,"after"))),"") | AW50: =COUNTIF(P50,"=*vuln*") -> 0 | AX50: =COUNTIF(R50,"=yes") -> 1 | AY50: ClearVoice Surveys | AZ50: =VLOOKUP(A50,certs!U:V,2,FALSE) -> https://www.clearvoicesurveys.com/legal/compliance
A51: Clubhouse | B51: =VLOOKUP(A51,industry!A:B,2,FALSE) -> Social Media | C51: =VLOOKUP(A51,acquisitions!A:D,2,FALSE) -> No | D51: =VLOOKUP(A51,acquisitions!A:D,4,FALSE) -> N/A | E51: =VLOOKUP(A51,acquisitions!A:D,3,FALSE) -> N/A | F51: =VLOOKUP(A51,acquisitions!I:K,2,FALSE) -> Active | G51: =IF(F51="active","",VLOOKUP(A51,acquisitions!I:K,3,FALSE)) | H51: =VLOOKUP(A51,public!A:D,2,FALSE) -> No | I51: =VLOOKUP(A51,public!J:K,2,FALSE) -> #N/A | K51: =VLOOKUP(A51,public!A:D,3,FALSE) -> N/A | L51: =VLOOKUP(A51,public!A:D,4,FALSE) -> N/A | M51: 2021 | N51: 1300000 | O51: User IDs, names, social media profiles | P51: Data Scraping | Q51: GDPR | R51: yes | AA51: =COUNTIF(O51,"=*personal*")+COUNTIF(O51,"=*ssn*")++COUNTIF(O51,"=*license*")+COUNTIF(O51,"=*email*")+COUNTIF(O51,"=*vehic*")+COUNTIF(O51,"=*profile*")+COUNTIF(O51,"=*account*")+COUNTIF(O51,"=*image*")+COUNTIF(O51,"=*phone*")+COUNTIF(O51,"=*photo*") -> 1 | AB51: =IF(AA51>0,"yes","") -> yes | AC51: =COUNTIF(O51,"=*financ*")+COUNTIF(O51,"=*card*")+COUNTIF(O51,"=*crypto*")+COUNTIF(O51,"=*bank*")+COUNTIF(O51,"=*pay*") -> 0 | AD51: =IF(AC51>0,"yes","") | AE51: =COUNTIF(O51,"=*health*")+COUNTIF(O51,"=*bio*")+COUNTIF(O51,"=*medic*")+COUNTIF(O51,"=*patient*") -> 0 | AF51: =IF(AE51>0,"yes","") | AG51: =COUNTIF(O51,"=*customer*")+COUNTIF(O51,"=*employee*")+COUNTIF(O51,"=*guest*")+COUNTIF(O51,"=*passen*")+COUNTIF(O51,"=*applicant*")+COUNTIF(O51,"=*client*") -> 0 | AH51: =IF(AG51>0,"yes","") | AI51: =COUNTIF(O51,"=*user*")+COUNTIF(O51,"=*code*")+COUNTIF(O51,"=*software*")+COUNTIF(O51,"=*system*")+COUNTIF(O51,"=*text*")+COUNTIF(O51,"=*api*")+COUNTIF(O51,"=*cyber*") -> 1 | AJ51: =IF(AI51>0,"yes","") -> yes | AK51: =COUNTIF(O51,"=*not disclosed*") -> 0 | AL51: =IF(AK51>0,"yes","") | AM51: =IF(C51="yes",D51,"") | AN51: =IF(H51="yes",I51,"") | AO51: =M51 -> 2021 | AP51: =IF(C51="yes",IF(AO51=D51,"same year",IF(AO51<D51,"before",IF(AO51>D51,"after"))),"") | AQ51: =IF(C51="yes",IF(AP51="before",D51-AO51,IF(AP51="after",AO51-D51,IF(AP51="same year",0))),"") | AR51: =IF(H51="yes",IF(AO51=I51,"same year",IF(AO51<I51,"before",IF(AO51>I51,"after"))),"") | AS51: =IF(H51="yes",IF(AR51="same year",0,IF(AR51="before",I51-AO51,IF(AR51="after",AO51-I51))),"") | AT51: =IF(R51="yes",IF(AO51<2018,"before",IF(AO51=2018,"same year",IF(AO51>2018,"after"))),"") -> after | AU51: =IF(R51="yes",IF(AT51="before",2018-AO51,IF(AT51="after",AO51-2018,IF(AT51="same year",0))),"") -> 3 | AV51: =IF(F51="defunct",IF(AO51=G51,"same year",IF(AO51<G51,"before",IF(AO51>=G51,"after"))),"") | AW51: =COUNTIF(P51,"=*vuln*") -> 0 | AX51: =COUNTIF(R51,"=yes") -> 1 | AY51: Clubhouse | AZ51: =VLOOKUP(A51,certs!U:V,2,FALSE) -> https://www.joinclubhouse.com/legal/compliance
A52: Codecov | B52: =VLOOKUP(A52,industry!A:B,2,FALSE) -> Technology | C52: =VLOOKUP(A52,acquisitions!A:D,2,FALSE) -> No | D52: =VLOOKUP(A52,acquisitions!A:D,4,FALSE) -> N/A | E52: =VLOOKUP(A52,acquisitions!A:D,3,FALSE) -> N/A | F52: =VLOOKUP(A52,acquisitions!I:K,2,FALSE) -> Active | G52: =IF(F52="active","",VLOOKUP(A52,acquisitions!I:K,3,FALSE)) | H52: =VLOOKUP(A52,public!A:D,2,FALSE) -> No | I52: =VLOOKUP(A52,public!J:K,2,FALSE) -> #N/A | K52: =VLOOKUP(A52,public!A:D,3,FALSE) -> N/A | L52: =VLOOKUP(A52,public!A:D,4,FALSE) -> N/A | M52: 2021 | N52: Unknown | O52: Customers' environment variables, tokens | P52: Supply Chain Attack | Q52: GDPR | R52: yes | AA52: =COUNTIF(O52,"=*personal*")+COUNTIF(O52,"=*ssn*")++COUNTIF(O52,"=*license*")+COUNTIF(O52,"=*email*")+COUNTIF(O52,"=*vehic*")+COUNTIF(O52,"=*profile*")+COUNTIF(O52,"=*account*")+COUNTIF(O52,"=*image*")+COUNTIF(O52,"=*phone*")+COUNTIF(O52,"=*photo*") -> 0 | AB52: =IF(AA52>0,"yes","") | AC52: =COUNTIF(O52,"=*financ*")+COUNTIF(O52,"=*card*")+COUNTIF(O52,"=*crypto*")+COUNTIF(O52,"=*bank*")+COUNTIF(O52,"=*pay*") -> 0 | AD52: =IF(AC52>0,"yes","") | AE52: =COUNTIF(O52,"=*health*")+COUNTIF(O52,"=*bio*")+COUNTIF(O52,"=*medic*")+COUNTIF(O52,"=*patient*") -> 0 | AF52: =IF(AE52>0,"yes","") | AG52: =COUNTIF(O52,"=*customer*")+COUNTIF(O52,"=*employee*")+COUNTIF(O52,"=*guest*")+COUNTIF(O52,"=*passen*")+COUNTIF(O52,"=*applicant*")+COUNTIF(O52,"=*client*") -> 1 | AH52: =IF(AG52>0,"yes","") -> yes | AI52: =COUNTIF(O52,"=*user*")+COUNTIF(O52,"=*code*")+COUNTIF(O52,"=*software*")+COUNTIF(O52,"=*system*")+COUNTIF(O52,"=*text*")+COUNTIF(O52,"=*api*")+COUNTIF(O52,"=*cyber*") -> 0 | AJ52: =IF(AI52>0,"yes","") | AK52: =COUNTIF(O52,"=*not disclosed*") -> 0 | AL52: =IF(AK52>0,"yes","") | AM52: =IF(C52="yes",D52,"") | AN52: =IF(H52="yes",I52,"") | AO52: =M52 -> 2021 | AP52: =IF(C52="yes",IF(AO52=D52,"same year",IF(AO52<D52,"before",IF(AO52>D52,"after"))),"") | AQ52: =IF(C52="yes",IF(AP52="before",D52-AO52,IF(AP52="after",AO52-D52,IF(AP52="same year",0))),"") | AR52: =IF(H52="yes",IF(AO52=I52,"same year",IF(AO52<I52,"before",IF(AO52>I52,"after"))),"") | AS52: =IF(H52="yes",IF(AR52="same year",0,IF(AR52="before",I52-AO52,IF(AR52="after",AO52-I52))),"") | AT52: =IF(R52="yes",IF(AO52<2018,"before",IF(AO52=2018,"same year",IF(AO52>2018,"after"))),"") -> after | AU52: =IF(R52="yes",IF(AT52="before",2018-AO52,IF(AT52="after",AO52-2018,IF(AT52="same year",0))),"") -> 3 | AV52: =IF(F52="defunct",IF(AO52=G52,"same year",IF(AO52<G52,"before",IF(AO52>=G52,"after"))),"") | AW52: =COUNTIF(P52,"=*vuln*") -> 0 | AX52: =COUNTIF(R52,"=yes") -> 1 | AY52: Codecov | AZ52: =VLOOKUP(A52,certs!U:V,2,FALSE) -> https://www.codecov.io/legal/compliance
A53: Crypto.com | B53: =VLOOKUP(A53,industry!A:B,2,FALSE) -> Financial Technology (FinTech) | C53: =VLOOKUP(A53,acquisitions!A:D,2,FALSE) -> No | D53: =VLOOKUP(A53,acquisitions!A:D,4,FALSE) -> N/A | E53: =VLOOKUP(A53,acquisitions!A:D,3,FALSE) -> N/A | F53: =VLOOKUP(A53,acquisitions!I:K,2,FALSE) -> Active | G53: =IF(F53="active","",VLOOKUP(A53,acquisitions!I:K,3,FALSE)) | H53: =VLOOKUP(A53,public!A:D,2,FALSE) -> No | I53: =VLOOKUP(A53,public!J:K,2,FALSE) -> #N/A | K53: =VLOOKUP(A53,public!A:D,3,FALSE) -> N/A | L53: =VLOOKUP(A53,public!A:D,4,FALSE) -> N/A | M53: 2022 | N53: 483 | O53: Cryptocurrency assets stolen ($34 million) | P53: Two Factor Authentication Exploit | Q53: GDPR | R53: yes | AA53: =COUNTIF(O53,"=*personal*")+COUNTIF(O53,"=*ssn*")++COUNTIF(O53,"=*license*")+COUNTIF(O53,"=*email*")+COUNTIF(O53,"=*vehic*")+COUNTIF(O53,"=*profile*")+COUNTIF(O53,"=*account*")+COUNTIF(O53,"=*image*")+COUNTIF(O53,"=*phone*")+COUNTIF(O53,"=*photo*") -> 0 | AB53: =IF(AA53>0,"yes","") | AC53: =COUNTIF(O53,"=*financ*")+COUNTIF(O53,"=*card*")+COUNTIF(O53,"=*crypto*")+COUNTIF(O53,"=*bank*")+COUNTIF(O53,"=*pay*") -> 1 | AD53: =IF(AC53>0,"yes","") -> yes | AE53: =COUNTIF(O53,"=*health*")+COUNTIF(O53,"=*bio*")+COUNTIF(O53,"=*medic*")+COUNTIF(O53,"=*patient*") -> 0 | AF53: =IF(AE53>0,"yes","") | AG53: =COUNTIF(O53,"=*customer*")+COUNTIF(O53,"=*employee*")+COUNTIF(O53,"=*guest*")+COUNTIF(O53,"=*passen*")+COUNTIF(O53,"=*applicant*")+COUNTIF(O53,"=*client*") -> 0 | AH53: =IF(AG53>0,"yes","") | AI53: =COUNTIF(O53,"=*user*")+COUNTIF(O53,"=*code*")+COUNTIF(O53,"=*software*")+COUNTIF(O53,"=*system*")+COUNTIF(O53,"=*text*")+COUNTIF(O53,"=*api*")+COUNTIF(O53,"=*cyber*") -> 0 | AJ53: =IF(AI53>0,"yes","") | AK53: =COUNTIF(O53,"=*not disclosed*") -> 0 | AL53: =IF(AK53>0,"yes","") | AM53: =IF(C53="yes",D53,"") | AN53: =IF(H53="yes",I53,"") | AO53: =M53 -> 2022 | AP53: =IF(C53="yes",IF(AO53=D53,"same year",IF(AO53<D53,"before",IF(AO53>D53,"after"))),"") | AQ53: =IF(C53="yes",IF(AP53="before",D53-AO53,IF(AP53="after",AO53-D53,IF(AP53="same year",0))),"") | AR53: =IF(H53="yes",IF(AO53=I53,"same year",IF(AO53<I53,"before",IF(AO53>I53,"after"))),"") | AS53: =IF(H53="yes",IF(AR53="same year",0,IF(AR53="before",I53-AO53,IF(AR53="after",AO53-I53))),"") | AT53: =IF(R53="yes",IF(AO53<2018,"before",IF(AO53=2018,"same year",IF(AO53>2018,"after"))),"") -> after | AU53: =IF(R53="yes",IF(AT53="before",2018-AO53,IF(AT53="after",AO53-2018,IF(AT53="same year",0))),"") -> 4 | AV53: =IF(F53="defunct",IF(AO53=G53,"same year",IF(AO53<G53,"before",IF(AO53>=G53,"after"))),"") | AW53: =COUNTIF(P53,"=*vuln*") -> 0 | AX53: =COUNTIF(R53,"=yes") -> 1 | AY53: Crypto.com | AZ53: =VLOOKUP(A53,certs!U:V,2,FALSE) -> https://crypto.com/legal/compliance
A54: Dave.com | B54: =VLOOKUP(A54,industry!A:B,2,FALSE) -> Financial Technology (FinTech) | C54: =VLOOKUP(A54,acquisitions!A:D,2,FALSE) -> No | D54: =VLOOKUP(A54,acquisitions!A:D,4,FALSE) -> N/A | E54: =VLOOKUP(A54,acquisitions!A:D,3,FALSE) -> N/A | F54: =VLOOKUP(A54,acquisitions!I:K,2,FALSE) -> Active | G54: =IF(F54="active","",VLOOKUP(A54,acquisitions!I:K,3,FALSE)) | H54: =VLOOKUP(A54,public!A:D,2,FALSE) -> No | I54: =VLOOKUP(A54,public!J:K,2,FALSE) -> #N/A | K54: =VLOOKUP(A54,public!A:D,3,FALSE) -> N/A | L54: =VLOOKUP(A54,public!A:D,4,FALSE) -> N/A | M54: 2020 | N54: 7500000 | O54: User data, financial details | P54: Phishing | Q54: GDPR | R54: yes | AA54: =COUNTIF(O54,"=*personal*")+COUNTIF(O54,"=*ssn*")++COUNTIF(O54,"=*license*")+COUNTIF(O54,"=*email*")+COUNTIF(O54,"=*vehic*")+COUNTIF(O54,"=*profile*")+COUNTIF(O54,"=*account*")+COUNTIF(O54,"=*image*")+COUNTIF(O54,"=*phone*")+COUNTIF(O54,"=*photo*") -> 0 | AB54: =IF(AA54>0,"yes","") | AC54: =COUNTIF(O54,"=*financ*")+COUNTIF(O54,"=*card*")+COUNTIF(O54,"=*crypto*")+COUNTIF(O54,"=*bank*")+COUNTIF(O54,"=*pay*") -> 1 | AD54: =IF(AC54>0,"yes","") -> yes | AE54: =COUNTIF(O54,"=*health*")+COUNTIF(O54,"=*bio*")+COUNTIF(O54,"=*medic*")+COUNTIF(O54,"=*patient*") -> 0 | AF54: =IF(AE54>0,"yes","") | AG54: =COUNTIF(O54,"=*customer*")+COUNTIF(O54,"=*employee*")+COUNTIF(O54,"=*guest*")+COUNTIF(O54,"=*passen*")+COUNTIF(O54,"=*applicant*")+COUNTIF(O54,"=*client*") -> 0 | AH54: =IF(AG54>0,"yes","") | AI54: =COUNTIF(O54,"=*user*")+COUNTIF(O54,"=*code*")+COUNTIF(O54,"=*software*")+COUNTIF(O54,"=*system*")+COUNTIF(O54,"=*text*")+COUNTIF(O54,"=*api*")+COUNTIF(O54,"=*cyber*") -> 1 | AJ54: =IF(AI54>0,"yes","") -> yes | AK54: =COUNTIF(O54,"=*not disclosed*") -> 0 | AL54: =IF(AK54>0,"yes","") | AM54: =IF(C54="yes",D54,"") | AN54: =IF(H54="yes",I54,"") | AO54: =M54 -> 2020 | AP54: =IF(C54="yes",IF(AO54=D54,"same year",IF(AO54<D54,"before",IF(AO54>D54,"after"))),"") | AQ54: =IF(C54="yes",IF(AP54="before",D54-AO54,IF(AP54="after",AO54-D54,IF(AP54="same year",0))),"") | AR54: =IF(H54="yes",IF(AO54=I54,"same year",IF(AO54<I54,"before",IF(AO54>I54,"after"))),"") | AS54: =IF(H54="yes",IF(AR54="same year",0,IF(AR54="before",I54-AO54,IF(AR54="after",AO54-I54))),"") | AT54: =IF(R54="yes",IF(AO54<2018,"before",IF(AO54=2018,"same year",IF(AO54>2018,"after"))),"") -> after | AU54: =IF(R54="yes",IF(AT54="before",2018-AO54,IF(AT54="after",AO54-2018,IF(AT54="same year",0))),"") -> 2 | AV54: =IF(F54="defunct",IF(AO54=G54,"same year",IF(AO54<G54,"before",IF(AO54>=G54,"after"))),"") | AW54: =COUNTIF(P54,"=*vuln*") -> 0 | AX54: =COUNTIF(R54,"=yes") -> 1 | AY54: Dave.com | AZ54: =VLOOKUP(A54,certs!U:V,2,FALSE) -> https://www.dave.com/legal/compliance
A55: Deep Root Analytics | B55: =VLOOKUP(A55,industry!A:B,2,FALSE) -> Analytics | C55: =VLOOKUP(A55,acquisitions!A:D,2,FALSE) -> No | D55: =VLOOKUP(A55,acquisitions!A:D,4,FALSE) -> N/A | E55: =VLOOKUP(A55,acquisitions!A:D,3,FALSE) -> N/A | F55: =VLOOKUP(A55,acquisitions!I:K,2,FALSE) -> Active | G55: =IF(F55="active","",VLOOKUP(A55,acquisitions!I:K,3,FALSE)) | H55: No | I55: =VLOOKUP(A55,public!J:K,2,FALSE) -> #N/A | K55: N/A | L55: N/A | M55: 2017 | N55: 198000000 | O55: Voter data | P55: Unsecured database | Q55: ISO 27001, SOC 2 Type II, GDPR, CCPA | R55: yes | S55: yes | X55: yes | Y55: yes | AA55: =COUNTIF(O55,"=*personal*")+COUNTIF(O55,"=*ssn*")++COUNTIF(O55,"=*license*")+COUNTIF(O55,"=*email*")+COUNTIF(O55,"=*vehic*")+COUNTIF(O55,"=*profile*")+COUNTIF(O55,"=*account*")+COUNTIF(O55,"=*image*")+COUNTIF(O55,"=*phone*")+COUNTIF(O55,"=*photo*") -> 0 | AB55: =IF(AA55>0,"yes","") | AC55: =COUNTIF(O55,"=*financ*")+COUNTIF(O55,"=*card*")+COUNTIF(O55,"=*crypto*")+COUNTIF(O55,"=*bank*")+COUNTIF(O55,"=*pay*") -> 0 | AD55: =IF(AC55>0,"yes","") | AE55: =COUNTIF(O55,"=*health*")+COUNTIF(O55,"=*bio*")+COUNTIF(O55,"=*medic*")+COUNTIF(O55,"=*patient*") -> 0 | AF55: =IF(AE55>0,"yes","") | AG55: =COUNTIF(O55,"=*customer*")+COUNTIF(O55,"=*employee*")+COUNTIF(O55,"=*guest*")+COUNTIF(O55,"=*passen*")+COUNTIF(O55,"=*applicant*")+COUNTIF(O55,"=*client*") -> 0 | AH55: =IF(AG55>0,"yes","") | AI55: =COUNTIF(O55,"=*user*")+COUNTIF(O55,"=*code*")+COUNTIF(O55,"=*software*")+COUNTIF(O55,"=*system*")+COUNTIF(O55,"=*text*")+COUNTIF(O55,"=*api*")+COUNTIF(O55,"=*cyber*") -> 0 | AJ55: =IF(AI55>0,"yes","") | AK55: =COUNTIF(O55,"=*not disclosed*") -> 0 | AL55: =IF(AK55>0,"yes","") | AM55: =IF(C55="yes",D55,"") | AN55: =IF(H55="yes",I55,"") | AO55: =M55 -> 2017 | AP55: =IF(C55="yes",IF(AO55=D55,"same year",IF(AO55<D55,"before",IF(AO55>D55,"after"))),"") | AQ55: =IF(C55="yes",IF(AP55="before",D55-AO55,IF(AP55="after",AO55-D55,IF(AP55="same year",0))),"") | AR55: =IF(H55="yes",IF(AO55=I55,"same year",IF(AO55<I55,"before",IF(AO55>I55,"after"))),"") | AS55: =IF(H55="yes",IF(AR55="same year",0,IF(AR55="before",I55-AO55,IF(AR55="after",AO55-I55))),"") | AT55: =IF(R55="yes",IF(AO55<2018,"before",IF(AO55=2018,"same year",IF(AO55>2018,"after"))),"") -> before | AU55: =IF(R55="yes",IF(AT55="before",2018-AO55,IF(AT55="after",AO55-2018,IF(AT55="same year",0))),"") -> 1 | AV55: =IF(F55="defunct",IF(AO55=G55,"same year",IF(AO55<G55,"before",IF(AO55>=G55,"after"))),"") | AW55: =COUNTIF(P55,"=*vuln*") -> 0 | AX55: =COUNTIF(R55,"=yes") -> 1 | AY55: Deep Root Analytics | AZ55: =VLOOKUP(A55,certs!U:V,2,FALSE) -> https://www.deeprootanalytics.com/legal/compliance
A56: Deloitte | B56: =VLOOKUP(A56,industry!A:B,2,FALSE) -> Professional Services | C56: =VLOOKUP(A56,acquisitions!A:D,2,FALSE) -> No | D56: =VLOOKUP(A56,acquisitions!A:D,4,FALSE) -> N/A | E56: =VLOOKUP(A56,acquisitions!A:D,3,FALSE) -> N/A | F56: =VLOOKUP(A56,acquisitions!I:K,2,FALSE) -> Active | G56: =IF(F56="active","",VLOOKUP(A56,acquisitions!I:K,3,FALSE)) | H56: No | I56: =VLOOKUP(A56,public!J:K,2,FALSE) -> #N/A | K56: N/A | L56: N/A | M56: 2017 | N56: 350 | O56: Client information, executive details | P56: Phishing | Q56: ISO 27001, SOC 2 Type II, GDPR, CCPA, HIPAA, SOX | R56: yes | S56: yes | U56: yes | W56: yes | X56: yes | Y56: yes | AA56: =COUNTIF(O56,"=*personal*")+COUNTIF(O56,"=*ssn*")++COUNTIF(O56,"=*license*")+COUNTIF(O56,"=*email*")+COUNTIF(O56,"=*vehic*")+COUNTIF(O56,"=*profile*")+COUNTIF(O56,"=*account*")+COUNTIF(O56,"=*image*")+COUNTIF(O56,"=*phone*")+COUNTIF(O56,"=*photo*") -> 0 | AB56: =IF(AA56>0,"yes","") | AC56: =COUNTIF(O56,"=*financ*")+COUNTIF(O56,"=*card*")+COUNTIF(O56,"=*crypto*")+COUNTIF(O56,"=*bank*")+COUNTIF(O56,"=*pay*") -> 0 | AD56: =IF(AC56>0,"yes","") | AE56: =COUNTIF(O56,"=*health*")+COUNTIF(O56,"=*bio*")+COUNTIF(O56,"=*medic*")+COUNTIF(O56,"=*patient*") -> 0 | AF56: =IF(AE56>0,"yes","") | AG56: =COUNTIF(O56,"=*customer*")+COUNTIF(O56,"=*employee*")+COUNTIF(O56,"=*guest*")+COUNTIF(O56,"=*passen*")+COUNTIF(O56,"=*applicant*")+COUNTIF(O56,"=*client*") -> 1 | AH56: =IF(AG56>0,"yes","") -> yes | AI56: =COUNTIF(O56,"=*user*")+COUNTIF(O56,"=*code*")+COUNTIF(O56,"=*software*")+COUNTIF(O56,"=*system*")+COUNTIF(O56,"=*text*")+COUNTIF(O56,"=*api*")+COUNTIF(O56,"=*cyber*") -> 0 | AJ56: =IF(AI56>0,"yes","") | AK56: =COUNTIF(O56,"=*not disclosed*") -> 0 | AL56: =IF(AK56>0,"yes","") | AM56: =IF(C56="yes",D56,"") | AN56: =IF(H56="yes",I56,"") | AO56: =M56 -> 2017 | AP56: =IF(C56="yes",IF(AO56=D56,"same year",IF(AO56<D56,"before",IF(AO56>D56,"after"))),"") | AQ56: =IF(C56="yes",IF(AP56="before",D56-AO56,IF(AP56="after",AO56-D56,IF(AP56="same year",0))),"") | AR56: =IF(H56="yes",IF(AO56=I56,"same year",IF(AO56<I56,"before",IF(AO56>I56,"after"))),"") | AS56: =IF(H56="yes",IF(AR56="same year",0,IF(AR56="before",I56-AO56,IF(AR56="after",AO56-I56))),"") | AT56: =IF(R56="yes",IF(AO56<2018,"before",IF(AO56=2018,"same year",IF(AO56>2018,"after"))),"") -> before | AU56: =IF(R56="yes",IF(AT56="before",2018-AO56,IF(AT56="after",AO56-2018,IF(AT56="same year",0))),"") -> 1 | AV56: =IF(F56="defunct",IF(AO56=G56,"same year",IF(AO56<G56,"before",IF(AO56>=G56,"after"))),"") | AW56: =COUNTIF(P56,"=*vuln*") -> 0 | AX56: =COUNTIF(R56,"=yes") -> 1 | AY56: Deloitte | AZ56: =VLOOKUP(A56,certs!U:V,2,FALSE) -> https://www2.deloitte.com/global/en/pages/risk/articles/compliance.html
A57: Dignity Health Lassen Medical Clinic | B57: =VLOOKUP(A57,industry!A:B,2,FALSE) -> Healthcare | C57: =VLOOKUP(A57,acquisitions!A:D,2,FALSE) -> Yes | D57: =VLOOKUP(A57,acquisitions!A:D,4,FALSE) -> 2019 | E57: =VLOOKUP(A57,acquisitions!A:D,3,FALSE) -> CommonSpirit Health | F57: =VLOOKUP(A57,acquisitions!I:K,2,FALSE) -> Active | G57: =IF(F57="active","",VLOOKUP(A57,acquisitions!I:K,3,FALSE)) | H57: =VLOOKUP(A57,public!A:D,2,FALSE) -> No | I57: =VLOOKUP(A57,public!J:K,2,FALSE) -> #N/A | K57: =VLOOKUP(A57,public!A:D,3,FALSE) -> N/A | L57: =VLOOKUP(A57,public!A:D,4,FALSE) -> N/A | M57: 2024 | N57: 65482 | O57: personal and health | P57: Phishing | Q57: HIPAA, HITECH Act | W57: yes | AA57: =COUNTIF(O57,"=*personal*")+COUNTIF(O57,"=*ssn*")++COUNTIF(O57,"=*license*")+COUNTIF(O57,"=*email*")+COUNTIF(O57,"=*vehic*")+COUNTIF(O57,"=*profile*")+COUNTIF(O57,"=*account*")+COUNTIF(O57,"=*image*")+COUNTIF(O57,"=*phone*")+COUNTIF(O57,"=*photo*") -> 1 | AB57: =IF(AA57>0,"yes","") -> yes | AC57: =COUNTIF(O57,"=*financ*")+COUNTIF(O57,"=*card*")+COUNTIF(O57,"=*crypto*")+COUNTIF(O57,"=*bank*")+COUNTIF(O57,"=*pay*") -> 0 | AD57: =IF(AC57>0,"yes","") | AE57: =COUNTIF(O57,"=*health*")+COUNTIF(O57,"=*bio*")+COUNTIF(O57,"=*medic*")+COUNTIF(O57,"=*patient*") -> 1 | AF57: =IF(AE57>0,"yes","") -> yes | AG57: =COUNTIF(O57,"=*customer*")+COUNTIF(O57,"=*employee*")+COUNTIF(O57,"=*guest*")+COUNTIF(O57,"=*passen*")+COUNTIF(O57,"=*applicant*")+COUNTIF(O57,"=*client*") -> 0 | AH57: =IF(AG57>0,"yes","") | AI57: =COUNTIF(O57,"=*user*")+COUNTIF(O57,"=*code*")+COUNTIF(O57,"=*software*")+COUNTIF(O57,"=*system*")+COUNTIF(O57,"=*text*")+COUNTIF(O57,"=*api*")+COUNTIF(O57,"=*cyber*") -> 0 | AJ57: =IF(AI57>0,"yes","") | AK57: =COUNTIF(O57,"=*not disclosed*") -> 0 | AL57: =IF(AK57>0,"yes","") | AM57: =IF(C57="yes",D57,"") -> 2019 | AN57: =IF(H57="yes",I57,"") | AO57: =M57 -> 2024 | AP57: =IF(C57="yes",IF(AO57=D57,"same year",IF(AO57<D57,"before",IF(AO57>D57,"after"))),"") -> after | AQ57: =IF(C57="yes",IF(AP57="before",D57-AO57,IF(AP57="after",AO57-D57,IF(AP57="same year",0))),"") -> 5 | AR57: =IF(H57="yes",IF(AO57=I57,"same year",IF(AO57<I57,"before",IF(AO57>I57,"after"))),"") | AS57: =IF(H57="yes",IF(AR57="same year",0,IF(AR57="before",I57-AO57,IF(AR57="after",AO57-I57))),"") | AT57: =IF(R57="yes",IF(AO57<2018,"before",IF(AO57=2018,"same year",IF(AO57>2018,"after"))),"") | AU57: =IF(R57="yes",IF(AT57="before",2018-AO57,IF(AT57="after",AO57-2018,IF(AT57="same year",0))),"") | AV57: =IF(F57="defunct",IF(AO57=G57,"same year",IF(AO57<G57,"before",IF(AO57>=G57,"after"))),"") | AW57: =COUNTIF(P57,"=*vuln*") -> 0 | AX57: =COUNTIF(R57,"=yes") -> 0 | AY57: Dignity Health Lassen Medical Clinic | AZ57: =VLOOKUP(A57,certs!U:V,2,FALSE) -> Not Available
A58: DocuSign | B58: =VLOOKUP(A58,industry!A:B,2,FALSE) -> Technology | C58: =VLOOKUP(A58,acquisitions!A:D,2,FALSE) -> No | D58: =VLOOKUP(A58,acquisitions!A:D,4,FALSE) -> N/A | E58: =VLOOKUP(A58,acquisitions!A:D,3,FALSE) -> N/A | F58: =VLOOKUP(A58,acquisitions!I:K,2,FALSE) -> Active | G58: =IF(F58="active","",VLOOKUP(A58,acquisitions!I:K,3,FALSE)) | H58: Yes | I58: =VLOOKUP(A58,public!J:K,2,FALSE) -> 2018 | J58: =VLOOKUP(A58,'net worth'!B:C,2,FALSE) -> 12800000000 | K58: NASDAQ | L58: DOCU | M58: 2017 | N58: 100000000 | O58: Email addresses | P58: Phishing | Q58: ISO 27001, ISO 27017, ISO 27018, PCI DSS, SOC 2 Type II, GDPR, FedRAMP, HIPAA, SOX | R58: yes | S58: yes | T58: yes | U58: yes | W58: yes | X58: yes | Z58: yes | AA58: =COUNTIF(O58,"=*personal*")+COUNTIF(O58,"=*ssn*")++COUNTIF(O58,"=*license*")+COUNTIF(O58,"=*email*")+COUNTIF(O58,"=*vehic*")+COUNTIF(O58,"=*profile*")+COUNTIF(O58,"=*account*")+COUNTIF(O58,"=*image*")+COUNTIF(O58,"=*phone*")+COUNTIF(O58,"=*photo*") -> 1 | AB58: =IF(AA58>0,"yes","") -> yes | AC58: =COUNTIF(O58,"=*financ*")+COUNTIF(O58,"=*card*")+COUNTIF(O58,"=*crypto*")+COUNTIF(O58,"=*bank*")+COUNTIF(O58,"=*pay*") -> 0 | AD58: =IF(AC58>0,"yes","") | AE58: =COUNTIF(O58,"=*health*")+COUNTIF(O58,"=*bio*")+COUNTIF(O58,"=*medic*")+COUNTIF(O58,"=*patient*") -> 0 | AF58: =IF(AE58>0,"yes","") | AG58: =COUNTIF(O58,"=*customer*")+COUNTIF(O58,"=*employee*")+COUNTIF(O58,"=*guest*")+COUNTIF(O58,"=*passen*")+COUNTIF(O58,"=*applicant*")+COUNTIF(O58,"=*client*") -> 0 | AH58: =IF(AG58>0,"yes","") | AI58: =COUNTIF(O58,"=*user*")+COUNTIF(O58,"=*code*")+COUNTIF(O58,"=*software*")+COUNTIF(O58,"=*system*")+COUNTIF(O58,"=*text*")+COUNTIF(O58,"=*api*")+COUNTIF(O58,"=*cyber*") -> 0 | AJ58: =IF(AI58>0,"yes","") | AK58: =COUNTIF(O58,"=*not disclosed*") -> 0 | AL58: =IF(AK58>0,"yes","") | AM58: =IF(C58="yes",D58,"") | AN58: =IF(H58="yes",I58,"") -> 2018 | AO58: =M58 -> 2017 | AP58: =IF(C58="yes",IF(AO58=D58,"same year",IF(AO58<D58,"before",IF(AO58>D58,"after"))),"") | AQ58: =IF(C58="yes",IF(AP58="before",D58-AO58,IF(AP58="after",AO58-D58,IF(AP58="same year",0))),"") | AR58: =IF(H58="yes",IF(AO58=I58,"same year",IF(AO58<I58,"before",IF(AO58>I58,"after"))),"") -> before | AS58: =IF(H58="yes",IF(AR58="same year",0,IF(AR58="before",I58-AO58,IF(AR58="after",AO58-I58))),"") -> 1 | AT58: =IF(R58="yes",IF(AO58<2018,"before",IF(AO58=2018,"same year",IF(AO58>2018,"after"))),"") -> before | AU58: =IF(R58="yes",IF(AT58="before",2018-AO58,IF(AT58="after",AO58-2018,IF(AT58="same year",0))),"") -> 1 | AV58: =IF(F58="defunct",IF(AO58=G58,"same year",IF(AO58<G58,"before",IF(AO58>=G58,"after"))),"") | AW58: =COUNTIF(P58,"=*vuln*") -> 0 | AX58: =COUNTIF(R58,"=yes") -> 1 | AY58: DocuSign | AZ58: =VLOOKUP(A58,certs!U:V,2,FALSE) -> https://www.docusign.com/trust/compliance
A59: DoorDash | B59: =VLOOKUP(A59,industry!A:B,2,FALSE) -> Food Delivery | C59: =VLOOKUP(A59,acquisitions!A:D,2,FALSE) -> No | D59: =VLOOKUP(A59,acquisitions!A:D,4,FALSE) -> N/A | E59: =VLOOKUP(A59,acquisitions!A:D,3,FALSE) -> N/A | F59: =VLOOKUP(A59,acquisitions!I:K,2,FALSE) -> Active | G59: =IF(F59="active","",VLOOKUP(A59,acquisitions!I:K,3,FALSE)) | H59: =VLOOKUP(A59,public!A:D,2,FALSE) -> Yes | I59: =VLOOKUP(A59,public!J:K,2,FALSE) -> 2020 | J59: =VLOOKUP(A59,'net worth'!B:C,2,FALSE) -> 24620000000 | K59: =VLOOKUP(A59,public!A:D,3,FALSE) -> NYSE | L59: =VLOOKUP(A59,public!A:D,4,FALSE) -> DASH | M59: 2019 | N59: 4900000 | O59: User data, driver's license numbers | P59: Data Scraping | Q59: GDPR | R59: yes | AA59: =COUNTIF(O59,"=*personal*")+COUNTIF(O59,"=*ssn*")++COUNTIF(O59,"=*license*")+COUNTIF(O59,"=*email*")+COUNTIF(O59,"=*vehic*")+COUNTIF(O59,"=*profile*")+COUNTIF(O59,"=*account*")+COUNTIF(O59,"=*image*")+COUNTIF(O59,"=*phone*")+COUNTIF(O59,"=*photo*") -> 1 | AB59: =IF(AA59>0,"yes","") -> yes | AC59: =COUNTIF(O59,"=*financ*")+COUNTIF(O59,"=*card*")+COUNTIF(O59,"=*crypto*")+COUNTIF(O59,"=*bank*")+COUNTIF(O59,"=*pay*") -> 0 | AD59: =IF(AC59>0,"yes","") | AE59: =COUNTIF(O59,"=*health*")+COUNTIF(O59,"=*bio*")+COUNTIF(O59,"=*medic*")+COUNTIF(O59,"=*patient*") -> 0 | AF59: =IF(AE59>0,"yes","") | AG59: =COUNTIF(O59,"=*customer*")+COUNTIF(O59,"=*employee*")+COUNTIF(O59,"=*guest*")+COUNTIF(O59,"=*passen*")+COUNTIF(O59,"=*applicant*")+COUNTIF(O59,"=*client*") -> 0 | AH59: =IF(AG59>0,"yes","") | AI59: =COUNTIF(O59,"=*user*")+COUNTIF(O59,"=*code*")+COUNTIF(O59,"=*software*")+COUNTIF(O59,"=*system*")+COUNTIF(O59,"=*text*")+COUNTIF(O59,"=*api*")+COUNTIF(O59,"=*cyber*") -> 1 | AJ59: =IF(AI59>0,"yes","") -> yes | AK59: =COUNTIF(O59,"=*not disclosed*") -> 0 | AL59: =IF(AK59>0,"yes","") | AM59: =IF(C59="yes",D59,"") | AN59: =IF(H59="yes",I59,"") -> 2020 | AO59: =M59 -> 2019 | AP59: =IF(C59="yes",IF(AO59=D59,"same year",IF(AO59<D59,"before",IF(AO59>D59,"after"))),"") | AQ59: =IF(C59="yes",IF(AP59="before",D59-AO59,IF(AP59="after",AO59-D59,IF(AP59="same year",0))),"") | AR59: =IF(H59="yes",IF(AO59=I59,"same year",IF(AO59<I59,"before",IF(AO59>I59,"after"))),"") -> before | AS59: =IF(H59="yes",IF(AR59="same year",0,IF(AR59="before",I59-AO59,IF(AR59="after",AO59-I59))),"") -> 1 | AT59: =IF(R59="yes",IF(AO59<2018,"before",IF(AO59=2018,"same year",IF(AO59>2018,"after"))),"") -> after | AU59: =IF(R59="yes",IF(AT59="before",2018-AO59,IF(AT59="after",AO59-2018,IF(AT59="same year",0))),"") -> 1 | AV59: =IF(F59="defunct",IF(AO59=G59,"same year",IF(AO59<G59,"before",IF(AO59>=G59,"after"))),"") | AW59: =COUNTIF(P59,"=*vuln*") -> 0 | AX59: =COUNTIF(R59,"=yes") -> 1 | AY59: DoorDash | AZ59: =VLOOKUP(A59,certs!U:V,2,FALSE) -> https://www.doordash.com/legal/compliance/
A60: Dr Lal PathLabs | B60: =VLOOKUP(A60,industry!A:B,2,FALSE) -> Healthcare | C60: =VLOOKUP(A60,acquisitions!A:D,2,FALSE) -> No | D60: =VLOOKUP(A60,acquisitions!A:D,4,FALSE) -> N/A | E60: =VLOOKUP(A60,acquisitions!A:D,3,FALSE) -> N/A | F60: =VLOOKUP(A60,acquisitions!I:K,2,FALSE) -> Active | G60: =IF(F60="active","",VLOOKUP(A60,acquisitions!I:K,3,FALSE)) | H60: =VLOOKUP(A60,public!A:D,2,FALSE) -> Yes | I60: =VLOOKUP(A60,public!J:K,2,FALSE) -> 2016 | J60: =VLOOKUP(A60,'net worth'!B:C,2,FALSE) -> 3410000000 | K60: =VLOOKUP(A60,public!A:D,3,FALSE) -> BSE | L60: =VLOOKUP(A60,public!A:D,4,FALSE) -> 539206 | M60: 2020 | N60: Unknown | O60: Patient medical records | P60: Third Party | Q60: GDPR | R60: yes | AA60: =COUNTIF(O60,"=*personal*")+COUNTIF(O60,"=*ssn*")++COUNTIF(O60,"=*license*")+COUNTIF(O60,"=*email*")+COUNTIF(O60,"=*vehic*")+COUNTIF(O60,"=*profile*")+COUNTIF(O60,"=*account*")+COUNTIF(O60,"=*image*")+COUNTIF(O60,"=*phone*")+COUNTIF(O60,"=*photo*") -> 0 | AB60: =IF(AA60>0,"yes","") | AC60: =COUNTIF(O60,"=*financ*")+COUNTIF(O60,"=*card*")+COUNTIF(O60,"=*crypto*")+COUNTIF(O60,"=*bank*")+COUNTIF(O60,"=*pay*") -> 0 | AD60: =IF(AC60>0,"yes","") | AE60: =COUNTIF(O60,"=*health*")+COUNTIF(O60,"=*bio*")+COUNTIF(O60,"=*medic*")+COUNTIF(O60,"=*patient*") -> 2 | AF60: =IF(AE60>0,"yes","") -> yes | AG60: =COUNTIF(O60,"=*customer*")+COUNTIF(O60,"=*employee*")+COUNTIF(O60,"=*guest*")+COUNTIF(O60,"=*passen*")+COUNTIF(O60,"=*applicant*")+COUNTIF(O60,"=*client*") -> 0 | AH60: =IF(AG60>0,"yes","") | AI60: =COUNTIF(O60,"=*user*")+COUNTIF(O60,"=*code*")+COUNTIF(O60,"=*software*")+COUNTIF(O60,"=*system*")+COUNTIF(O60,"=*text*")+COUNTIF(O60,"=*api*")+COUNTIF(O60,"=*cyber*") -> 0 | AJ60: =IF(AI60>0,"yes","") | AK60: =COUNTIF(O60,"=*not disclosed*") -> 0 | AL60: =IF(AK60>0,"yes","") | AM60: =IF(C60="yes",D60,"") | AN60: =IF(H60="yes",I60,"") -> 2016 | AO60: =M60 -> 2020 | AP60: =IF(C60="yes",IF(AO60=D60,"same year",IF(AO60<D60,"before",IF(AO60>D60,"after"))),"") | AQ60: =IF(C60="yes",IF(AP60="before",D60-AO60,IF(AP60="after",AO60-D60,IF(AP60="same year",0))),"") | AR60: =IF(H60="yes",IF(AO60=I60,"same year",IF(AO60<I60,"before",IF(AO60>I60,"after"))),"") -> after | AS60: =IF(H60="yes",IF(AR60="same year",0,IF(AR60="before",I60-AO60,IF(AR60="after",AO60-I60))),"") -> 4 | AT60: =IF(R60="yes",IF(AO60<2018,"before",IF(AO60=2018,"same year",IF(AO60>2018,"after"))),"") -> after | AU60: =IF(R60="yes",IF(AT60="before",2018-AO60,IF(AT60="after",AO60-2018,IF(AT60="same year",0))),"") -> 2 | AV60: =IF(F60="defunct",IF(AO60=G60,"same year",IF(AO60<G60,"before",IF(AO60>=G60,"after"))),"") | AW60: =COUNTIF(P60,"=*vuln*") -> 0 | AX60: =COUNTIF(R60,"=yes") -> 1 | AY60: Dr Lal PathLabs | AZ60: =VLOOKUP(A60,certs!U:V,2,FALSE) -> Not Available
A61: Drizly | B61: =VLOOKUP(A61,industry!A:B,2,FALSE) -> Retail | C61: =VLOOKUP(A61,acquisitions!A:D,2,FALSE) -> Yes | D61: =VLOOKUP(A61,acquisitions!A:D,4,FALSE) -> 2021 | E61: =VLOOKUP(A61,acquisitions!A:D,3,FALSE) -> Uber | F61: =VLOOKUP(A61,acquisitions!I:K,2,FALSE) -> Active | G61: =IF(F61="active","",VLOOKUP(A61,acquisitions!I:K,3,FALSE)) | H61: =VLOOKUP(A61,public!A:D,2,FALSE) -> No | I61: =VLOOKUP(A61,public!J:K,2,FALSE) -> #N/A | K61: =VLOOKUP(A61,public!A:D,3,FALSE) -> N/A | L61: =VLOOKUP(A61,public!A:D,4,FALSE) -> N/A | M61: 2020 | N61: 2500000 | O61: Customer emails, DOB, passwords | P61: Unsecured Database | Q61: GDPR | R61: yes | AA61: =COUNTIF(O61,"=*personal*")+COUNTIF(O61,"=*ssn*")++COUNTIF(O61,"=*license*")+COUNTIF(O61,"=*email*")+COUNTIF(O61,"=*vehic*")+COUNTIF(O61,"=*profile*")+COUNTIF(O61,"=*account*")+COUNTIF(O61,"=*image*")+COUNTIF(O61,"=*phone*")+COUNTIF(O61,"=*photo*") -> 1 | AB61: =IF(AA61>0,"yes","") -> yes | AC61: =COUNTIF(O61,"=*financ*")+COUNTIF(O61,"=*card*")+COUNTIF(O61,"=*crypto*")+COUNTIF(O61,"=*bank*")+COUNTIF(O61,"=*pay*") -> 0 | AD61: =IF(AC61>0,"yes","") | AE61: =COUNTIF(O61,"=*health*")+COUNTIF(O61,"=*bio*")+COUNTIF(O61,"=*medic*")+COUNTIF(O61,"=*patient*") -> 0 | AF61: =IF(AE61>0,"yes","") | AG61: =COUNTIF(O61,"=*customer*")+COUNTIF(O61,"=*employee*")+COUNTIF(O61,"=*guest*")+COUNTIF(O61,"=*passen*")+COUNTIF(O61,"=*applicant*")+COUNTIF(O61,"=*client*") -> 1 | AH61: =IF(AG61>0,"yes","") -> yes | AI61: =COUNTIF(O61,"=*user*")+COUNTIF(O61,"=*code*")+COUNTIF(O61,"=*software*")+COUNTIF(O61,"=*system*")+COUNTIF(O61,"=*text*")+COUNTIF(O61,"=*api*")+COUNTIF(O61,"=*cyber*") -> 0 | AJ61: =IF(AI61>0,"yes","") | AK61: =COUNTIF(O61,"=*not disclosed*") -> 0 | AL61: =IF(AK61>0,"yes","") | AM61: =IF(C61="yes",D61,"") -> 2021 | AN61: =IF(H61="yes",I61,"") | AO61: =M61 -> 2020 | AP61: =IF(C61="yes",IF(AO61=D61,"same year",IF(AO61<D61,"before",IF(AO61>D61,"after"))),"") -> before | AQ61: =IF(C61="yes",IF(AP61="before",D61-AO61,IF(AP61="after",AO61-D61,IF(AP61="same year",0))),"") -> 1 | AR61: =IF(H61="yes",IF(AO61=I61,"same year",IF(AO61<I61,"before",IF(AO61>I61,"after"))),"") | AS61: =IF(H61="yes",IF(AR61="same year",0,IF(AR61="before",I61-AO61,IF(AR61="after",AO61-I61))),"") | AT61: =IF(R61="yes",IF(AO61<2018,"before",IF(AO61=2018,"same year",IF(AO61>2018,"after"))),"") -> after | AU61: =IF(R61="yes",IF(AT61="before",2018-AO61,IF(AT61="after",AO61-2018,IF(AT61="same year",0))),"") -> 2 | AV61: =IF(F61="defunct",IF(AO61=G61,"same year",IF(AO61<G61,"before",IF(AO61>=G61,"after"))),"") | AW61: =COUNTIF(P61,"=*vuln*") -> 0 | AX61: =COUNTIF(R61,"=yes") -> 1 | AY61: Drizly | AZ61: =VLOOKUP(A61,certs!U:V,2,FALSE) -> https://www.drizly.com/about/legal
A62: Dropbox | B62: =VLOOKUP(A62,industry!A:B,2,FALSE) -> Technology | C62: =VLOOKUP(A62,acquisitions!A:D,2,FALSE) -> No | D62: =VLOOKUP(A62,acquisitions!A:D,4,FALSE) -> N/A | E62: =VLOOKUP(A62,acquisitions!A:D,3,FALSE) -> N/A | F62: =VLOOKUP(A62,acquisitions!I:K,2,FALSE) -> Active | G62: =IF(F62="active","",VLOOKUP(A62,acquisitions!I:K,3,FALSE)) | H62: =VLOOKUP(A62,public!A:D,2,FALSE) -> Yes | I62: =VLOOKUP(A62,public!J:K,2,FALSE) -> 2018 | J62: =VLOOKUP(A62,'net worth'!B:C,2,FALSE) -> 10770000000 | K62: =VLOOKUP(A62,public!A:D,3,FALSE) -> NASDAQ | L62: =VLOOKUP(A62,public!A:D,4,FALSE) -> DBX | M62: 2022 | N62: 130 | O62: Source code repositories via phishing attack | P62: Phishing | Q62: GDPR | R62: yes | AA62: =COUNTIF(O62,"=*personal*")+COUNTIF(O62,"=*ssn*")++COUNTIF(O62,"=*license*")+COUNTIF(O62,"=*email*")+COUNTIF(O62,"=*vehic*")+COUNTIF(O62,"=*profile*")+COUNTIF(O62,"=*account*")+COUNTIF(O62,"=*image*")+COUNTIF(O62,"=*phone*")+COUNTIF(O62,"=*photo*") -> 0 | AB62: =IF(AA62>0,"yes","") | AC62: =COUNTIF(O62,"=*financ*")+COUNTIF(O62,"=*card*")+COUNTIF(O62,"=*crypto*")+COUNTIF(O62,"=*bank*")+COUNTIF(O62,"=*pay*") -> 0 | AD62: =IF(AC62>0,"yes","") | AE62: =COUNTIF(O62,"=*health*")+COUNTIF(O62,"=*bio*")+COUNTIF(O62,"=*medic*")+COUNTIF(O62,"=*patient*") -> 0 | AF62: =IF(AE62>0,"yes","") | AG62: =COUNTIF(O62,"=*customer*")+COUNTIF(O62,"=*employee*")+COUNTIF(O62,"=*guest*")+COUNTIF(O62,"=*passen*")+COUNTIF(O62,"=*applicant*")+COUNTIF(O62,"=*client*") -> 0 | AH62: =IF(AG62>0,"yes","") | AI62: =COUNTIF(O62,"=*user*")+COUNTIF(O62,"=*code*")+COUNTIF(O62,"=*software*")+COUNTIF(O62,"=*system*")+COUNTIF(O62,"=*text*")+COUNTIF(O62,"=*api*")+COUNTIF(O62,"=*cyber*") -> 1 | AJ62: =IF(AI62>0,"yes","") -> yes | AK62: =COUNTIF(O62,"=*not disclosed*") -> 0 | AL62: =IF(AK62>0,"yes","") | AM62: =IF(C62="yes",D62,"") | AN62: =IF(H62="yes",I62,"") -> 2018 | AO62: =M62 -> 2022 | AP62: =IF(C62="yes",IF(AO62=D62,"same year",IF(AO62<D62,"before",IF(AO62>D62,"after"))),"") | AQ62: =IF(C62="yes",IF(AP62="before",D62-AO62,IF(AP62="after",AO62-D62,IF(AP62="same year",0))),"") | AR62: =IF(H62="yes",IF(AO62=I62,"same year",IF(AO62<I62,"before",IF(AO62>I62,"after"))),"") -> after | AS62: =IF(H62="yes",IF(AR62="same year",0,IF(AR62="before",I62-AO62,IF(AR62="after",AO62-I62))),"") -> 4 | AT62: =IF(R62="yes",IF(AO62<2018,"before",IF(AO62=2018,"same year",IF(AO62>2018,"after"))),"") -> after | AU62: =IF(R62="yes",IF(AT62="before",2018-AO62,IF(AT62="after",AO62-2018,IF(AT62="same year",0))),"") -> 4 | AV62: =IF(F62="defunct",IF(AO62=G62,"same year",IF(AO62<G62,"before",IF(AO62>=G62,"after"))),"") | AW62: =COUNTIF(P62,"=*vuln*") -> 0 | AX62: =COUNTIF(R62,"=yes") -> 1 | AY62: Dropbox | AZ62: =VLOOKUP(A62,certs!U:V,2,FALSE) -> https://www.dropbox.com/compliance
A63: Dubsmash | B63: =VLOOKUP(A63,industry!A:B,2,FALSE) -> Social Media | C63: =VLOOKUP(A63,acquisitions!A:D,2,FALSE) -> Yes | D63: =VLOOKUP(A63,acquisitions!A:D,4,FALSE) -> 2020 | E63: =VLOOKUP(A63,acquisitions!A:D,3,FALSE) -> Reddit | F63: =VLOOKUP(A63,acquisitions!I:K,2,FALSE) -> Active | G63: =IF(F63="active","",VLOOKUP(A63,acquisitions!I:K,3,FALSE)) | H63: =VLOOKUP(A63,public!A:D,2,FALSE) -> No | I63: =VLOOKUP(A63,public!J:K,2,FALSE) -> #N/A | K63: =VLOOKUP(A63,public!A:D,3,FALSE) -> N/A | L63: =VLOOKUP(A63,public!A:D,4,FALSE) -> N/A | M63: 2019 | N63: 162000000 | O63: User accounts, personal data | P63: Third Party | Q63: GDPR | R63: yes | AA63: =COUNTIF(O63,"=*personal*")+COUNTIF(O63,"=*ssn*")++COUNTIF(O63,"=*license*")+COUNTIF(O63,"=*email*")+COUNTIF(O63,"=*vehic*")+COUNTIF(O63,"=*profile*")+COUNTIF(O63,"=*account*")+COUNTIF(O63,"=*image*")+COUNTIF(O63,"=*phone*")+COUNTIF(O63,"=*photo*") -> 2 | AB63: =IF(AA63>0,"yes","") -> yes | AC63: =COUNTIF(O63,"=*financ*")+COUNTIF(O63,"=*card*")+COUNTIF(O63,"=*crypto*")+COUNTIF(O63,"=*bank*")+COUNTIF(O63,"=*pay*") -> 0 | AD63: =IF(AC63>0,"yes","") | AE63: =COUNTIF(O63,"=*health*")+COUNTIF(O63,"=*bio*")+COUNTIF(O63,"=*medic*")+COUNTIF(O63,"=*patient*") -> 0 | AF63: =IF(AE63>0,"yes","") | AG63: =COUNTIF(O63,"=*customer*")+COUNTIF(O63,"=*employee*")+COUNTIF(O63,"=*guest*")+COUNTIF(O63,"=*passen*")+COUNTIF(O63,"=*applicant*")+COUNTIF(O63,"=*client*") -> 0 | AH63: =IF(AG63>0,"yes","") | AI63: =COUNTIF(O63,"=*user*")+COUNTIF(O63,"=*code*")+COUNTIF(O63,"=*software*")+COUNTIF(O63,"=*system*")+COUNTIF(O63,"=*text*")+COUNTIF(O63,"=*api*")+COUNTIF(O63,"=*cyber*") -> 1 | AJ63: =IF(AI63>0,"yes","") -> yes | AK63: =COUNTIF(O63,"=*not disclosed*") -> 0 | AL63: =IF(AK63>0,"yes","") | AM63: =IF(C63="yes",D63,"") -> 2020 | AN63: =IF(H63="yes",I63,"") | AO63: =M63 -> 2019 | AP63: =IF(C63="yes",IF(AO63=D63,"same year",IF(AO63<D63,"before",IF(AO63>D63,"after"))),"") -> before | AQ63: =IF(C63="yes",IF(AP63="before",D63-AO63,IF(AP63="after",AO63-D63,IF(AP63="same year",0))),"") -> 1 | AR63: =IF(H63="yes",IF(AO63=I63,"same year",IF(AO63<I63,"before",IF(AO63>I63,"after"))),"") | AS63: =IF(H63="yes",IF(AR63="same year",0,IF(AR63="before",I63-AO63,IF(AR63="after",AO63-I63))),"") | AT63: =IF(R63="yes",IF(AO63<2018,"before",IF(AO63=2018,"same year",IF(AO63>2018,"after"))),"") -> after | AU63: =IF(R63="yes",IF(AT63="before",2018-AO63,IF(AT63="after",AO63-2018,IF(AT63="same year",0))),"") -> 1 | AV63: =IF(F63="defunct",IF(AO63=G63,"same year",IF(AO63<G63,"before",IF(AO63>=G63,"after"))),"") | AW63: =COUNTIF(P63,"=*vuln*") -> 0 | AX63: =COUNTIF(R63,"=yes") -> 1 | AY63: Dubsmash | AZ63: =VLOOKUP(A63,certs!U:V,2,FALSE) -> Not Available
A64: EasyJet | B64: =VLOOKUP(A64,industry!A:B,2,FALSE) -> Airlines | C64: =VLOOKUP(A64,acquisitions!A:D,2,FALSE) -> No | D64: =VLOOKUP(A64,acquisitions!A:D,4,FALSE) -> N/A | E64: =VLOOKUP(A64,acquisitions!A:D,3,FALSE) -> N/A | F64: =VLOOKUP(A64,acquisitions!I:K,2,FALSE) -> Active | G64: =IF(F64="active","",VLOOKUP(A64,acquisitions!I:K,3,FALSE)) | H64: =VLOOKUP(A64,public!A:D,2,FALSE) -> Yes | I64: =VLOOKUP(A64,public!J:K,2,FALSE) -> 2000 | J64: =VLOOKUP(A64,'net worth'!B:C,2,FALSE) -> 5120000000 | K64: =VLOOKUP(A64,public!A:D,3,FALSE) -> LSE | L64: =VLOOKUP(A64,public!A:D,4,FALSE) -> EZJ | M64: 2020 | N64: 9000000 | O64: Customer emails, travel details | P64: System Vulnerability Exploit | Q64: GDPR | R64: yes | AA64: =COUNTIF(O64,"=*personal*")+COUNTIF(O64,"=*ssn*")++COUNTIF(O64,"=*license*")+COUNTIF(O64,"=*email*")+COUNTIF(O64,"=*vehic*")+COUNTIF(O64,"=*profile*")+COUNTIF(O64,"=*account*")+COUNTIF(O64,"=*image*")+COUNTIF(O64,"=*phone*")+COUNTIF(O64,"=*photo*") -> 1 | AB64: =IF(AA64>0,"yes","") -> yes | AC64: =COUNTIF(O64,"=*financ*")+COUNTIF(O64,"=*card*")+COUNTIF(O64,"=*crypto*")+COUNTIF(O64,"=*bank*")+COUNTIF(O64,"=*pay*") -> 0 | AD64: =IF(AC64>0,"yes","") | AE64: =COUNTIF(O64,"=*health*")+COUNTIF(O64,"=*bio*")+COUNTIF(O64,"=*medic*")+COUNTIF(O64,"=*patient*") -> 0 | AF64: =IF(AE64>0,"yes","") | AG64: =COUNTIF(O64,"=*customer*")+COUNTIF(O64,"=*employee*")+COUNTIF(O64,"=*guest*")+COUNTIF(O64,"=*passen*")+COUNTIF(O64,"=*applicant*")+COUNTIF(O64,"=*client*") -> 1 | AH64: =IF(AG64>0,"yes","") -> yes | AI64: =COUNTIF(O64,"=*user*")+COUNTIF(O64,"=*code*")+COUNTIF(O64,"=*software*")+COUNTIF(O64,"=*system*")+COUNTIF(O64,"=*text*")+COUNTIF(O64,"=*api*")+COUNTIF(O64,"=*cyber*") -> 0 | AJ64: =IF(AI64>0,"yes","") | AK64: =COUNTIF(O64,"=*not disclosed*") -> 0 | AL64: =IF(AK64>0,"yes","") | AM64: =IF(C64="yes",D64,"") | AN64: =IF(H64="yes",I64,"") -> 2000 | AO64: =M64 -> 2020 | AP64: =IF(C64="yes",IF(AO64=D64,"same year",IF(AO64<D64,"before",IF(AO64>D64,"after"))),"") | AQ64: =IF(C64="yes",IF(AP64="before",D64-AO64,IF(AP64="after",AO64-D64,IF(AP64="same year",0))),"") | AR64: =IF(H64="yes",IF(AO64=I64,"same year",IF(AO64<I64,"before",IF(AO64>I64,"after"))),"") -> after | AS64: =IF(H64="yes",IF(AR64="same year",0,IF(AR64="before",I64-AO64,IF(AR64="after",AO64-I64))),"") -> 20 | AT64: =IF(R64="yes",IF(AO64<2018,"before",IF(AO64=2018,"same year",IF(AO64>2018,"after"))),"") -> after | AU64: =IF(R64="yes",IF(AT64="before",2018-AO64,IF(AT64="after",AO64-2018,IF(AT64="same year",0))),"") -> 2 | AV64: =IF(F64="defunct",IF(AO64=G64,"same year",IF(AO64<G64,"before",IF(AO64>=G64,"after"))),"") | AW64: =COUNTIF(P64,"=*vuln*") -> 1 | AX64: =COUNTIF(R64,"=yes") -> 1 | AY64: EasyJet | AZ64: =VLOOKUP(A64,certs!U:V,2,FALSE) -> https://www.easyjet.com/en/terms-and-conditions
A65: Edmodo | B65: =VLOOKUP(A65,industry!A:B,2,FALSE) -> Technology | C65: =VLOOKUP(A65,acquisitions!A:D,2,FALSE) -> No | D65: =VLOOKUP(A65,acquisitions!A:D,4,FALSE) -> N/A | E65: =VLOOKUP(A65,acquisitions!A:D,3,FALSE) -> N/A | F65: =VLOOKUP(A65,acquisitions!I:K,2,FALSE) -> Active | G65: =IF(F65="active","",VLOOKUP(A65,acquisitions!I:K,3,FALSE)) | H65: No | I65: =VLOOKUP(A65,public!J:K,2,FALSE) -> #N/A | K65: N/A | L65: N/A | M65: 2017 | N65: 77000000 | O65: Usernames, email addresses, passwords | P65: Third Party | Q65: ISO 27001, SOC 2 Type II, GDPR, COPPA, FERPA | R65: yes | S65: yes | X65: yes | AA65: =COUNTIF(O65,"=*personal*")+COUNTIF(O65,"=*ssn*")++COUNTIF(O65,"=*license*")+COUNTIF(O65,"=*email*")+COUNTIF(O65,"=*vehic*")+COUNTIF(O65,"=*profile*")+COUNTIF(O65,"=*account*")+COUNTIF(O65,"=*image*")+COUNTIF(O65,"=*phone*")+COUNTIF(O65,"=*photo*") -> 1 | AB65: =IF(AA65>0,"yes","") -> yes | AC65: =COUNTIF(O65,"=*financ*")+COUNTIF(O65,"=*card*")+COUNTIF(O65,"=*crypto*")+COUNTIF(O65,"=*bank*")+COUNTIF(O65,"=*pay*") -> 0 | AD65: =IF(AC65>0,"yes","") | AE65: =COUNTIF(O65,"=*health*")+COUNTIF(O65,"=*bio*")+COUNTIF(O65,"=*medic*")+COUNTIF(O65,"=*patient*") -> 0 | AF65: =IF(AE65>0,"yes","") | AG65: =COUNTIF(O65,"=*customer*")+COUNTIF(O65,"=*employee*")+COUNTIF(O65,"=*guest*")+COUNTIF(O65,"=*passen*")+COUNTIF(O65,"=*applicant*")+COUNTIF(O65,"=*client*") -> 0 | AH65: =IF(AG65>0,"yes","") | AI65: =COUNTIF(O65,"=*user*")+COUNTIF(O65,"=*code*")+COUNTIF(O65,"=*software*")+COUNTIF(O65,"=*system*")+COUNTIF(O65,"=*text*")+COUNTIF(O65,"=*api*")+COUNTIF(O65,"=*cyber*") -> 1 | AJ65: =IF(AI65>0,"yes","") -> yes | AK65: =COUNTIF(O65,"=*not disclosed*") -> 0 | AL65: =IF(AK65>0,"yes","") | AM65: =IF(C65="yes",D65,"") | AN65: =IF(H65="yes",I65,"") | AO65: =M65 -> 2017 | AP65: =IF(C65="yes",IF(AO65=D65,"same year",IF(AO65<D65,"before",IF(AO65>D65,"after"))),"") | AQ65: =IF(C65="yes",IF(AP65="before",D65-AO65,IF(AP65="after",AO65-D65,IF(AP65="same year",0))),"") | AR65: =IF(H65="yes",IF(AO65=I65,"same year",IF(AO65<I65,"before",IF(AO65>I65,"after"))),"") | AS65: =IF(H65="yes",IF(AR65="same year",0,IF(AR65="before",I65-AO65,IF(AR65="after",AO65-I65))),"") | AT65: =IF(R65="yes",IF(AO65<2018,"before",IF(AO65=2018,"same year",IF(AO65>2018,"after"))),"") -> before | AU65: =IF(R65="yes",IF(AT65="before",2018-AO65,IF(AT65="after",AO65-2018,IF(AT65="same year",0))),"") -> 1 | AV65: =IF(F65="defunct",IF(AO65=G65,"same year",IF(AO65<G65,"before",IF(AO65>=G65,"after"))),"") | AW65: =COUNTIF(P65,"=*vuln*") -> 0 | AX65: =COUNTIF(R65,"=yes") -> 1 | AY65: Edmodo | AZ65: =VLOOKUP(A65,certs!U:V,2,FALSE) -> Not Available
